Workbook

Sheet 1 QZ JUNHO
N4: 0.6
H5: =SUBTOTAL(9,H7:H343) -> 0 | I5: =SUBTOTAL(9,I7:I343) -> 9122.95 | J5: =SUBTOTAL(9,J7:J343) -> 1500 | K5: =SUBTOTAL(9,K7:K343) -> 17.1 | L5: =SUBTOTAL(9,L7:L343) -> 0 | M5: =SUBTOTAL(9,M7:M343) -> -7640.05 | N5: =SUBTOTAL(9,N7:N343) -> 0 | O5: =SUBTOTAL(9,O7:O393) -> 0
A6: COLABORADOR | B6: CPF | C6: SITUAÇÃO | D6: REGIONAL | E6: CENTRO DE CUSTO | F6: GESTOR | G6: DIRETOR | H6: SALDO REEMBOLSAR | I6: SALDO FINAL | J6: 1ª QZ | K6: SALDO CARTAO | L6: Adiantamento | M6: CARGA PARCIAL | N6: REEMBOLSO | O6: Carga Final | P6: obs | Q6: STATUS DO CARTÃO
A7: ABNER ANDRADE CAVALCANTE | B7: 02027745203 | C7: ATIVO | D7: REGIONAL CO | E7: CEF AM AC RR | F7: ANGELICA SOARES | G7: ROGERIO SCATAMBULO | H7: 227.55 | I7: 0 | J7: 9840 | K7: 5 | M7: =Tabela1[[#This Row],[1ª QZ]]-Tabela1[[#This Row],[SALDO FINAL]]-Tabela1[[#This Row],[SALDO CARTAO]]-Tabela1[[#This Row],[Adiantamento ]] -> 9835 | N7: =Tabela1[[#This Row],[SALDO REEMBOLSAR]]*$N$4 -> 136.53 | O7: 9948.775 | Q7: =_xlfn.XLOOKUP(Tabela1[[#This Row],[COLABORADOR]],'STATUS CARTAO'!D:D,'STATUS CARTAO'!G:G) -> Cartão ativo
A8: ADAN LEONARDO SOUZA BATISTA | B8: 01932662537 | C8: ATIVO | D8: REGIONAL NE | E8: TELEFONICA BA | F8: GERSON OLIVEIRA | G8: ROGERIO SCATAMBULO | H8: 0 | I8: 601.41 | J8: 1000 | K8: 3 | M8: =Tabela1[[#This Row],[1ª QZ]]-Tabela1[[#This Row],[SALDO FINAL]]-Tabela1[[#This Row],[SALDO CARTAO]]-Tabela1[[#This Row],[Adiantamento ]] -> 395.59 | N8: =Tabela1[[#This Row],[SALDO REEMBOLSAR]]*$N$4 -> 0 | O8: 395.59 | Q8: =_xlfn.XLOOKUP(Tabela1[[#This Row],[COLABORADOR]],'STATUS CARTAO'!D:D,'STATUS CARTAO'!G:G) -> Cartão ativo
A9: ADAUTO JOSE PEREIRA | B9: 85087572634 | C9: ATIVO | D9: REGIONAL MG | E9: CEF FACILITIES BH | F9: HUGO ALEXANDRE | G9: MARCOS CARIAS | H9: 0 | I9: 116.83 | J9: 500 | K9: 1.1 | M9: =Tabela1[[#This Row],[1ª QZ]]-Tabela1[[#This Row],[SALDO FINAL]]-Tabela1[[#This Row],[SALDO CARTAO]]-Tabela1[[#This Row],[Adiantamento ]] -> 382.07 | N9: =Tabela1[[#This Row],[SALDO REEMBOLSAR]]*$N$4 -> 0 | O9: 382.07 | Q9: =_xlfn.XLOOKUP(Tabela1[[#This Row],[COLABORADOR]],'STATUS CARTAO'!D:D,'STATUS CARTAO'!G:G) -> Cartão ativo
A10: ADEMARCIO DUARTE LOPES | B10: 06223031980 | C10: ATIVO | D10: REGIONAL SC | E10: CEF FACILITIES CURITIBA PR | F10: LEANDRO MARCUSSO | G10: EVERSON GAIDSTIECHI | H10: 0 | I10: 1963.08 | J10: 2000 | K10: 2567.13 | M10: =Tabela1[[#This Row],[1ª QZ]]-Tabela1[[#This Row],[SALDO FINAL]]-Tabela1[[#This Row],[SALDO CARTAO]]-Tabela1[[#This Row],[Adiantamento ]] -> -2530.21 | N10: =Tabela1[[#This Row],[SALDO REEMBOLSAR]]*$N$4 -> 0 | O10: 0 | Q10: =_xlfn.XLOOKUP(Tabela1[[#This Row],[COLABORADOR]],'STATUS CARTAO'!D:D,'STATUS CARTAO'!G:G) -> Cartão ativo
A11: ADILSON MELLO DE CAMARGO | B11: 67324398049 | C11: ATIVO | D11: REGIONAL RS | E11: BB SERET RS | F11: ALEXANDRE GROSS | G11: EVERSON GAIDSTIECHI | H11: 0 | I11: 759.37 | J11: 800 | K11: 43 | M11: =Tabela1[[#This Row],[1ª QZ]]-Tabela1[[#This Row],[SALDO FINAL]]-Tabela1[[#This Row],[SALDO CARTAO]]-Tabela1[[#This Row],[Adiantamento ]] -> -2.37 | N11: =Tabela1[[#This Row],[SALDO REEMBOLSAR]]*$N$4 -> 0 | O11: 0 | Q11: =_xlfn.XLOOKUP(Tabela1[[#This Row],[COLABORADOR]],'STATUS CARTAO'!D:D,'STATUS CARTAO'!G:G) -> Cartão ativo
A12: ADIVAR ANTONIO DA SILVA JUNIOR | B12: 28604876898 | C12: ATIVO | D12: REGIONAL CLARO INFRA SUL | E12: CLARO INFRA SC | F12: BRUNO EDUARDO | G12: EVERSON GAIDSTIECHI | H12: 0 | I12: 342.63 | J12: 160 | K12: 48.2 | M12: =Tabela1[[#This Row],[1ª QZ]]-Tabela1[[#This Row],[SALDO FINAL]]-Tabela1[[#This Row],[SALDO CARTAO]]-Tabela1[[#This Row],[Adiantamento ]] -> -230.83 | N12: =Tabela1[[#This Row],[SALDO REEMBOLSAR]]*$N$4 -> 0 | O12: 0 | Q12: =_xlfn.XLOOKUP(Tabela1[[#This Row],[COLABORADOR]],'STATUS CARTAO'!D:D,'STATUS CARTAO'!G:G) -> Cartão ativo
A13: ADMILSON DOS SANTOS GALAN | B13: 04769973993 | C13: ATIVO | D13: REGIONAL SC | E13: CEF NORTE SC | F13: LEANDRO MARCUSSO | G13: EVERSON GAIDSTIECHI | H13: 0 | I13: 617.35 | J13: 1680 | K13: 8.58 | M13: =Tabela1[[#This Row],[1ª QZ]]-Tabela1[[#This Row],[SALDO FINAL]]-Tabela1[[#This Row],[SALDO CARTAO]]-Tabela1[[#This Row],[Adiantamento ]] -> 1054.07 | N13: =Tabela1[[#This Row],[SALDO REEMBOLSAR]]*$N$4 -> 0 | O13: 1054.07 | Q13: =_xlfn.XLOOKUP(Tabela1[[#This Row],[COLABORADOR]],'STATUS CARTAO'!D:D,'STATUS CARTAO'!G:G) -> Cartão ativo
A14: ADRIANO FRANCISCO DE PAULA | B14: 08813588607 | C14: ATIVO | D14: REGIONAL MG | E14: CLARO INFRA MG | F14: HUGO ALEXANDRE | G14: MARCOS CARIAS | H14: 0 | I14: 480.58 | J14: 400 | K14: 90.58 | M14: =Tabela1[[#This Row],[1ª QZ]]-Tabela1[[#This Row],[SALDO FINAL]]-Tabela1[[#This Row],[SALDO CARTAO]]-Tabela1[[#This Row],[Adiantamento ]] -> -171.16 | N14: =Tabela1[[#This Row],[SALDO REEMBOLSAR]]*$N$4 -> 0 | O14: 0 | Q14: =_xlfn.XLOOKUP(Tabela1[[#This Row],[COLABORADOR]],'STATUS CARTAO'!D:D,'STATUS CARTAO'!G:G) -> Cartão ativo
A15: ADSON ARAUJO DA SILVA | B15: 94551804304 | C15: ATIVO | D15: REGIONAL CLARO INFRA NORDESTE | E15: CLARO INFRA NORDESTE | F15: FELIPE JOSE | G15: ROGERIO SCATAMBULO | H15: 796.12 | I15: 0 | J15: 1600 | K15: 6 | M15: =Tabela1[[#This Row],[1ª QZ]]-Tabela1[[#This Row],[SALDO FINAL]]-Tabela1[[#This Row],[SALDO CARTAO]]-Tabela1[[#This Row],[Adiantamento ]] -> 1594 | N15: =Tabela1[[#This Row],[SALDO REEMBOLSAR]]*$N$4 -> 477.672 | O15: 1992.06 | Q15: =_xlfn.XLOOKUP(Tabela1[[#This Row],[COLABORADOR]],'STATUS CARTAO'!D:D,'STATUS CARTAO'!G:G) -> Cartão ativo
A16: ADSON SANTOS DA SILVA | B16: 83058133553 | C16: ATIVO | D16: REGIONAL NE | E16: TELEFONICA BA | F16: GERSON OLIVEIRA | G16: ROGERIO SCATAMBULO | H16: 0 | I16: 1978 | J16: 2000 | K16: 5.51 | M16: =Tabela1[[#This Row],[1ª QZ]]-Tabela1[[#This Row],[SALDO FINAL]]-Tabela1[[#This Row],[SALDO CARTAO]]-Tabela1[[#This Row],[Adiantamento ]] -> 16.49 | N16: =Tabela1[[#This Row],[SALDO REEMBOLSAR]]*$N$4 -> 0 | O16: 16.49 | Q16: =_xlfn.XLOOKUP(Tabela1[[#This Row],[COLABORADOR]],'STATUS CARTAO'!D:D,'STATUS CARTAO'!G:G) -> Cartão ativo
A17: AGNO CHRISTIAN DE LIMA TELES | B17: 06911519624 | C17: ATIVO | D17: REGIONAL MG | E17: CLARO INFRA MG | F17: HUGO ALEXANDRE | G17: MARCOS CARIAS | H17: 686.33 | I17: 0 | J17: 1000 | K17: 6.5 | M17: =Tabela1[[#This Row],[1ª QZ]]-Tabela1[[#This Row],[SALDO FINAL]]-Tabela1[[#This Row],[SALDO CARTAO]]-Tabela1[[#This Row],[Adiantamento ]] -> 993.5 | N17: =Tabela1[[#This Row],[SALDO REEMBOLSAR]]*$N$4 -> 411.798 | O17: 1336.665 | Q17: =_xlfn.XLOOKUP(Tabela1[[#This Row],[COLABORADOR]],'STATUS CARTAO'!D:D,'STATUS CARTAO'!G:G) -> Cartão ativo
A18: ALAERTE JACINTO JUNIOR | B18: 03071605994 | C18: ATIVO | D18: REGIONAL SC | E18: PTB AREAS VERDES SC | F18: LEANDRO MARCUSSO | G18: EVERSON GAIDSTIECHI | H18: 0 | I18: 351.32 | J18: 350 | K18: 31.32 | M18: =Tabela1[[#This Row],[1ª QZ]]-Tabela1[[#This Row],[SALDO FINAL]]-Tabela1[[#This Row],[SALDO CARTAO]]-Tabela1[[#This Row],[Adiantamento ]] -> -32.64 | N18: =Tabela1[[#This Row],[SALDO REEMBOLSAR]]*$N$4 -> 0 | O18: 0 | Q18: =_xlfn.XLOOKUP(Tabela1[[#This Row],[COLABORADOR]],'STATUS CARTAO'!D:D,'STATUS CARTAO'!G:G) -> Cartão ativo
... A31: ANDERSON RICARDO VIEIRA | B31: 07822591975 | C31: ATIVO | D31: REGIONAL SC | E31: BB NORTE OESTE PR | F31: LEANDRO MARCUSSO | G31: EVERSON GAIDSTIECHI | H31: 0 | I31: 0 | J31: 500 | K31: 0 | M31: =Tabela1[[#This Row],[1ª QZ]]-Tabela1[[#This Row],[SALDO FINAL]]-Tabela1[[#This Row],[SALDO CARTAO]]-Tabela1[[#This Row],[Adiantamento ]] -> 500 | N31: =Tabela1[[#This Row],[SALDO REEMBOLSAR]]*$N$4 -> 0 | O31: 500 | Q31: =_xlfn.XLOOKUP(Tabela1[[#This Row],[COLABORADOR]],'STATUS CARTAO'!D:D,'STATUS CARTAO'!G:G) -> Cartão ativo
A32: ANDRE ARANHA MEISTER | B32: 03032275326 | C32: ATIVO | D32: REGIONAL CO | E32: BB MARANHAO MA | F32: ANGELICA SOARES | G32: ROGERIO SCATAMBULO | H32: 0 | I32: 35614.06 | J32: 9000 | K32: 4.57 | L32: 4000 | M32: =Tabela1[[#This Row],[1ª QZ]]-Tabela1[[#This Row],[SALDO FINAL]]-Tabela1[[#This Row],[SALDO CARTAO]]-Tabela1[[#This Row],[Adiantamento ]] -> -30618.63 | N32: =Tabela1[[#This Row],[SALDO REEMBOLSAR]]*$N$4 -> 0 | O32: 0 | Q32: =_xlfn.XLOOKUP(Tabela1[[#This Row],[COLABORADOR]],'STATUS CARTAO'!D:D,'STATUS CARTAO'!G:G) -> Cartão ativo
A33: ANDRE LUIZ SANTANA | B33: 11897381638 | C33: ATIVO | D33: REGIONAL RS | E33: CEF SERRA GAUCHA RS | F33: ALEXANDRE GROSS | G33: EVERSON GAIDSTIECHI | H33: 0 | I33: 0 | J33: 2800 | K33: 1.75 | M33: =Tabela1[[#This Row],[1ª QZ]]-Tabela1[[#This Row],[SALDO FINAL]]-Tabela1[[#This Row],[SALDO CARTAO]]-Tabela1[[#This Row],[Adiantamento ]] -> 2798.25 | N33: =Tabela1[[#This Row],[SALDO REEMBOLSAR]]*$N$4 -> 0 | O33: 2798.25 | Q33: =_xlfn.XLOOKUP(Tabela1[[#This Row],[COLABORADOR]],'STATUS CARTAO'!D:D,'STATUS CARTAO'!G:G) -> Cartão ativo
A34: ANDRE PINHEIRO BALOTIN | B34: 98603566020 | C34: ATIVO | D34: REGIONAL CLARO INFRA SUL | E34: CELESC NORTE SC | F34: BRUNO EDUARDO | G34: EVERSON GAIDSTIECHI | H34: 0 | I34: 2450.98 | J34: 1200 | K34: 1708.41 | M34: =Tabela1[[#This Row],[1ª QZ]]-Tabela1[[#This Row],[SALDO FINAL]]-Tabela1[[#This Row],[SALDO CARTAO]]-Tabela1[[#This Row],[Adiantamento ]] -> -2959.39 | N34: =Tabela1[[#This Row],[SALDO REEMBOLSAR]]*$N$4 -> 0 | O34: 0 | Q34: =_xlfn.XLOOKUP(Tabela1[[#This Row],[COLABORADOR]],'STATUS CARTAO'!D:D,'STATUS CARTAO'!G:G) -> Cartão ativo
A35: ANDRE VALERIO DE PAIVA | B35: 12682517633 | C35: ATIVO | D35: REGIONAL MG | E35: CLARO INFRA MG | F35: HUGO ALEXANDRE | G35: MARCOS CARIAS | H35: 0 | I35: 1012.22 | J35: 400 | K35: 4.12 | M35: =Tabela1[[#This Row],[1ª QZ]]-Tabela1[[#This Row],[SALDO FINAL]]-Tabela1[[#This Row],[SALDO CARTAO]]-Tabela1[[#This Row],[Adiantamento ]] -> -616.34 | N35: =Tabela1[[#This Row],[SALDO REEMBOLSAR]]*$N$4 -> 0 | O35: 0 | Q35: =_xlfn.XLOOKUP(Tabela1[[#This Row],[COLABORADOR]],'STATUS CARTAO'!D:D,'STATUS CARTAO'!G:G) -> Cartão ativo
A36: ANDRESA INDIRA SANTANA AGGIO | B36: 33162718805 | C36: ATIVO | D36: REGIONAL SC | E36: ADM FILIAL SC | F36: LEANDRO MARCUSSO | G36: EVERSON GAIDSTIECHI | H36: 0 | I36: 1506.3 | J36: 1000 | K36: 969.8 | L36: 341.7 | M36: =Tabela1[[#This Row],[1ª QZ]]-Tabela1[[#This Row],[SALDO FINAL]]-Tabela1[[#This Row],[SALDO CARTAO]]-Tabela1[[#This Row],[Adiantamento ]] -> -1817.8 | N36: =Tabela1[[#This Row],[SALDO REEMBOLSAR]]*$N$4 -> 0 | O36: 0 | Q36: =_xlfn.XLOOKUP(Tabela1[[#This Row],[COLABORADOR]],'STATUS CARTAO'!D:D,'STATUS CARTAO'!G:G) -> Cartão ativo
A37: ANGELICA SOARES AMARANTE SILVA | B37: 07643300712 | C37: ATIVO | D37: REGIONAL CO | E37: ADM FILIAL CO | F37: ANGELICA SOARES | G37: ROGERIO SCATAMBULO | H37: 0 | I37: 9122.95 | J37: 1500 | K37: 17.1 | L37: 0 | M37: =Tabela1[[#This Row],[1ª QZ]]-Tabela1[[#This Row],[SALDO FINAL]]-Tabela1[[#This Row],[SALDO CARTAO]]-Tabela1[[#This Row],[Adiantamento ]] -> -7640.05 | N37: =Tabela1[[#This Row],[SALDO REEMBOLSAR]]*$N$4 -> 0 | O37: 0 | Q37: =_xlfn.XLOOKUP(Tabela1[[#This Row],[COLABORADOR]],'STATUS CARTAO'!D:D,'STATUS CARTAO'!G:G) -> Cartão ativo
A38: ANTONIO DE PADUA LEITE | B38: 26992280600 | C38: ATIVO | D38: REGIONAL MG | E38: VTAL CYBER MG | F38: HUGO ALEXANDRE | G38: MARCOS CARIAS | H38: 0 | I38: 367.33 | J38: 300 | K38: 4.82 | M38: =Tabela1[[#This Row],[1ª QZ]]-Tabela1[[#This Row],[SALDO FINAL]]-Tabela1[[#This Row],[SALDO CARTAO]]-Tabela1[[#This Row],[Adiantamento ]] -> -72.15 | N38: =Tabela1[[#This Row],[SALDO REEMBOLSAR]]*$N$4 -> 0 | O38: 0 | Q38: =_xlfn.XLOOKUP(Tabela1[[#This Row],[COLABORADOR]],'STATUS CARTAO'!D:D,'STATUS CARTAO'!G:G) -> Cartão ativo
A39: ANTONIO FERREIRA DE MENDONCA NETO | B39: 05766838760 | C39: ATIVO | D39: REGIONAL RJ | E39: TRIBUNAL DE JUSTICA RJ | F39: ALLAN JEFFERSON | G39: ROGERIO SCATAMBULO | H39: 0 | I39: 4790.77 | J39: 5000 | K39: 2666 | M39: =Tabela1[[#This Row],[1ª QZ]]-Tabela1[[#This Row],[SALDO FINAL]]-Tabela1[[#This Row],[SALDO CARTAO]]-Tabela1[[#This Row],[Adiantamento ]] -> -2456.77 | N39: =Tabela1[[#This Row],[SALDO REEMBOLSAR]]*$N$4 -> 0 | O39: 0 | Q39: =_xlfn.XLOOKUP(Tabela1[[#This Row],[COLABORADOR]],'STATUS CARTAO'!D:D,'STATUS CARTAO'!G:G) -> Cartão ativo
A40: ANTONIO JOSE PEREIRA DA SILVA | B40: 08326260401 | C40: ATIVO | D40: REGIONAL NE | E40: TELEFONICA NE | F40: GERSON OLIVEIRA | G40: ROGERIO SCATAMBULO | H40: 788.5 | I40: 0 | J40: 1000 | K40: 3 | M40: =Tabela1[[#This Row],[1ª QZ]]-Tabela1[[#This Row],[SALDO FINAL]]-Tabela1[[#This Row],[SALDO CARTAO]]-Tabela1[[#This Row],[Adiantamento ]] -> 997 | N40: =Tabela1[[#This Row],[SALDO REEMBOLSAR]]*$N$4 -> 473.1 | O40: 1391.25 | Q40: =_xlfn.XLOOKUP(Tabela1[[#This Row],[COLABORADOR]],'STATUS CARTAO'!D:D,'STATUS CARTAO'!G:G) -> Cartão ativo
A41: ANTONIO MARCOS CAMARGO | B41: 04836584990 | C41: ATIVO | D41: REGIONAL SC | E41: TRIBUNAL DE JUSTICA PR | F41: LEANDRO MARCUSSO | G41: EVERSON GAIDSTIECHI | H41: 0 | I41: 68.46 | J41: 800 | K41: 89.41 | M41: =Tabela1[[#This Row],[1ª QZ]]-Tabela1[[#This Row],[SALDO FINAL]]-Tabela1[[#This Row],[SALDO CARTAO]]-Tabela1[[#This Row],[Adiantamento ]] -> 642.13 | N41: =Tabela1[[#This Row],[SALDO REEMBOLSAR]]*$N$4 -> 0 | O41: 642.13 | Q41: =_xlfn.XLOOKUP(Tabela1[[#This Row],[COLABORADOR]],'STATUS CARTAO'!D:D,'STATUS CARTAO'!G:G) -> Cartão ativo
A42: ARLEY HENRIQUE DE SOUZA LUZ | B42: 01170402232 | C42: ATIVO | D42: REGIONAL CO | E42: CEF GOIANIA CO | F42: ANGELICA SOARES | G42: ROGERIO SCATAMBULO | H42: 0 | I42: 1453.02 | J42: 2000 | K42: 36 | M42: =Tabela1[[#This Row],[1ª QZ]]-Tabela1[[#This Row],[SALDO FINAL]]-Tabela1[[#This Row],[SALDO CARTAO]]-Tabela1[[#This Row],[Adiantamento ]] -> 510.98 | N42: =Tabela1[[#This Row],[SALDO REEMBOLSAR]]*$N$4 -> 0 | O42: 510.98 | Q42: =_xlfn.XLOOKUP(Tabela1[[#This Row],[COLABORADOR]],'STATUS CARTAO'!D:D,'STATUS CARTAO'!G:G) -> Cartão ativo
A43: ARTHUR GOMES DE PAULO | B43: 12877857603 | C43: ATIVO | D43: REGIONAL MG | E43: CLARO INFRA MG | F43: HUGO ALEXANDRE | G43: MARCOS CARIAS | H43: 0 | I43: 854.02 | J43: 800 | K43: 110.64 | M43: =Tabela1[[#This Row],[1ª QZ]]-Tabela1[[#This Row],[SALDO FINAL]]-Tabela1[[#This Row],[SALDO CARTAO]]-Tabela1[[#This Row],[Adiantamento ]] -> -164.66 | N43: =Tabela1[[#This Row],[SALDO REEMBOLSAR]]*$N$4 -> 0 | O43: 0 | Q43: =_xlfn.XLOOKUP(Tabela1[[#This Row],[COLABORADOR]],'STATUS CARTAO'!D:D,'STATUS CARTAO'!G:G) -> Cartão ativo
A44: ARTHUR SANTOS DE OLIVEIRA | B44: 13921847621 | C44: ATIVO | D44: REGIONAL MG | E44: CLARO INFRA MG | F44: HUGO ALEXANDRE | G44: MARCOS CARIAS | H44: 0 | I44: 35.56 | J44: 700 | K44: 3 | M44: =Tabela1[[#This Row],[1ª QZ]]-Tabela1[[#This Row],[SALDO FINAL]]-Tabela1[[#This Row],[SALDO CARTAO]]-Tabela1[[#This Row],[Adiantamento ]] -> 661.44 | N44: =Tabela1[[#This Row],[SALDO REEMBOLSAR]]*$N$4 -> 0 | O44: 661.44 | Q44: =_xlfn.XLOOKUP(Tabela1[[#This Row],[COLABORADOR]],'STATUS CARTAO'!D:D,'STATUS CARTAO'!G:G) -> Cartão ativo
A45: ARTUR JACO PAGANI DE SOUZA | B45: 07105914971 | C45: ATIVO | D45: REGIONAL CLARO INFRA SUL | E45: CLARO INFRA SC | F45: BRUNO EDUARDO | G45: EVERSON GAIDSTIECHI | H45: 0 | I45: 932.38 | J45: 80 | K45: 0.3 | M45: =Tabela1[[#This Row],[1ª QZ]]-Tabela1[[#This Row],[SALDO FINAL]]-Tabela1[[#This Row],[SALDO CARTAO]]-Tabela1[[#This Row],[Adiantamento ]] -> -852.68 | N45: =Tabela1[[#This Row],[SALDO REEMBOLSAR]]*$N$4 -> 0 | O45: 0 | Q45: =_xlfn.XLOOKUP(Tabela1[[#This Row],[COLABORADOR]],'STATUS CARTAO'!D:D,'STATUS CARTAO'!G:G) -> Cartão ativo
A46: AURO MOREIRA PEDROSO | B46: 32060157900 | C46: ATIVO | D46: REGIONAL SC | E46: BB NORTE OESTE PR | F46: LEANDRO MARCUSSO | G46: EVERSON GAIDSTIECHI | H46: 368.83 | I46: 0 | J46: 700 | K46: 144.11 | M46: =Tabela1[[#This Row],[1ª QZ]]-Tabela1[[#This Row],[SALDO FINAL]]-Tabela1[[#This Row],[SALDO CARTAO]]-Tabela1[[#This Row],[Adiantamento ]] -> 555.89 | N46: =Tabela1[[#This Row],[SALDO REEMBOLSAR]]*$N$4 -> 221.298 | O46: 740.305 | Q46: =_xlfn.XLOOKUP(Tabela1[[#This Row],[COLABORADOR]],'STATUS CARTAO'!D:D,'STATUS CARTAO'!G:G) -> Cartão ativo
A47: BEATRIZ SILVA DE SIQUEIRA | B47: 35575473880 | C47: ATIVO | D47: REGIONAL SP | E47: CEF SP SUL | F47: LEANDRO NUNES | G47: EVERSON GAIDSTIECHI | H47: 0 | I47: 1798.93 | J47: 2200 | K47: 9.21 | M47: =Tabela1[[#This Row],[1ª QZ]]-Tabela1[[#This Row],[SALDO FINAL]]-Tabela1[[#This Row],[SALDO CARTAO]]-Tabela1[[#This Row],[Adiantamento ]] -> 391.86 | N47: =Tabela1[[#This Row],[SALDO REEMBOLSAR]]*$N$4 -> 0 | O47: 391.86 | Q47: =_xlfn.XLOOKUP(Tabela1[[#This Row],[COLABORADOR]],'STATUS CARTAO'!D:D,'STATUS CARTAO'!G:G) -> Cartão ativo
A48: BEN HUR MENDES OLIVEIRA | B48: 00046347054 | C48: ATIVO | D48: REGIONAL CLARO INFRA SUL | E48: CLARO INFRA SC | F48: BRUNO EDUARDO | G48: EVERSON GAIDSTIECHI | H48: 0 | I48: 662.75 | J48: 120 | K48: 0 | M48: =Tabela1[[#This Row],[1ª QZ]]-Tabela1[[#This Row],[SALDO FINAL]]-Tabela1[[#This Row],[SALDO CARTAO]]-Tabela1[[#This Row],[Adiantamento ]] -> -542.75 | N48: =Tabela1[[#This Row],[SALDO REEMBOLSAR]]*$N$4 -> 0 | O48: 0 | Q48: =_xlfn.XLOOKUP(Tabela1[[#This Row],[COLABORADOR]],'STATUS CARTAO'!D:D,'STATUS CARTAO'!G:G) -> Cartão ativo
A49: BRUNA LAIS AZEVEDO CUNHA | B49: 07747008406 | C49: ATIVO | D49: REGIONAL CLARO INFRA NORDESTE | E49: CLARO INFRA NORDESTE | F49: FELIPE JOSE | G49: ROGERIO SCATAMBULO | H49: 138.11 | I49: 0 | J49: 1000 | K49: 56.66 | M49: =Tabela1[[#This Row],[1ª QZ]]-Tabela1[[#This Row],[SALDO FINAL]]-Tabela1[[#This Row],[SALDO CARTAO]]-Tabela1[[#This Row],[Adiantamento ]] -> 943.34 | N49: =Tabela1[[#This Row],[SALDO REEMBOLSAR]]*$N$4 -> 82.866 | O49: 1012.395 | Q49: =_xlfn.XLOOKUP(Tabela1[[#This Row],[COLABORADOR]],'STATUS CARTAO'!D:D,'STATUS CARTAO'!G:G) -> Cartão ativo
A50: BRUNA LAIS DOS SANTOS PESSOA | B50: 13459423625 | C50: ATIVO | D50: REGIONAL MG | E50: ASSEMBLEIA LEGISLATIVA MG | F50: HUGO ALEXANDRE | G50: MARCOS CARIAS | H50: 0 | I50: 661.88 | J50: 800 | K50: 327.29 | M50: =Tabela1[[#This Row],[1ª QZ]]-Tabela1[[#This Row],[SALDO FINAL]]-Tabela1[[#This Row],[SALDO CARTAO]]-Tabela1[[#This Row],[Adiantamento ]] -> -189.17 | N50: =Tabela1[[#This Row],[SALDO REEMBOLSAR]]*$N$4 -> 0 | O50: 0 | Q50: =_xlfn.XLOOKUP(Tabela1[[#This Row],[COLABORADOR]],'STATUS CARTAO'!D:D,'STATUS CARTAO'!G:G) -> Cartão ativo
A51: BRUNA LAIS DOS SANTOS PESSOA | B51: 13459423625 | D51: REGIONAL MG | E51: ASSEMBLEIA LEGISLATIVA MG | M51: =Tabela1[[#This Row],[1ª QZ]]-Tabela1[[#This Row],[SALDO FINAL]]-Tabela1[[#This Row],[SALDO CARTAO]]-Tabela1[[#This Row],[Adiantamento ]] -> 0 | N51: =Tabela1[[#This Row],[SALDO REEMBOLSAR]]*$N$4 -> 0 | O51: 288.12 | Q51: =_xlfn.XLOOKUP(Tabela1[[#This Row],[COLABORADOR]],'STATUS CARTAO'!D:D,'STATUS CARTAO'!G:G) -> Cartão ativo
A52: BRUNO EDUARDO DE SOUZA | B52: 82341478972 | C52: ATIVO | D52: REGIONAL SC | E52: CLARO INFRA SC | F52: LEANDRO MARCUSSO | G52: EVERSON GAIDSTIECHI | H52: 0 | I52: 692.8 | J52: 700 | K52: 900 | M52: =Tabela1[[#This Row],[1ª QZ]]-Tabela1[[#This Row],[SALDO FINAL]]-Tabela1[[#This Row],[SALDO CARTAO]]-Tabela1[[#This Row],[Adiantamento ]] -> -892.8 | N52: =Tabela1[[#This Row],[SALDO REEMBOLSAR]]*$N$4 -> 0 | O52: 0 | Q52: =_xlfn.XLOOKUP(Tabela1[[#This Row],[COLABORADOR]],'STATUS CARTAO'!D:D,'STATUS CARTAO'!G:G) -> Cartão ativo
A53: BRUNO FERREIRA DE SOUZA RODRIGUES | B53: 16306431730 | C53: ATIVO | D53: REGIONAL RJ | E53: TELEFONICA RJ | F53: ALLAN JEFFERSON | G53: ROGERIO SCATAMBULO | H53: 0 | I53: 32541 | J53: 5000 | K53: 0.73 | M53: =Tabela1[[#This Row],[1ª QZ]]-Tabela1[[#This Row],[SALDO FINAL]]-Tabela1[[#This Row],[SALDO CARTAO]]-Tabela1[[#This Row],[Adiantamento ]] -> -27541.73 | N53: =Tabela1[[#This Row],[SALDO REEMBOLSAR]]*$N$4 -> 0 | O53: 0 | Q53: =_xlfn.XLOOKUP(Tabela1[[#This Row],[COLABORADOR]],'STATUS CARTAO'!D:D,'STATUS CARTAO'!G:G) -> Cartão ativo
A54: BRUNO OLIVEIRA DIAS | B54: 11992259755 | C54: ATIVO | D54: REGIONAL ES | E54: PTB TIC INFRA | F54: VINICIUS LOCATELLY | G54: MARCOS CARIAS | H54: 0 | I54: 7221.14 | J54: 6200 | K54: 2463.33 | M54: =Tabela1[[#This Row],[1ª QZ]]-Tabela1[[#This Row],[SALDO FINAL]]-Tabela1[[#This Row],[SALDO CARTAO]]-Tabela1[[#This Row],[Adiantamento ]] -> -3484.47 | N54: =Tabela1[[#This Row],[SALDO REEMBOLSAR]]*$N$4 -> 0 | O54: 0 | Q54: =_xlfn.XLOOKUP(Tabela1[[#This Row],[COLABORADOR]],'STATUS CARTAO'!D:D,'STATUS CARTAO'!G:G) -> Cartão ativo
A55: CAIO FRANCESCONI RIBEIRO | B55: 08924586904 | C55: ATIVO | D55: REGIONAL SC | E55: TJ APOIO PR | F55: LEANDRO MARCUSSO | G55: EVERSON GAIDSTIECHI | H55: 0 | I55: 3166.14 | J55: 3900 | K55: 4.82 | M55: =Tabela1[[#This Row],[1ª QZ]]-Tabela1[[#This Row],[SALDO FINAL]]-Tabela1[[#This Row],[SALDO CARTAO]]-Tabela1[[#This Row],[Adiantamento ]] -> 729.04 | N55: =Tabela1[[#This Row],[SALDO REEMBOLSAR]]*$N$4 -> 0 | O55: 729.04 | Q55: =_xlfn.XLOOKUP(Tabela1[[#This Row],[COLABORADOR]],'STATUS CARTAO'!D:D,'STATUS CARTAO'!G:G) -> Cartão ativo
A56: CAIOS VINICIUS NUNES BROERING | B56: 07053418952 | C56: ATIVO | D56: REGIONAL CLARO INFRA SUL | E56: CLARO INFRA SC | F56: BRUNO EDUARDO | G56: EVERSON GAIDSTIECHI | H56: 0 | I56: 2956.26 | J56: 2520 | K56: 90.56 | M56: =Tabela1[[#This Row],[1ª QZ]]-Tabela1[[#This Row],[SALDO FINAL]]-Tabela1[[#This Row],[SALDO CARTAO]]-Tabela1[[#This Row],[Adiantamento ]] -> -526.82 | N56: =Tabela1[[#This Row],[SALDO REEMBOLSAR]]*$N$4 -> 0 | O56: 0 | Q56: =_xlfn.XLOOKUP(Tabela1[[#This Row],[COLABORADOR]],'STATUS CARTAO'!D:D,'STATUS CARTAO'!G:G) -> Cartão ativo
A57: CAIOS VINICIUS NUNES BROERING | B57: 07053418952 | D57: REGIONAL CLARO INFRA SUL | E57: CLARO INFRA SC | M57: =Tabela1[[#This Row],[1ª QZ]]-Tabela1[[#This Row],[SALDO FINAL]]-Tabela1[[#This Row],[SALDO CARTAO]]-Tabela1[[#This Row],[Adiantamento ]] -> 0 | N57: =Tabela1[[#This Row],[SALDO REEMBOLSAR]]*$N$4 -> 0 | O57: 2165.74 | Q57: =_xlfn.XLOOKUP(Tabela1[[#This Row],[COLABORADOR]],'STATUS CARTAO'!D:D,'STATUS CARTAO'!G:G) -> Cartão ativo
A58: CAMILA DE OLIVEIRA VELOSO | B58: 85076538553 | C58: ATIVO | D58: REGIONAL NE | E58: BANCO CENTRAL SALVADOR BA | F58: GERSON OLIVEIRA | G58: ROGERIO SCATAMBULO | H58: 0 | I58: 169.16 | J58: 200 | K58: 90.66 | M58: =Tabela1[[#This Row],[1ª QZ]]-Tabela1[[#This Row],[SALDO FINAL]]-Tabela1[[#This Row],[SALDO CARTAO]]-Tabela1[[#This Row],[Adiantamento ]] -> -59.82 | N58: =Tabela1[[#This Row],[SALDO REEMBOLSAR]]*$N$4 -> 0 | O58: 0 | Q58: =_xlfn.XLOOKUP(Tabela1[[#This Row],[COLABORADOR]],'STATUS CARTAO'!D:D,'STATUS CARTAO'!G:G) -> Cartão ativo
A59: CARLOS ALEXANDRE GIGI | B59: 20005473896 | C59: ATIVO | D59: REGIONAL SP | E59: BB SP | F59: LEANDRO NUNES | G59: EVERSON GAIDSTIECHI | H59: 0 | I59: 342.76 | J59: 400 | K59: 364.2 | M59: =Tabela1[[#This Row],[1ª QZ]]-Tabela1[[#This Row],[SALDO FINAL]]-Tabela1[[#This Row],[SALDO CARTAO]]-Tabela1[[#This Row],[Adiantamento ]] -> -306.96 | N59: =Tabela1[[#This Row],[SALDO REEMBOLSAR]]*$N$4 -> 0 | O59: 0 | Q59: =_xlfn.XLOOKUP(Tabela1[[#This Row],[COLABORADOR]],'STATUS CARTAO'!D:D,'STATUS CARTAO'!G:G) -> Cartão ativo
A60: CARLOS EDUARDO SCATAMBULO | B60: 22730778829 | C60: ATIVO | D60: REGIONAL SP | E60: CEF LESTE SP | F60: LEANDRO NUNES | G60: EVERSON GAIDSTIECHI | H60: 0 | I60: 447.69 | J60: 2300 | K60: 1.68 | M60: =Tabela1[[#This Row],[1ª QZ]]-Tabela1[[#This Row],[SALDO FINAL]]-Tabela1[[#This Row],[SALDO CARTAO]]-Tabela1[[#This Row],[Adiantamento ]] -> 1850.63 | N60: =Tabela1[[#This Row],[SALDO REEMBOLSAR]]*$N$4 -> 0 | O60: 1850.63 | Q60: =_xlfn.XLOOKUP(Tabela1[[#This Row],[COLABORADOR]],'STATUS CARTAO'!D:D,'STATUS CARTAO'!G:G) -> Cartão ativo
A61: CARLOS FRANCISCO GODOY | B61: 82741980004 | C61: ATIVO | D61: REGIONAL RS | E61: CEF LESTE GAUCHO RS | F61: ALEXANDRE GROSS | G61: EVERSON GAIDSTIECHI | H61: 0 | I61: 45.82 | J61: 125 | K61: 18.46 | M61: =Tabela1[[#This Row],[1ª QZ]]-Tabela1[[#This Row],[SALDO FINAL]]-Tabela1[[#This Row],[SALDO CARTAO]]-Tabela1[[#This Row],[Adiantamento ]] -> 60.72 | N61: =Tabela1[[#This Row],[SALDO REEMBOLSAR]]*$N$4 -> 0 | O61: 60.72 | Q61: =_xlfn.XLOOKUP(Tabela1[[#This Row],[COLABORADOR]],'STATUS CARTAO'!D:D,'STATUS CARTAO'!G:G) -> Cartão ativo
A62: CARLOS NASCIMENTO NONATO JUNIOR | B62: 65973500225 | C62: ATIVO | D62: REGIONAL CO | E62: CEF AM AC RR | F62: ANGELICA SOARES | G62: ROGERIO SCATAMBULO | H62: 0 | I62: 9334.01 | J62: 4000 | K62: 2 | M62: =Tabela1[[#This Row],[1ª QZ]]-Tabela1[[#This Row],[SALDO FINAL]]-Tabela1[[#This Row],[SALDO CARTAO]]-Tabela1[[#This Row],[Adiantamento ]] -> -5336.01 | N62: =Tabela1[[#This Row],[SALDO REEMBOLSAR]]*$N$4 -> 0 | O62: 0 | Q62: =_xlfn.XLOOKUP(Tabela1[[#This Row],[COLABORADOR]],'STATUS CARTAO'!D:D,'STATUS CARTAO'!G:G) -> Cartão ativo
A63: CARLOS RENATO PACHECO DA SILVA | B63: 90443306087 | C63: ATIVO | D63: REGIONAL RS | E63: CEF LESTE GAUCHO RS | F63: ALEXANDRE GROSS | G63: EVERSON GAIDSTIECHI | H63: 2222.63 | I63: 0 | J63: 2800 | K63: 80.77 | M63: =Tabela1[[#This Row],[1ª QZ]]-Tabela1[[#This Row],[SALDO FINAL]]-Tabela1[[#This Row],[SALDO CARTAO]]-Tabela1[[#This Row],[Adiantamento ]] -> 2719.23 | N63: =Tabela1[[#This Row],[SALDO REEMBOLSAR]]*$N$4 -> 1333.578 | O63: 3830.545 | Q63: =_xlfn.XLOOKUP(Tabela1[[#This Row],[COLABORADOR]],'STATUS CARTAO'!D:D,'STATUS CARTAO'!G:G) -> Cartão ativo
A64: CARLOS ROBERTO DE CARVALHO PERES | B64: 09867858816 | C64: ATIVO | D64: REGIONAL CO | E64: CLARO CO | F64: ANGELICA SOARES | G64: ROGERIO SCATAMBULO | H64: 0 | I64: 2002.63 | J64: 1500 | K64: 3.51 | M64: =Tabela1[[#This Row],[1ª QZ]]-Tabela1[[#This Row],[SALDO FINAL]]-Tabela1[[#This Row],[SALDO CARTAO]]-Tabela1[[#This Row],[Adiantamento ]] -> -506.14 | N64: =Tabela1[[#This Row],[SALDO REEMBOLSAR]]*$N$4 -> 0 | O64: 0 | Q64: =_xlfn.XLOOKUP(Tabela1[[#This Row],[COLABORADOR]],'STATUS CARTAO'!D:D,'STATUS CARTAO'!G:G) -> Cartão ativo
A65: CHARLES NEVES MATTIUZZI | B65: 12547938790 | C65: ATIVO | D65: REGIONAL ES | E65: TELEFONICA ES | F65: VINICIUS LOCATELLY | G65: MARCOS CARIAS | H65: 0 | I65: 1769.12 | J65: 4200 | K65: 9.43 | M65: =Tabela1[[#This Row],[1ª QZ]]-Tabela1[[#This Row],[SALDO FINAL]]-Tabela1[[#This Row],[SALDO CARTAO]]-Tabela1[[#This Row],[Adiantamento ]] -> 2421.45 | N65: =Tabela1[[#This Row],[SALDO REEMBOLSAR]]*$N$4 -> 0 | O65: 2421.45 | Q65: =_xlfn.XLOOKUP(Tabela1[[#This Row],[COLABORADOR]],'STATUS CARTAO'!D:D,'STATUS CARTAO'!G:G) -> Cartão ativo
A66: CHARLYTON COSTA ANDRADE | B66: 01050938232 | C66: ATIVO | D66: REGIONAL CO | E66: CEF AM AC RR | F66: ANGELICA SOARES | G66: ROGERIO SCATAMBULO | H66: 0 | I66: 3931.78 | J66: 17100 | K66: 18.93 | M66: =Tabela1[[#This Row],[1ª QZ]]-Tabela1[[#This Row],[SALDO FINAL]]-Tabela1[[#This Row],[SALDO CARTAO]]-Tabela1[[#This Row],[Adiantamento ]] -> 13149.29 | N66: =Tabela1[[#This Row],[SALDO REEMBOLSAR]]*$N$4 -> 0 | O66: 13149.29 | Q66: =_xlfn.XLOOKUP(Tabela1[[#This Row],[COLABORADOR]],'STATUS CARTAO'!D:D,'STATUS CARTAO'!G:G) -> Cartão ativo
A67: CLAUDEMIR GREGOSKI RODRIGUES | B67: 05144026958 | C67: ATIVO | D67: REGIONAL SC | E67: CEF FACILITIES CURITIBA PR | F67: LEANDRO MARCUSSO | G67: EVERSON GAIDSTIECHI | H67: 1900 | I67: 0 | J67: 1000 | K67: 0 | M67: =Tabela1[[#This Row],[1ª QZ]]-Tabela1[[#This Row],[SALDO FINAL]]-Tabela1[[#This Row],[SALDO CARTAO]]-Tabela1[[#This Row],[Adiantamento ]] -> 1000 | N67: =Tabela1[[#This Row],[SALDO REEMBOLSAR]]*$N$4 -> 1140 | O67: 1950 | Q67: =_xlfn.XLOOKUP(Tabela1[[#This Row],[COLABORADOR]],'STATUS CARTAO'!D:D,'STATUS CARTAO'!G:G) -> Cartão ativo
A68: CLAUDEMIR MOREIRA | B68: 75609444004 | C68: ATIVO | D68: REGIONAL SC | E68: TRIBUNAL DE JUSTICA PR | F68: LEANDRO MARCUSSO | G68: EVERSON GAIDSTIECHI | H68: 0 | I68: 774.52 | J68: 800 | K68: 166.62 | M68: =Tabela1[[#This Row],[1ª QZ]]-Tabela1[[#This Row],[SALDO FINAL]]-Tabela1[[#This Row],[SALDO CARTAO]]-Tabela1[[#This Row],[Adiantamento ]] -> -141.14 | N68: =Tabela1[[#This Row],[SALDO REEMBOLSAR]]*$N$4 -> 0 | O68: 0 | Q68: =_xlfn.XLOOKUP(Tabela1[[#This Row],[COLABORADOR]],'STATUS CARTAO'!D:D,'STATUS CARTAO'!G:G) -> Cartão ativo
A69: CLAUDEMIR MOREIRA | B69: 75609444004 | D69: REGIONAL SC | E69: TRIBUNAL DE JUSTICA PR | M69: =Tabela1[[#This Row],[1ª QZ]]-Tabela1[[#This Row],[SALDO FINAL]]-Tabela1[[#This Row],[SALDO CARTAO]]-Tabela1[[#This Row],[Adiantamento ]] -> 0 | N69: =Tabela1[[#This Row],[SALDO REEMBOLSAR]]*$N$4 -> 0 | O69: 325.48 | Q69: =_xlfn.XLOOKUP(Tabela1[[#This Row],[COLABORADOR]],'STATUS CARTAO'!D:D,'STATUS CARTAO'!G:G) -> Cartão ativo
A70: CLAUDINEI AMARAL | B70: 10433881844 | C70: ATIVO | D70: REGIONAL SC | E70: TRIBUNAL DE JUSTICA PR | F70: LEANDRO MARCUSSO | G70: EVERSON GAIDSTIECHI | H70: 419.41 | I70: 0 | J70: 900 | K70: 14.42 | M70: =Tabela1[[#This Row],[1ª QZ]]-Tabela1[[#This Row],[SALDO FINAL]]-Tabela1[[#This Row],[SALDO CARTAO]]-Tabela1[[#This Row],[Adiantamento ]] -> 885.58 | N70: =Tabela1[[#This Row],[SALDO REEMBOLSAR]]*$N$4 -> 251.646 | O70: 1095.285 | Q70: =_xlfn.XLOOKUP(Tabela1[[#This Row],[COLABORADOR]],'STATUS CARTAO'!D:D,'STATUS CARTAO'!G:G) -> Cartão ativo
A71: CLAUDINEI VICENTE DE LIMA | B71: 91920795987 | C71: ATIVO | D71: REGIONAL CLARO INFRA SUL | E71: CELESC NORTE SC | F71: BRUNO EDUARDO | G71: EVERSON GAIDSTIECHI | H71: 0 | I71: 165.3 | J71: 240 | K71: 17.8 | M71: =Tabela1[[#This Row],[1ª QZ]]-Tabela1[[#This Row],[SALDO FINAL]]-Tabela1[[#This Row],[SALDO CARTAO]]-Tabela1[[#This Row],[Adiantamento ]] -> 56.9 | N71: =Tabela1[[#This Row],[SALDO REEMBOLSAR]]*$N$4 -> 0 | O71: 56.9 | Q71: =_xlfn.XLOOKUP(Tabela1[[#This Row],[COLABORADOR]],'STATUS CARTAO'!D:D,'STATUS CARTAO'!G:G) -> Cartão ativo
A72: CLAUDIO DONIZETE DA SILVA | B72: 93457235953 | C72: ATIVO | D72: REGIONAL SC | E72: TRIBUNAL DE JUSTICA PR | F72: LEANDRO MARCUSSO | G72: EVERSON GAIDSTIECHI | H72: 0 | I72: 164.32 | J72: 600 | K72: 0.02 | M72: =Tabela1[[#This Row],[1ª QZ]]-Tabela1[[#This Row],[SALDO FINAL]]-Tabela1[[#This Row],[SALDO CARTAO]]-Tabela1[[#This Row],[Adiantamento ]] -> 435.66 | N72: =Tabela1[[#This Row],[SALDO REEMBOLSAR]]*$N$4 -> 0 | O72: 435.66 | Q72: =_xlfn.XLOOKUP(Tabela1[[#This Row],[COLABORADOR]],'STATUS CARTAO'!D:D,'STATUS CARTAO'!G:G) -> Cartão ativo
A73: CLAUDIO RENALDI NUNES | B73: 02705722955 | C73: ATIVO | D73: REGIONAL SC | E73: TRIBUNAL DE JUSTICA PR | F73: LEANDRO MARCUSSO | G73: EVERSON GAIDSTIECHI | H73: 0 | I73: 251.32 | J73: 750 | K73: 251.32 | M73: =Tabela1[[#This Row],[1ª QZ]]-Tabela1[[#This Row],[SALDO FINAL]]-Tabela1[[#This Row],[SALDO CARTAO]]-Tabela1[[#This Row],[Adiantamento ]] -> 247.36 | N73: =Tabela1[[#This Row],[SALDO REEMBOLSAR]]*$N$4 -> 0 | O73: 247.36 | Q73: =_xlfn.XLOOKUP(Tabela1[[#This Row],[COLABORADOR]],'STATUS CARTAO'!D:D,'STATUS CARTAO'!G:G) -> Cartão ativo
A74: CLAUDIO RENALDI NUNES | B74: 02705722955 | D74: REGIONAL SC | E74: TRIBUNAL DE JUSTICA PR | M74: =Tabela1[[#This Row],[1ª QZ]]-Tabela1[[#This Row],[SALDO FINAL]]-Tabela1[[#This Row],[SALDO CARTAO]]-Tabela1[[#This Row],[Adiantamento ]] -> 0 | N74: =Tabela1[[#This Row],[SALDO REEMBOLSAR]]*$N$4 -> 0 | O74: 251.32 | Q74: =_xlfn.XLOOKUP(Tabela1[[#This Row],[COLABORADOR]],'STATUS CARTAO'!D:D,'STATUS CARTAO'!G:G) -> Cartão ativo
A75: CLAYTON DE OLIVEIRA | B75: 02928835954 | C75: ATIVO | D75: REGIONAL CLARO INFRA SUL | E75: CLARO INFRA PR | F75: BRUNO EDUARDO | G75: EVERSON GAIDSTIECHI | H75: 0 | I75: 243.75 | J75: 150 | K75: 0.3 | M75: =Tabela1[[#This Row],[1ª QZ]]-Tabela1[[#This Row],[SALDO FINAL]]-Tabela1[[#This Row],[SALDO CARTAO]]-Tabela1[[#This Row],[Adiantamento ]] -> -94.05 | N75: =Tabela1[[#This Row],[SALDO REEMBOLSAR]]*$N$4 -> 0 | O75: 0 | Q75: =_xlfn.XLOOKUP(Tabela1[[#This Row],[COLABORADOR]],'STATUS CARTAO'!D:D,'STATUS CARTAO'!G:G) -> Cartão ativo
A76: CLEBERSON APARECIDO BORGES DOS SANTOS | B76: 05864921947 | C76: ATIVO | D76: REGIONAL SC | E76: TRIBUNAL DE JUSTICA PR | F76: LEANDRO MARCUSSO | G76: EVERSON GAIDSTIECHI | H76: 0 | I76: 729.26 | J76: 800 | K76: 94.75 | M76: =Tabela1[[#This Row],[1ª QZ]]-Tabela1[[#This Row],[SALDO FINAL]]-Tabela1[[#This Row],[SALDO CARTAO]]-Tabela1[[#This Row],[Adiantamento ]] -> -24.01 | N76: =Tabela1[[#This Row],[SALDO REEMBOLSAR]]*$N$4 -> 0 | O76: 0 | Q76: =_xlfn.XLOOKUP(Tabela1[[#This Row],[COLABORADOR]],'STATUS CARTAO'!D:D,'STATUS CARTAO'!G:G) -> Cartão ativo
A77: CLEITON DA SILVA MONTALVAO | B77: 01929647638 | C77: ATIVO | D77: REGIONAL MG | E77: CLARO INFRA MG | F77: HUGO ALEXANDRE | G77: MARCOS CARIAS | H77: 0 | I77: 759.69 | J77: 250 | K77: 462.19 | M77: =Tabela1[[#This Row],[1ª QZ]]-Tabela1[[#This Row],[SALDO FINAL]]-Tabela1[[#This Row],[SALDO CARTAO]]-Tabela1[[#This Row],[Adiantamento ]] -> -971.88 | N77: =Tabela1[[#This Row],[SALDO REEMBOLSAR]]*$N$4 -> 0 | O77: 0 | Q77: =_xlfn.XLOOKUP(Tabela1[[#This Row],[COLABORADOR]],'STATUS CARTAO'!D:D,'STATUS CARTAO'!G:G) -> Cartão ativo
A78: CLERITON BACILA DOS SANTOS | B78: 05456615959 | C78: ATIVO | D78: REGIONAL SC | E78: NET CTA PR | F78: LEANDRO MARCUSSO | G78: EVERSON GAIDSTIECHI | H78: 0 | I78: 4960.29 | J78: 3000 | K78: 77.9 | M78: =Tabela1[[#This Row],[1ª QZ]]-Tabela1[[#This Row],[SALDO FINAL]]-Tabela1[[#This Row],[SALDO CARTAO]]-Tabela1[[#This Row],[Adiantamento ]] -> -2038.19 | N78: =Tabela1[[#This Row],[SALDO REEMBOLSAR]]*$N$4 -> 0 | O78: 0 | Q78: =_xlfn.XLOOKUP(Tabela1[[#This Row],[COLABORADOR]],'STATUS CARTAO'!D:D,'STATUS CARTAO'!G:G) -> Cartão ativo
A79: CLEVERSON PAULOUSKI | B79: 08609699919 | C79: ATIVO | D79: REGIONAL CLARO INFRA SUL | E79: CLARO INFRA PR | F79: BRUNO EDUARDO | G79: EVERSON GAIDSTIECHI | H79: 0 | I79: 65 | J79: 100 | K79: 65 | M79: =Tabela1[[#This Row],[1ª QZ]]-Tabela1[[#This Row],[SALDO FINAL]]-Tabela1[[#This Row],[SALDO CARTAO]]-Tabela1[[#This Row],[Adiantamento ]] -> -30 | N79: =Tabela1[[#This Row],[SALDO REEMBOLSAR]]*$N$4 -> 0 | O79: 0 | Q79: =_xlfn.XLOOKUP(Tabela1[[#This Row],[COLABORADOR]],'STATUS CARTAO'!D:D,'STATUS CARTAO'!G:G) -> Cartão ativo
A80: CREOL APARECIDO DOS SANTOS | B80: 03363725906 | C80: ATIVO | D80: REGIONAL CLARO INFRA SUL | E80: CLARO INFRA PR | F80: BRUNO EDUARDO | G80: EVERSON GAIDSTIECHI | H80: 0 | I80: 14.58 | J80: 100 | K80: 2.88 | M80: =Tabela1[[#This Row],[1ª QZ]]-Tabela1[[#This Row],[SALDO FINAL]]-Tabela1[[#This Row],[SALDO CARTAO]]-Tabela1[[#This Row],[Adiantamento ]] -> 82.54 | N80: =Tabela1[[#This Row],[SALDO REEMBOLSAR]]*$N$4 -> 0 | O80: 82.54 | Q80: =_xlfn.XLOOKUP(Tabela1[[#This Row],[COLABORADOR]],'STATUS CARTAO'!D:D,'STATUS CARTAO'!G:G) -> Cartão ativo
A81: CRISTIANO ANESIO GOMES DO NASCIMENTO | B81: 02862032786 | C81: ATIVO | D81: REGIONAL RJ | E81: CEF INTERIOR RJ | F81: ALLAN JEFFERSON | G81: ROGERIO SCATAMBULO | H81: 0 | I81: 1271.06 | J81: 2000 | K81: 6 | M81: =Tabela1[[#This Row],[1ª QZ]]-Tabela1[[#This Row],[SALDO FINAL]]-Tabela1[[#This Row],[SALDO CARTAO]]-Tabela1[[#This Row],[Adiantamento ]] -> 722.94 | N81: =Tabela1[[#This Row],[SALDO REEMBOLSAR]]*$N$4 -> 0 | O81: 722.94 | Q81: =_xlfn.XLOOKUP(Tabela1[[#This Row],[COLABORADOR]],'STATUS CARTAO'!D:D,'STATUS CARTAO'!G:G) -> Cartão ativo
A82: CRISTIANO DA SILVA VALADARES | B82: 99062208649 | C82: ATIVO | D82: REGIONAL MG | E82: CCBB BH MINAS | F82: HUGO ALEXANDRE | G82: MARCOS CARIAS | H82: 0 | I82: 29.9 | J82: 500 | K82: 0 | M82: =Tabela1[[#This Row],[1ª QZ]]-Tabela1[[#This Row],[SALDO FINAL]]-Tabela1[[#This Row],[SALDO CARTAO]]-Tabela1[[#This Row],[Adiantamento ]] -> 470.1 | N82: =Tabela1[[#This Row],[SALDO REEMBOLSAR]]*$N$4 -> 0 | O82: 470.1 | Q82: =_xlfn.XLOOKUP(Tabela1[[#This Row],[COLABORADOR]],'STATUS CARTAO'!D:D,'STATUS CARTAO'!G:G) -> Cartão ativo
A83: DANIEL DA SILVA LOPES | B83: 94288259053 | C83: ATIVO | D83: REGIONAL SC | E83: NET APOIO SC | F83: LEANDRO MARCUSSO | G83: EVERSON GAIDSTIECHI | H83: 0 | I83: 2062 | J83: 2710 | K83: 0 | M83: =Tabela1[[#This Row],[1ª QZ]]-Tabela1[[#This Row],[SALDO FINAL]]-Tabela1[[#This Row],[SALDO CARTAO]]-Tabela1[[#This Row],[Adiantamento ]] -> 648 | N83: =Tabela1[[#This Row],[SALDO REEMBOLSAR]]*$N$4 -> 0 | O83: 648 | Q83: =_xlfn.XLOOKUP(Tabela1[[#This Row],[COLABORADOR]],'STATUS CARTAO'!D:D,'STATUS CARTAO'!G:G) -> Cartão ativo
A84: DANIEL DA SILVA LOPES | B84: 94288259053 | D84: REGIONAL SC | E84: NET APOIO SC | M84: =Tabela1[[#This Row],[1ª QZ]]-Tabela1[[#This Row],[SALDO FINAL]]-Tabela1[[#This Row],[SALDO CARTAO]]-Tabela1[[#This Row],[Adiantamento ]] -> 0 | N84: =Tabela1[[#This Row],[SALDO REEMBOLSAR]]*$N$4 -> 0 | O84: 1741.55 | Q84: =_xlfn.XLOOKUP(Tabela1[[#This Row],[COLABORADOR]],'STATUS CARTAO'!D:D,'STATUS CARTAO'!G:G) -> Cartão ativo
A85: DANIEL SANTOS DE ASSUNCAO | B85: 97592439549 | C85: ATIVO | D85: REGIONAL NE | E85: BANCO ITAU BA | F85: GERSON OLIVEIRA | G85: ROGERIO SCATAMBULO | H85: 354.42 | I85: 0 | J85: 1500 | K85: 16 | M85: =Tabela1[[#This Row],[1ª QZ]]-Tabela1[[#This Row],[SALDO FINAL]]-Tabela1[[#This Row],[SALDO CARTAO]]-Tabela1[[#This Row],[Adiantamento ]] -> 1484 | N85: =Tabela1[[#This Row],[SALDO REEMBOLSAR]]*$N$4 -> 212.652 | O85: 1661.21 | Q85: =_xlfn.XLOOKUP(Tabela1[[#This Row],[COLABORADOR]],'STATUS CARTAO'!D:D,'STATUS CARTAO'!G:G) -> Cartão ativo
A86: DANIELA CARVALHO STAHLER | B86: 01066881030 | C86: ATIVO | D86: REGIONAL RS | E86: NET APOIO RS | F86: ALEXANDRE GROSS | G86: EVERSON GAIDSTIECHI | H86: 0 | I86: 102.5 | J86: 200 | K86: 102.5 | M86: =Tabela1[[#This Row],[1ª QZ]]-Tabela1[[#This Row],[SALDO FINAL]]-Tabela1[[#This Row],[SALDO CARTAO]]-Tabela1[[#This Row],[Adiantamento ]] -> -5 | N86: =Tabela1[[#This Row],[SALDO REEMBOLSAR]]*$N$4 -> 0 | O86: 0 | Q86: =_xlfn.XLOOKUP(Tabela1[[#This Row],[COLABORADOR]],'STATUS CARTAO'!D:D,'STATUS CARTAO'!G:G) -> Cartão ativo
A87: DANILO ZANATTA LUCIANO | B87: 06285125970 | C87: ATIVO | D87: REGIONAL CLARO INFRA SUL | E87: CLARO INFRA SC | F87: BRUNO EDUARDO | G87: EVERSON GAIDSTIECHI | H87: 0 | I87: 131.4 | J87: 120 | K87: 50 | M87: =Tabela1[[#This Row],[1ª QZ]]-Tabela1[[#This Row],[SALDO FINAL]]-Tabela1[[#This Row],[SALDO CARTAO]]-Tabela1[[#This Row],[Adiantamento ]] -> -61.4 | N87: =Tabela1[[#This Row],[SALDO REEMBOLSAR]]*$N$4 -> 0 | O87: 0 | Q87: =_xlfn.XLOOKUP(Tabela1[[#This Row],[COLABORADOR]],'STATUS CARTAO'!D:D,'STATUS CARTAO'!G:G) -> Cartão ativo
A88: DAVID DA SILVA PEREIRA | B88: 02344854002 | C88: ATIVO | D88: REGIONAL RS | E88: DEFENSORIA PUBLICA RS | F88: ALEXANDRE GROSS | G88: EVERSON GAIDSTIECHI | H88: 0 | I88: 3493.4 | J88: 250 | K88: 12.92 | M88: =Tabela1[[#This Row],[1ª QZ]]-Tabela1[[#This Row],[SALDO FINAL]]-Tabela1[[#This Row],[SALDO CARTAO]]-Tabela1[[#This Row],[Adiantamento ]] -> -3256.32 | N88: =Tabela1[[#This Row],[SALDO REEMBOLSAR]]*$N$4 -> 0 | O88: 0 | Q88: =_xlfn.XLOOKUP(Tabela1[[#This Row],[COLABORADOR]],'STATUS CARTAO'!D:D,'STATUS CARTAO'!G:G) -> Cartão ativo
A89: DAVID DE OLIVEIRA FRIGERIO | B89: 04817177900 | C89: ATIVO | D89: REGIONAL SC | E89: CEF NORTE PR | F89: LEANDRO MARCUSSO | G89: EVERSON GAIDSTIECHI | H89: 0 | I89: 635.11 | J89: 2500 | K89: 9 | M89: =Tabela1[[#This Row],[1ª QZ]]-Tabela1[[#This Row],[SALDO FINAL]]-Tabela1[[#This Row],[SALDO CARTAO]]-Tabela1[[#This Row],[Adiantamento ]] -> 1855.89 | N89: =Tabela1[[#This Row],[SALDO REEMBOLSAR]]*$N$4 -> 0 | O89: 1855.89 | Q89: =_xlfn.XLOOKUP(Tabela1[[#This Row],[COLABORADOR]],'STATUS CARTAO'!D:D,'STATUS CARTAO'!G:G) -> Cartão ativo
A90: DAVID VICHI DE BRITO | B90: 21641472863 | C90: ATIVO | D90: REGIONAL NE | E90: CEF FACILITIES PE | F90: GERSON OLIVEIRA | G90: ROGERIO SCATAMBULO | H90: 0 | I90: 502.78 | J90: 4000 | K90: 441.43 | M90: =Tabela1[[#This Row],[1ª QZ]]-Tabela1[[#This Row],[SALDO FINAL]]-Tabela1[[#This Row],[SALDO CARTAO]]-Tabela1[[#This Row],[Adiantamento ]] -> 3055.79 | N90: =Tabela1[[#This Row],[SALDO REEMBOLSAR]]*$N$4 -> 0 | O90: 3055.79 | Q90: =_xlfn.XLOOKUP(Tabela1[[#This Row],[COLABORADOR]],'STATUS CARTAO'!D:D,'STATUS CARTAO'!G:G) -> Cartão ativo
A91: DEBORA ARAUJO FIGUEIREDO | B91: 85225720030 | C91: ATIVO | D91: REGIONAL RS | E91: DRF NOVO HAMBURGO RS | F91: ALEXANDRE GROSS | G91: EVERSON GAIDSTIECHI | H91: 669.93 | I91: 0 | J91: 750 | K91: 3 | M91: =Tabela1[[#This Row],[1ª QZ]]-Tabela1[[#This Row],[SALDO FINAL]]-Tabela1[[#This Row],[SALDO CARTAO]]-Tabela1[[#This Row],[Adiantamento ]] -> 747 | N91: =Tabela1[[#This Row],[SALDO REEMBOLSAR]]*$N$4 -> 401.958 | O91: 1081.965 | Q91: =_xlfn.XLOOKUP(Tabela1[[#This Row],[COLABORADOR]],'STATUS CARTAO'!D:D,'STATUS CARTAO'!G:G) -> Cartão ativo
A92: DEISE SOARES DE CAMPOS | B92: 69116709004 | C92: ATIVO | D92: REGIONAL SC | E92: CEF NORTE SC | F92: LEANDRO MARCUSSO | G92: EVERSON GAIDSTIECHI | H92: 0 | I92: 4948.25 | J92: 1600 | K92: 4054.99 | M92: =Tabela1[[#This Row],[1ª QZ]]-Tabela1[[#This Row],[SALDO FINAL]]-Tabela1[[#This Row],[SALDO CARTAO]]-Tabela1[[#This Row],[Adiantamento ]] -> -7403.24 | N92: =Tabela1[[#This Row],[SALDO REEMBOLSAR]]*$N$4 -> 0 | O92: 0 | Q92: =_xlfn.XLOOKUP(Tabela1[[#This Row],[COLABORADOR]],'STATUS CARTAO'!D:D,'STATUS CARTAO'!G:G) -> Cartão ativo
A93: DELVANO AILTON DA SILVA | B93: 05289382666 | C93: ATIVO | D93: REGIONAL MG | E93: NET LESTE MG | F93: HUGO ALEXANDRE | G93: MARCOS CARIAS | H93: 0 | I93: 1043.05 | J93: 750 | K93: 602.09 | M93: =Tabela1[[#This Row],[1ª QZ]]-Tabela1[[#This Row],[SALDO FINAL]]-Tabela1[[#This Row],[SALDO CARTAO]]-Tabela1[[#This Row],[Adiantamento ]] -> -895.14 | N93: =Tabela1[[#This Row],[SALDO REEMBOLSAR]]*$N$4 -> 0 | O93: 0 | Q93: =_xlfn.XLOOKUP(Tabela1[[#This Row],[COLABORADOR]],'STATUS CARTAO'!D:D,'STATUS CARTAO'!G:G) -> Cartão ativo
A94: DENILSO DIDONE | B94: 04859818903 | C94: ATIVO | D94: REGIONAL CLARO INFRA SUL | E94: CLARO INFRA SC | F94: BRUNO EDUARDO | G94: EVERSON GAIDSTIECHI | H94: 0 | I94: 368.8 | J94: 160 | K94: 0 | M94: =Tabela1[[#This Row],[1ª QZ]]-Tabela1[[#This Row],[SALDO FINAL]]-Tabela1[[#This Row],[SALDO CARTAO]]-Tabela1[[#This Row],[Adiantamento ]] -> -208.8 | N94: =Tabela1[[#This Row],[SALDO REEMBOLSAR]]*$N$4 -> 0 | O94: 0 | Q94: =_xlfn.XLOOKUP(Tabela1[[#This Row],[COLABORADOR]],'STATUS CARTAO'!D:D,'STATUS CARTAO'!G:G) -> Cartão ativo
A95: DENIS FERREIRA DA SILVA | B95: 06637541435 | C95: ATIVO | D95: REGIONAL NE | E95: ORIGEM ENERGIA AL | F95: GERSON OLIVEIRA | G95: ROGERIO SCATAMBULO | H95: 0 | I95: 711 | J95: 400 | K95: 0 | M95: =Tabela1[[#This Row],[1ª QZ]]-Tabela1[[#This Row],[SALDO FINAL]]-Tabela1[[#This Row],[SALDO CARTAO]]-Tabela1[[#This Row],[Adiantamento ]] -> -311 | N95: =Tabela1[[#This Row],[SALDO REEMBOLSAR]]*$N$4 -> 0 | O95: 0 | Q95: =_xlfn.XLOOKUP(Tabela1[[#This Row],[COLABORADOR]],'STATUS CARTAO'!D:D,'STATUS CARTAO'!G:G) -> Cartão ativo
A96: DHIEGO RIBEIRO DINIZ | B96: 00049250256 | C96: ATIVO | D96: REGIONAL CO | E96: CEF GOIANIA CO | F96: ANGELICA SOARES | G96: ROGERIO SCATAMBULO | H96: 0 | I96: 256.39 | J96: 2000 | K96: 9.37 | M96: =Tabela1[[#This Row],[1ª QZ]]-Tabela1[[#This Row],[SALDO FINAL]]-Tabela1[[#This Row],[SALDO CARTAO]]-Tabela1[[#This Row],[Adiantamento ]] -> 1734.24 | N96: =Tabela1[[#This Row],[SALDO REEMBOLSAR]]*$N$4 -> 0 | O96: 1734.24 | Q96: =_xlfn.XLOOKUP(Tabela1[[#This Row],[COLABORADOR]],'STATUS CARTAO'!D:D,'STATUS CARTAO'!G:G) -> Cartão ativo
... A104: DOUGLAS TIAGO DE OLIVEIRA | B104: 08492402989 | C104: ATIVO | D104: REGIONAL SC | E104: TRIBUNAL DE JUSTICA PR | F104: LEANDRO MARCUSSO | G104: EVERSON GAIDSTIECHI | H104: 0 | I104: 194.63 | J104: 800 | K104: 162.63 | M104: =Tabela1[[#This Row],[1ª QZ]]-Tabela1[[#This Row],[SALDO FINAL]]-Tabela1[[#This Row],[SALDO CARTAO]]-Tabela1[[#This Row],[Adiantamento ]] -> 442.74 | N104: =Tabela1[[#This Row],[SALDO REEMBOLSAR]]*$N$4 -> 0 | O104: 442.74 | Q104: =_xlfn.XLOOKUP(Tabela1[[#This Row],[COLABORADOR]],'STATUS CARTAO'!D:D,'STATUS CARTAO'!G:G) -> Cartão ativo
A105: DOUGLAS TIAGO DE OLIVEIRA | B105: 08492402989 | D105: REGIONAL SC | E105: TRIBUNAL DE JUSTICA PR | M105: =Tabela1[[#This Row],[1ª QZ]]-Tabela1[[#This Row],[SALDO FINAL]]-Tabela1[[#This Row],[SALDO CARTAO]]-Tabela1[[#This Row],[Adiantamento ]] -> 0 | N105: =Tabela1[[#This Row],[SALDO REEMBOLSAR]]*$N$4 -> 0 | O105: 194.63 | Q105: =_xlfn.XLOOKUP(Tabela1[[#This Row],[COLABORADOR]],'STATUS CARTAO'!D:D,'STATUS CARTAO'!G:G) -> Cartão ativo
A106: DOUGLAS WESLEN CARDOSO DOS SANTOS | B106: 08784554932 | C106: ATIVO | D106: REGIONAL SC | E106: TRIBUNAL DE JUSTICA PR | F106: LEANDRO MARCUSSO | G106: EVERSON GAIDSTIECHI | H106: 0 | I106: 1079.9 | J106: 800 | K106: 0.3 | M106: =Tabela1[[#This Row],[1ª QZ]]-Tabela1[[#This Row],[SALDO FINAL]]-Tabela1[[#This Row],[SALDO CARTAO]]-Tabela1[[#This Row],[Adiantamento ]] -> -280.2 | N106: =Tabela1[[#This Row],[SALDO REEMBOLSAR]]*$N$4 -> 0 | O106: 0 | Q106: =_xlfn.XLOOKUP(Tabela1[[#This Row],[COLABORADOR]],'STATUS CARTAO'!D:D,'STATUS CARTAO'!G:G) -> Cartão ativo
A107: EDER AUGUSTO DE ARAUJO CARVALHO | B107: 03985382638 | C107: ATIVO | D107: REGIONAL MG | E107: CLARO INFRA MG | F107: HUGO ALEXANDRE | G107: MARCOS CARIAS | H107: 713.4 | I107: 0 | J107: 1500 | K107: 36.15 | M107: =Tabela1[[#This Row],[1ª QZ]]-Tabela1[[#This Row],[SALDO FINAL]]-Tabela1[[#This Row],[SALDO CARTAO]]-Tabela1[[#This Row],[Adiantamento ]] -> 1463.85 | N107: =Tabela1[[#This Row],[SALDO REEMBOLSAR]]*$N$4 -> 428.04 | O107: 1820.55 | Q107: =_xlfn.XLOOKUP(Tabela1[[#This Row],[COLABORADOR]],'STATUS CARTAO'!D:D,'STATUS CARTAO'!G:G) -> Cartão ativo
A108: EDER MEDICI | B108: 03040370952 | C108: ATIVO | D108: REGIONAL CLARO INFRA SUL | E108: CLARO INFRA PR | F108: BRUNO EDUARDO | G108: EVERSON GAIDSTIECHI | H108: 0 | I108: 130 | J108: 100 | K108: 45 | M108: =Tabela1[[#This Row],[1ª QZ]]-Tabela1[[#This Row],[SALDO FINAL]]-Tabela1[[#This Row],[SALDO CARTAO]]-Tabela1[[#This Row],[Adiantamento ]] -> -75 | N108: =Tabela1[[#This Row],[SALDO REEMBOLSAR]]*$N$4 -> 0 | O108: 0 | Q108: =_xlfn.XLOOKUP(Tabela1[[#This Row],[COLABORADOR]],'STATUS CARTAO'!D:D,'STATUS CARTAO'!G:G) -> Cartão ativo
A109: EDERSON LUIS BARROS DA ROSA | B109: 04614285988 | C109: ATIVO | D109: REGIONAL CLARO INFRA SUL | E109: CLARO INFRA PR | F109: BRUNO EDUARDO | G109: EVERSON GAIDSTIECHI | H109: 212.01 | I109: 0 | J109: 300 | K109: 51.06 | M109: =Tabela1[[#This Row],[1ª QZ]]-Tabela1[[#This Row],[SALDO FINAL]]-Tabela1[[#This Row],[SALDO CARTAO]]-Tabela1[[#This Row],[Adiantamento ]] -> 248.94 | N109: =Tabela1[[#This Row],[SALDO REEMBOLSAR]]*$N$4 -> 127.206 | O109: 354.945 | Q109: =_xlfn.XLOOKUP(Tabela1[[#This Row],[COLABORADOR]],'STATUS CARTAO'!D:D,'STATUS CARTAO'!G:G) -> Cartão ativo
A110: EDEVALDO DUTRA GONCALVES | B110: 00312735057 | C110: ATIVO | D110: REGIONAL SC | E110: NET LITORAL PR | F110: LEANDRO MARCUSSO | G110: EVERSON GAIDSTIECHI | H110: 0 | I110: 915.3 | J110: 400 | K110: 19 | M110: =Tabela1[[#This Row],[1ª QZ]]-Tabela1[[#This Row],[SALDO FINAL]]-Tabela1[[#This Row],[SALDO CARTAO]]-Tabela1[[#This Row],[Adiantamento ]] -> -534.3 | N110: =Tabela1[[#This Row],[SALDO REEMBOLSAR]]*$N$4 -> 0 | O110: 0 | Q110: =_xlfn.XLOOKUP(Tabela1[[#This Row],[COLABORADOR]],'STATUS CARTAO'!D:D,'STATUS CARTAO'!G:G) -> Cartão ativo
A111: EDIBERTO GEORGE RELIQUIAS | B111: 34596010862 | C111: ATIVO | D111: REGIONAL SP | E111: CEF FACILITIES SP | F111: LEANDRO NUNES | G111: EVERSON GAIDSTIECHI | H111: 0 | I111: 702.3 | J111: 675 | K111: 168 | M111: =Tabela1[[#This Row],[1ª QZ]]-Tabela1[[#This Row],[SALDO FINAL]]-Tabela1[[#This Row],[SALDO CARTAO]]-Tabela1[[#This Row],[Adiantamento ]] -> -195.3 | N111: =Tabela1[[#This Row],[SALDO REEMBOLSAR]]*$N$4 -> 0 | O111: 0 | Q111: =_xlfn.XLOOKUP(Tabela1[[#This Row],[COLABORADOR]],'STATUS CARTAO'!D:D,'STATUS CARTAO'!G:G) -> Cartão ativo
A112: EDIPO SANTOS BARRETO | B112: 37896893860 | C112: ATIVO | D112: REGIONAL SP | E112: TRIBUNAL DE JUSTICA SP | F112: LEANDRO NUNES | G112: EVERSON GAIDSTIECHI | H112: 0 | I112: 385.99 | J112: 1600 | K112: 16.27 | M112: =Tabela1[[#This Row],[1ª QZ]]-Tabela1[[#This Row],[SALDO FINAL]]-Tabela1[[#This Row],[SALDO CARTAO]]-Tabela1[[#This Row],[Adiantamento ]] -> 1197.74 | N112: =Tabela1[[#This Row],[SALDO REEMBOLSAR]]*$N$4 -> 0 | O112: 1197.74 | Q112: =_xlfn.XLOOKUP(Tabela1[[#This Row],[COLABORADOR]],'STATUS CARTAO'!D:D,'STATUS CARTAO'!G:G) -> Cartão ativo
A113: EDMAR FERREIRA CARDOSO | B113: 06311884607 | C113: ATIVO | D113: REGIONAL MG | E113: NET METROPOLITANA MG | F113: HUGO ALEXANDRE | G113: MARCOS CARIAS | H113: 0 | I113: 590.26 | J113: 750 | K113: 0 | M113: =Tabela1[[#This Row],[1ª QZ]]-Tabela1[[#This Row],[SALDO FINAL]]-Tabela1[[#This Row],[SALDO CARTAO]]-Tabela1[[#This Row],[Adiantamento ]] -> 159.74 | N113: =Tabela1[[#This Row],[SALDO REEMBOLSAR]]*$N$4 -> 0 | O113: 159.74 | Q113: =_xlfn.XLOOKUP(Tabela1[[#This Row],[COLABORADOR]],'STATUS CARTAO'!D:D,'STATUS CARTAO'!G:G) -> Cartão ativo
A114: EDSON CALIXTO THOMAZ | B114: 05765681719 | C114: ATIVO | D114: REGIONAL RJ | E114: CEF INTERIOR RJ | F114: ALLAN JEFFERSON | G114: ROGERIO SCATAMBULO | H114: 771.58 | I114: 0 | J114: 1000 | K114: 3 | M114: =Tabela1[[#This Row],[1ª QZ]]-Tabela1[[#This Row],[SALDO FINAL]]-Tabela1[[#This Row],[SALDO CARTAO]]-Tabela1[[#This Row],[Adiantamento ]] -> 997 | N114: =Tabela1[[#This Row],[SALDO REEMBOLSAR]]*$N$4 -> 462.948 | O114: 1382.79 | Q114: =_xlfn.XLOOKUP(Tabela1[[#This Row],[COLABORADOR]],'STATUS CARTAO'!D:D,'STATUS CARTAO'!G:G) -> Cartão ativo
A115: EDSON VEIGA SILVEIRA | B115: 62063774072 | C115: ATIVO | D115: REGIONAL CO | E115: CLARO CO | F115: ANGELICA SOARES | G115: ROGERIO SCATAMBULO | H115: 514.27 | I115: 0 | J115: 400 | K115: 15 | M115: =Tabela1[[#This Row],[1ª QZ]]-Tabela1[[#This Row],[SALDO FINAL]]-Tabela1[[#This Row],[SALDO CARTAO]]-Tabela1[[#This Row],[Adiantamento ]] -> 385 | N115: =Tabela1[[#This Row],[SALDO REEMBOLSAR]]*$N$4 -> 308.562 | O115: 642.135 | Q115: =_xlfn.XLOOKUP(Tabela1[[#This Row],[COLABORADOR]],'STATUS CARTAO'!D:D,'STATUS CARTAO'!G:G) -> Cartão ativo
A116: EDUARDO ANDREY VENSON SILVA | B116: 02960685946 | C116: ATIVO | D116: REGIONAL SC | E116: CEF OESTE SC | F116: LEANDRO MARCUSSO | G116: EVERSON GAIDSTIECHI | H116: 0 | I116: 4470.45 | J116: 4000 | K116: 3.3 | M116: =Tabela1[[#This Row],[1ª QZ]]-Tabela1[[#This Row],[SALDO FINAL]]-Tabela1[[#This Row],[SALDO CARTAO]]-Tabela1[[#This Row],[Adiantamento ]] -> -473.75 | N116: =Tabela1[[#This Row],[SALDO REEMBOLSAR]]*$N$4 -> 0 | O116: 0 | Q116: =_xlfn.XLOOKUP(Tabela1[[#This Row],[COLABORADOR]],'STATUS CARTAO'!D:D,'STATUS CARTAO'!G:G) -> Cartão ativo
A117: EDUARDO FRAGA DOS REIS | B117: 04050867095 | C117: ATIVO | D117: REGIONAL RS | E117: ADM FILIAL RS | F117: ALEXANDRE GROSS | G117: EVERSON GAIDSTIECHI | H117: 0 | I117: 450.67 | J117: 1000 | K117: 438.17 | L117: 1000 | M117: =Tabela1[[#This Row],[1ª QZ]]-Tabela1[[#This Row],[SALDO FINAL]]-Tabela1[[#This Row],[SALDO CARTAO]]-Tabela1[[#This Row],[Adiantamento ]] -> -888.84 | N117: =Tabela1[[#This Row],[SALDO REEMBOLSAR]]*$N$4 -> 0 | O117: 0 | Q117: =_xlfn.XLOOKUP(Tabela1[[#This Row],[COLABORADOR]],'STATUS CARTAO'!D:D,'STATUS CARTAO'!G:G) -> Cartão ativo
A118: EDUARDO SANTOS | B118: 91270529072 | C118: ATIVO | D118: REGIONAL RS | E118: NET APOIO RS | F118: ALEXANDRE GROSS | G118: EVERSON GAIDSTIECHI | H118: 0 | I118: 964.99 | J118: 2500 | K118: 1106.25 | M118: =Tabela1[[#This Row],[1ª QZ]]-Tabela1[[#This Row],[SALDO FINAL]]-Tabela1[[#This Row],[SALDO CARTAO]]-Tabela1[[#This Row],[Adiantamento ]] -> 428.76 | N118: =Tabela1[[#This Row],[SALDO REEMBOLSAR]]*$N$4 -> 0 | O118: 428.76 | Q118: =_xlfn.XLOOKUP(Tabela1[[#This Row],[COLABORADOR]],'STATUS CARTAO'!D:D,'STATUS CARTAO'!G:G) -> Cartão ativo
A119: EDUARDO SANTOS | B119: 91270529072 | D119: REGIONAL RS | E119: NET APOIO RS | M119: =Tabela1[[#This Row],[1ª QZ]]-Tabela1[[#This Row],[SALDO FINAL]]-Tabela1[[#This Row],[SALDO CARTAO]]-Tabela1[[#This Row],[Adiantamento ]] -> 0 | N119: =Tabela1[[#This Row],[SALDO REEMBOLSAR]]*$N$4 -> 0 | O119: 964.99 | Q119: =_xlfn.XLOOKUP(Tabela1[[#This Row],[COLABORADOR]],'STATUS CARTAO'!D:D,'STATUS CARTAO'!G:G) -> Cartão ativo
A120: ELIANDRO BRUNING | B120: 00461757923 | C120: ATIVO | D120: REGIONAL SC | E120: TRIBUNAL DE JUSTICA PR | F120: LEANDRO MARCUSSO | G120: EVERSON GAIDSTIECHI | H120: 0 | I120: 537.79 | J120: 800 | K120: 437.79 | M120: =Tabela1[[#This Row],[1ª QZ]]-Tabela1[[#This Row],[SALDO FINAL]]-Tabela1[[#This Row],[SALDO CARTAO]]-Tabela1[[#This Row],[Adiantamento ]] -> -175.58 | N120: =Tabela1[[#This Row],[SALDO REEMBOLSAR]]*$N$4 -> 0 | O120: 0 | Q120: =_xlfn.XLOOKUP(Tabela1[[#This Row],[COLABORADOR]],'STATUS CARTAO'!D:D,'STATUS CARTAO'!G:G) -> Cartão ativo
A121: ELIANDRO BRUNING | B121: 00461757923 | D121: REGIONAL SC | E121: TRIBUNAL DE JUSTICA PR | M121: =Tabela1[[#This Row],[1ª QZ]]-Tabela1[[#This Row],[SALDO FINAL]]-Tabela1[[#This Row],[SALDO CARTAO]]-Tabela1[[#This Row],[Adiantamento ]] -> 0 | N121: =Tabela1[[#This Row],[SALDO REEMBOLSAR]]*$N$4 -> 0 | O121: 362.21 | Q121: =_xlfn.XLOOKUP(Tabela1[[#This Row],[COLABORADOR]],'STATUS CARTAO'!D:D,'STATUS CARTAO'!G:G) -> Cartão ativo
A122: EMERSON CHOUBI PRADO | B122: 29722576852 | C122: ATIVO | D122: REGIONAL SP | E122: TRIBUNAL DE JUSTICA SP | F122: LEANDRO NUNES | G122: EVERSON GAIDSTIECHI | H122: 0 | I122: 895 | J122: 800 | K122: 697 | M122: =Tabela1[[#This Row],[1ª QZ]]-Tabela1[[#This Row],[SALDO FINAL]]-Tabela1[[#This Row],[SALDO CARTAO]]-Tabela1[[#This Row],[Adiantamento ]] -> -792 | N122: =Tabela1[[#This Row],[SALDO REEMBOLSAR]]*$N$4 -> 0 | O122: 0 | Q122: =_xlfn.XLOOKUP(Tabela1[[#This Row],[COLABORADOR]],'STATUS CARTAO'!D:D,'STATUS CARTAO'!G:G) -> Cartão ativo
...

Sheet Planilha1
B2: COLABORADOR | C2: CPF | D2: SITUAÇÃO | E2: REGIONAL | F2: CENTRO DE CUSTO | G2: COD. CENTRO DE CUSTO | H2: GESTOR | I2: Carga Final | K2: Rótulos de Linha | L2: Soma de Carga Final
B3: CHARLYTON COSTA ANDRADE | C3: 01050938232 | D3: ATIVO | E3: REGIONAL CO | F3: CEF AM AC RR | G3: 11030290001 | H3: ANGELICA SOARES | I3: 13149.29 | K3: 1201014 | L3: 926.515
B4: RAFAEL AMORIM VELLO | C4: 01677920599 | D4: ATIVO | E4: REGIONAL NE | F4: CEF NORTE OESTE BA | G4: 11030260001 | H4: GERSON OLIVEIRA | I4: 13690.57 | K4: 1201017 | L4: 388.93
B5: CARLOS RENATO PACHECO DA SILVA | C5: 90443306087 | D5: ATIVO | E5: REGIONAL RS | F5: CEF LESTE GAUCHO RS | G5: 11030580001 | H5: ALEXANDRE GROSS | I5: 3830.545 | K5: 1201020 | L5: 3000
B6: SANDRO BARRETO DE SOUZA | C6: 78021324953 | D6: ATIVO | E6: REGIONAL SC | F6: CEF SUL SC | G6: 11030700001 | H6: LEANDRO MARCUSSO | I6: 5250.44 | K6: 1201071 | L6: 1588.425
B7: CLAUDEMIR GREGOSKI RODRIGUES | C7: 05144026958 | D7: ATIVO | E7: REGIONAL SC | F7: CEF FACILITIES CURITIBA PR | G7: 11030860001 | H7: LEANDRO MARCUSSO | I7: 1950 | K7: 1104150001 | L7: 3110.3
B8: LEANDRO GUSMAO MUNIZ | C8: 13126691790 | D8: ATIVO | E8: REGIONAL RJ | F8: CEF INTERIOR RJ | G8: 11030870001 | H8: ALLAN JEFFERSON | I8: 2272.45 | K8: 11010060001 | L8: 738.48
B9: LUCAS MARTINS MACAN | C9: 00975748998 | D9: ATIVO | E9: REGIONAL NE | F9: CEF CEARA | G9: 11030890001 | H9: GERSON OLIVEIRA | I9: 3920.34 | K9: 11010080001 | L9: 751.5
B10: JOSE CARLOS BATISTA | C10: 26652452804 | D10: ATIVO | E10: REGIONAL SP | F10: PTB INFRA SUDESTE | G10: 11080170001 | H10: LEANDRO NUNES | I10: 5586.18 | K10: 11010110001 | L10: 843.82
B11: SAULO ARAUJO DE PAULA | C11: 31040091806 | D11: ATIVO | E11: REGIONAL SP | F11: CEF SP SUL | G11: 11030750001 | H11: LEANDRO NUNES | I11: 3319.26 | K11: 11010150001 | L11: 220
B12: VICTOR SIGOLO PINHEIRO PIMENTA | C12: 12237490619 | D12: ATIVO | E12: REGIONAL SP | F12: INSS SP | G12: 11062640001 | H12: LEANDRO NUNES | I12: 1856.69 | K12: 11010170001 | L12: 1787.705
B13: MARCO AURELIO DE ANDRADE MORAES | C13: 72756284220 | D13: ATIVO | E13: REGIONAL CO | F13: CEF AM AC RR | G13: 11030290001 | H13: ANGELICA SOARES | I13: 4685.92 | K13: 11010180001 | L13: 3315.12
B14: MARCELO GIMENEZ ARGEMON | C14: 95073272153 | D14: ATIVO | E14: REGIONAL SP | F14: CEF FACILITIES CAMPINAS SP | G14: 11030780001 | H14: LEANDRO NUNES | I14: 2622 | K14: 11010270001 | L14: 199.9
... B92: LUAN THIAGO DA SILVA | C92: 08030478437 | D92: ATIVO | E92: REGIONAL CLARO INFRA NORDESTE | F92: CLARO INFRA NORDESTE | G92: 11040170001 | H92: FELIPE JOSE | I92: 916.48 | K92: 11110340001 | L92: 920.18
B93: RICARDO ZORZETTO | C93: 00539580040 | D93: ATIVO | E93: REGIONAL RS | F93: CEF QUERENCIA RS | G93: 11030650001 | H93: ALEXANDRE GROSS | I93: 1305.025 | K93: Total Geral | L93: 268239.94
B94: WILLIAM NORONHA TEIXEIRA | C94: 02013700008 | D94: ATIVO | E94: REGIONAL RS | F94: NET APOIO RS | G94: 11061770001 | H94: ALEXANDRE GROSS | I94: 499.675
B95: RONALDO DE MATOS LELIS | C95: 47502843604 | D95: ATIVO | E95: REGIONAL MG | F95: CLARO INFRA MG | G95: 11040160001 | H95: HUGO ALEXANDRE | I95: 766.125
B96: JAEDER RODRIGUES JUNIOR | C96: 07505987607 | D96: ATIVO | E96: REGIONAL MG | F96: CEF NORDESTE MG | G96: 11030660001 | H96: HUGO ALEXANDRE | I96: 7264.135
B97: SILVIO VINICIUS PINHEIRO GOES | C97: 51182084168 | D97: ATIVO | E97: REGIONAL CO | F97: CLARO CO | G97: 11040040001 | H97: ANGELICA SOARES | I97: 298.08
B98: MARCIO BOUZAS FERREIRA | C98: 07318362780 | D98: ATIVO | E98: REGIONAL RJ | F98: VTAL CYBER RJ | G98: 11110340001 | H98: ALLAN JEFFERSON | I98: 920.18
B99: CLAUDINEI AMARAL | C99: 10433881844 | D99: ATIVO | E99: REGIONAL SC | F99: TRIBUNAL DE JUSTICA PR | G99: 11061720001 | H99: LEANDRO MARCUSSO | I99: 1095.285
B100: DIEGO JOSE DE PAULO | C100: 01553544692 | D100: ATIVO | E100: REGIONAL MG | F100: CLARO INFRA MG | G100: 11040160001 | H100: HUGO ALEXANDRE | I100: 1590.325
B101: ANDERSON BICA PEREZ | C101: 00053957040 | D101: ATIVO | E101: REGIONAL RS | F101: NET PORTO ALEGRE RS | G101: 11061820001 | H101: ALEXANDRE GROSS | I101: 678.795
B102: JAQUELINE ONORIO DOS SANTOS ALVES | C102: 37258325875 | D102: ATIVO | E102: REGIONAL SP | F102: TELEFONICA SP | G102: 11061420001 | H102: LEANDRO NUNES | I102: 1685.215
B103: AURO MOREIRA PEDROSO | C103: 32060157900 | D103: ATIVO | E103: REGIONAL SC | F103: BB NORTE OESTE PR | G103: 11010370001 | H103: LEANDRO MARCUSSO | I103: 740.305
B104: DANIEL SANTOS DE ASSUNCAO | C104: 97592439549 | D104: ATIVO | E104: REGIONAL NE | F104: BANCO ITAU BA | G104: 11062270001 | H104: GERSON OLIVEIRA | I104: 1661.21
B105: MOISES DOS SANTOS CABRAL | C105: 68746458204 | D105: ATIVO | E105: REGIONAL CO | F105: CEF FAC RO | G105: 11030810001 | H105: ANGELICA SOARES | I105: 541.35
... B170: ISAIAS DA SILVA | C170: 04083479965 | D170: ATIVO | E170: REGIONAL SC | F170: TRIBUNAL DE JUSTICA PR | G170: 11061720001 | H170: LEANDRO MARCUSSO | I170: 804.9
B171: SILVIO VINICIUS PINHEIRO GOES | C171: 51182084168 | E171: REGIONAL CO | F171: CLARO CO | G171: 11040040001 | I171: 5401.92
B172: FLAVIO FERNANDES DOS REIS LIMA | C172: 01767960107 | E172: REGIONAL CO | F172: TELEFONICA CO | G172: 11061430001 | I172: 3436.77
B173: WALTER DE CAMPOS NUNES NETO | C173: 99114160030 | E173: REGIONAL CLARO INFRA SUL | F173: CLARO INFRA RS | G173: 1104150001 | I173: 2810.3
B174: CAIOS VINICIUS NUNES BROERING | C174: 07053418952 | E174: REGIONAL CLARO INFRA SUL | F174: CLARO INFRA SC | G174: 11040130001 | I174: 2165.74
B175: JOELSON FERREIRA DOS SANTOS | C175: 07690263623 | E175: REGIONAL MG | F175: CEF SUDESTE MG | G175: 11060700001 | I175: 1816.75
B176: DANIEL DA SILVA LOPES | C176: 94288259053 | E176: REGIONAL SC | F176: NET APOIO SC | G176: 11061200001 | I176: 1741.55
B177: PAULO NILTON COSTA MOREIRA | C177: 45159599053 | E177: REGIONAL RS | F177: CEF EXTREMO SUL RS | G177: 11030590001 | I177: 1525.98
B178: PATRICK ANTONIEVICZ ALVES | C178: 06456801923 | E178: REGIONAL SC | F178: TRIBUNAL DE JUSTICA PR | G178: 11061720001 | I178: 1379
B179: FRANCIELLY FELIX CAVALCANTE DE ANDRADE | C179: 09276240446 | E179: REGIONAL CO | F179: CEF AM AC RR | G179: 11030290001 | I179: 1000
B180: LUCAS RODRIGUES DE MOURA GALVAO | C180: 04013986175 | E180: REGIONAL CO | F180: CEF GOIANIA CO | G180: 11030850001 | I180: 998.98
B181: EDUARDO SANTOS | C181: 91270529072 | E181: REGIONAL RS | F181: NET APOIO RS | G181: 11061770001 | I181: 964.99
B182: FABIO PROVESI | C182: 05731312958 | E182: REGIONAL SC | F182: BB SERET SC | G182: 11010180001 | I182: 668.02
... B215: WELTON GERALDO WROBLEWSKI | C215: 91443130982 | E215: REGIONAL SC | F215: TRIBUNAL DE JUSTICA PR | G215: 11061720001 | I215: 101.85

Sheet RETIRAR
B2: COLABORADOR | C2: CPF | D2: SITUAÇÃO | E2: REGIONAL | F2: CENTRO DE CUSTO | G2: GESTOR | H2: DIRETOR | I2: SALDO REEMBOLSAR | J2: REEMBOLSO FEITO | K2: REEMBOLSO CORRETO | L2: RETIRAR
B3: CARLOS RENATO PACHECO DA SILVA | C3: 90443306087 | D3: ATIVO | E3: REGIONAL RS | F3: CEF LESTE GAUCHO RS | G3: ALEXANDRE GROSS | H3: EVERSON GAIDSTIECHI | I3: 2222.63 | J3: 1333.578 | K3: 1111.315 | L3: 222.263
B4: SANDRO BARRETO DE SOUZA | C4: 78021324953 | D4: ATIVO | E4: REGIONAL SC | F4: CEF SUL SC | G4: LEANDRO MARCUSSO | H4: EVERSON GAIDSTIECHI | I4: 2038.88 | J4: 1223.328 | K4: 1019.44 | L4: 203.888
B5: CLAUDEMIR GREGOSKI RODRIGUES | C5: 05144026958 | D5: ATIVO | E5: REGIONAL SC | F5: CEF FACILITIES CURITIBA PR | G5: LEANDRO MARCUSSO | H5: EVERSON GAIDSTIECHI | I5: 1900 | J5: 1140 | K5: 950 | L5: 190
B6: LEANDRO GUSMAO MUNIZ | C6: 13126691790 | D6: ATIVO | E6: REGIONAL RJ | F6: CEF INTERIOR RJ | G6: ALLAN JEFFERSON | H6: ROGERIO SCATAMBULO | I6: 1545 | J6: 927 | K6: 772.5 | L6: 154.5
B7: MARCELO GIMENEZ ARGEMON | C7: 95073272153 | D7: ATIVO | E7: REGIONAL SP | F7: CEF FACILITIES CAMPINAS SP | G7: LEANDRO NUNES | H7: EVERSON GAIDSTIECHI | I7: 1256 | J7: 753.6 | K7: 628 | L7: 125.6
B8: MARIA EDUARDA ARAGAO | C8: 10363402950 | D8: ATIVO | E8: REGIONAL SC | F8: CEF SUL SC | G8: LEANDRO MARCUSSO | H8: EVERSON GAIDSTIECHI | I8: 960.45 | J8: 576.27 | K8: 480.225 | L8: 96.045
B9: GUILHERME MOTTA RIBEIRO SILVA | C9: 11178519740 | D9: ATIVO | E9: REGIONAL ES | F9: CEF ES | G9: VINICIUS LOCATELLY | H9: MARCOS CARIAS | I9: 921.06 | J9: 552.636 | K9: 460.53 | L9: 92.106
B10: JUNIO VICENTE BARBOSA | C10: 10054353670 | D10: ATIVO | E10: REGIONAL MG | F10: CEF NORDESTE MG | G10: HUGO ALEXANDRE | H10: MARCOS CARIAS | I10: 848.61 | J10: 509.166 | K10: 424.305 | L10: 84.861
B11: TEOFILO TOLLENDAL PACHECO | C11: 26687333836 | D11: ATIVO | E11: REGIONAL SP | F11: TELEFONICA SP | G11: LEANDRO NUNES | H11: EVERSON GAIDSTIECHI | I11: 818.79 | J11: 491.274 | K11: 409.395 | L11: 81.879
B12: MARCELO DE ANDRADE CALVETTI | C12: 02587708052 | D12: ATIVO | E12: REGIONAL RS | F12: NET PORTO ALEGRE RS | G12: ALEXANDRE GROSS | H12: EVERSON GAIDSTIECHI | I12: 807.82 | J12: 484.692 | K12: 403.91 | L12: 80.782
B13: LEANDRO MARCUSSO | C13: 01857561902 | D13: ATIVO | E13: REGIONAL SC | F13: ADM FILIAL SC | G13: LEANDRO MARCUSSO | H13: EVERSON GAIDSTIECHI | I13: 806.09 | J13: 483.654 | K13: 403.045 | L13: 80.609
B14: JOSE JONAS FURLANETTO | C14: 55889913115 | D14: ATIVO | E14: REGIONAL SC | F14: BB NORTE OESTE PR | G14: LEANDRO MARCUSSO | H14: EVERSON GAIDSTIECHI | I14: 803.22 | J14: 481.932 | K14: 401.61 | L14: 80.322
... B59: ISAIAS DA SILVA | C59: 04083479965 | D59: ATIVO | E59: REGIONAL SC | F59: TRIBUNAL DE JUSTICA PR | G59: LEANDRO MARCUSSO | H59: EVERSON GAIDSTIECHI | I59: 10.02 | J59: 6.012 | K59: 5.01 | L59: 1.002

Sheet STATUS CARTAO
C2: Cobrança | D2: Nome | E2: E-mail | F2: Tipo de usuário | G2: Status do Cartão | H2: Permissão de Uso | I2: Permissão de Gestão | J2: Ações
D3: ABNER ANDRADE CAVALCANTE | E3: abner.cavalcante@eqsengenharia.com.br | F3: Normal | G3: Cartão ativo | H3: Portador de Cartão | I3: Sem permissão
D4: ADAN LEONARDO SOUZA BATISTA | E4: adan.batista@eqsengenharia.com.br | F4: Normal | G4: Cartão ativo | H4: Portador de Cartão | I4: Sem permissão
D5: ADAUTO JOSE PEREIRA | E5: adautojosepereira@yahoo.com.br | F5: Normal | G5: Cartão ativo | H5: Portador de Cartão | I5: Sem permissão
D6: ADEMARCIO DUARTE LOPES | E6: ctba_projetos@hotmail.com | F6: Normal | G6: Cartão ativo | H6: Portador de Cartão | I6: Sem permissão
D7: ADILSON ANTONIO JACINTO | E7: dirson4867@yahoo.com | F7: Normal | G7: Cartão ativo | H7: Portador de Cartão | I7: Sem permissão
D8: ADILSON MELLO DE CAMARGO | E8: adilsoncamargo@eqseng.com.br | F8: Normal | G8: Cartão ativo | H8: Portador de Cartão | I8: Sem permissão
D9: ADILSON RODRIGUES FERREIRA | E9: adilson.ferreira@eqsengenharia.com.br | F9: Intermediário | G9: Cadastro pendente | H9: Portador de Cartão | I9: Sem permissão
D10: ADIVAR ANTONIO DA SILVA JUNIOR | E10: adivarjunior@gmail.com | F10: Normal | G10: Cartão ativo | H10: Portador de Cartão | I10: Sem permissão
D11: ADMILSON DA SILVA FARIAS | E11: admilsonfarias2016@gmail.com | F11: Normal | G11: Cadastro pendente | H11: Portador de Cartão | I11: Sem permissão
D12: ADMILSON DOS SANTOS GALAN | E12: admilsongalan@gmail.com | F12: Normal | G12: Cartão ativo | H12: Portador de Cartão | I12: Sem permissão
D13: ADRIANA DA CONCEICAO PEREIRA DE MELO | E13: adriana.melo@eqsengenharia.com.br | F13: Normal | G13: Cadastro pendente | H13: Portador de Cartão | I13: Sem permissão
D14: ADRIANE CARON | E14: adriane.caron@eqseng.com.br | F14: Normal | G14: Cartão ativo | H14: Portador de Cartão | I14: Sem permissão
... D52: ANDRE ARANHA MEISTER | E52: andre.meister@eqsengenharia.com.br | F52: Normal | G52: Cartão ativo | H52: Portador de Cartão | I52: Sem permissão
C53: Cobrança | D53: Nome | E53: E-mail | F53: Tipo de usuário | G53: Status do Cartão | H53: Permissão de Uso | I53: Permissão de Gestão | J53: Ações
D54: ANDRE DE MOURA ESCOBAR | E54: andre.escobar@eqseng.com.br | F54: Normal | G54: Cartão ativo | H54: Portador de Cartão | I54: Sem permissão
D55: ANDRE LUIZ DOS SANTOS OLIVEIRA | E55: andre.oliveira.supervisor.telecom@gmail.com | F55: Normal | G55: Cadastro pendente | H55: Portador de Cartão | I55: Sem permissão
D56: ANDRE LUIZ SANTANA | E56: andre.santana@eqsengenharia.com.br | F56: Normal | G56: Cartão ativo | H56: Portador de Cartão | I56: Sem permissão
D57: ANDRE PINHEIRO BALOTIN | E57: andre.balotin@eqsengenharia.com.br | F57: Normal | G57: Cartão ativo | H57: Portador de Cartão | I57: Sem permissão
D58: ANDRE VALERIO DE PAIVA | E58: toxcroen@gmail.com | F58: Normal | G58: Cartão ativo | H58: Portador de Cartão | I58: Sem permissão
D59: ANDREA ANTUNES GOMES | E59: andrea.antunes@eqsengenharia.com.br | F59: Normal | G59: Cartão ativo | H59: Portador de Cartão | I59: Sem permissão
D60: ANDRESA INDIRA SANTANA AGGIO | E60: andresa.aggio@eqsengenharia.com.br | F60: Normal | G60: Cartão ativo | H60: Portador de Cartão | I60: Sem permissão
D61: ANDREY CARDOSO REGINALDO | E61: andrey.reginaldo@eqsengenharia.com.br | F61: Administrador | G61: Cadastro pendente | H61: Portador de Cartão | I61: Gestor de Contas
D62: ANELISE MENDONCA DE AVILA | E62: anelise@eqsengenharia.com.br | F62: Normal | G62: Cartão ativo | H62: Portador de Cartão | I62: Sem permissão
D63: Angelica Sampaio Sousa | E63: angelica.sousa@eqsengenharia.com.br | F63: Normal | G63: Cartão ativo | H63: Portador de Cartão | I63: Sem permissão
D64: ANGELICA SOARES AMARANTE SILVA | E64: angelica.amarante@eqsengenharia.com.br | F64: Intermediário | G64: Cartão ativo | H64: Portador de Cartão | I64: Sem permissão
D65: ANTONIO DE PADUA LEITE | E65: antonio@eqseng.com.br | F65: Normal | G65: Cartão ativo | H65: Portador de Cartão | I65: Sem permissão
... D103: CHARLES NEVES MATTIUZZI | E103: cmattyuzzy@gmail.com | F103: Normal | G103: Cartão ativo | H103: Portador de Cartão | I103: Sem permissão
C104: Cobrança | D104: Nome | E104: E-mail | F104: Tipo de usuário | G104: Status do Cartão | H104: Permissão de Uso | I104: Permissão de Gestão | J104: Ações
D105: CHARLYTON COSTA ANDRADE | E105: charlyton.andrade@eqsengenharia.com.br | F105: Normal | G105: Cartão ativo | H105: Portador de Cartão | I105: Sem permissão
D106: CINTIA DOS SANTOS RABELO | E106: cintia.rabelo@eqsengenharia.com.br | F106: Normal | G106: Cartão ativo | H106: Portador de Cartão | I106: Sem permissão
D107: CLAUDEMIR GREGOSKI RODRIGUES | E107: claudemir.rodrigues@eqsengenharia.com.br | F107: Normal | G107: Cartão ativo | H107: Portador de Cartão | I107: Sem permissão
D108: CLAUDEMIR MOREIRA | E108: claudemir.moreura054@gmail.com | F108: Normal | G108: Cartão ativo | H108: Portador de Cartão | I108: Sem permissão
D109: CLAUDINEI AMARAL | E109: amaralclaudinei@hotmail.com | F109: Normal | G109: Cartão ativo | H109: Portador de Cartão | I109: Sem permissão
D110: CLAUDINEI VICENTE DE LIMA | E110: claudinei.lima@eqsengenharia.com.br | F110: Normal | G110: Cartão ativo | H110: Portador de Cartão | I110: Sem permissão
D111: CLAUDIO DONIZETE DA SILVA | E111: claudiodonizete8321@gmail.com | F111: Normal | G111: Cartão ativo | H111: Portador de Cartão | I111: Sem permissão
D112: CLAUDIO RENALDI NUNES | E112: clrenaldinunes@gmail.com | F112: Normal | G112: Cartão ativo | H112: Portador de Cartão | I112: Sem permissão
D113: CLAYTON DE OLIVEIRA | E113: claytonpr@gmail.com | F113: Normal | G113: Cartão ativo | H113: Portador de Cartão | I113: Sem permissão
D114: CLEBERSON APARECIDO BORGES DOS SANTOS | E114: binhoclebersonsantos@gmail.com | F114: Normal | G114: Cartão ativo | H114: Portador de Cartão | I114: Sem permissão
D115: CLEDIVALDO DINIZ BERNARDO | E115: DINIZCLEDIVALDO@GMAIL.COM | F115: Normal | G115: Cartão não habilitado | H115: Sem permissão | I115: Sem permissão
D116: CLEITON DA SILVA MONTALVAO | E116: cleiton.montalvao@eqsengenharia.com.br | F116: Normal | G116: Cartão ativo | H116: Portador de Cartão | I116: Sem permissão
... D154: DOUGLAS BRUCK MACHADO | E154: bruckdoug@gmail.com | F154: Normal | G154: Cartão ativo | H154: Portador de Cartão | I154: Sem permissão
C155: Cobrança | D155: Nome | E155: E-mail | F155: Tipo de usuário | G155: Status do Cartão | H155: Permissão de Uso | I155: Permissão de Gestão | J155: Ações
D156: DOUGLAS TIAGO DE OLIVEIRA | E156: odouglastiago@gmail.com | F156: Normal | G156: Cartão ativo | H156: Portador de Cartão | I156: Sem permissão
D157: DOUGLAS VENTURA SILVEIRA | E157: douglas.silveira@eqseng.com.br | F157: Normal | G157: Cartão ativo | H157: Portador de Cartão | I157: Sem permissão
D158: DOUGLAS WESLEN CARDOSO DOS SANTOS | E158: drywtop@outlook.com | F158: Normal | G158: Cartão ativo | H158: Portador de Cartão | I158: Sem permissão
D159: DYONES ONOFRE HORACIO DE OLIVEIRA | E159: mdmargoso@yahoo.com.br | F159: Normal | G159: Cartão ativo | H159: Portador de Cartão | I159: Sem permissão
D160: EDER AUGUSTO DE ARAUJO CARVALHO | E160: edercarvalho@eqsengenharia.com.br | F160: Normal | G160: Cartão ativo | H160: Portador de Cartão | I160: Sem permissão
D161: EDER MEDICI | E161: eder.medici@gmail.com | F161: Normal | G161: Cartão ativo | H161: Portador de Cartão | I161: Sem permissão
D162: EDERSON GUIZOLFI PEREIRA | E162: ederson.pereira@eqseng.com.br | F162: Normal | G162: Cartão ativo | H162: Portador de Cartão | I162: Sem permissão
D163: EDERSON LUIS BARROS DA ROSA | E163: Ederson_tjmsn@hotmail.com | F163: Normal | G163: Cartão ativo | H163: Portador de Cartão | I163: Sem permissão
D164: EDERSON STRELOW | E164: strelowederson@gmail.com | F164: Normal | G164: Cartão ativo | H164: Portador de Cartão | I164: Sem permissão
D165: EDEVALDO DUTRA GONCALVES | E165: ede_dutra@hotmail.com | F165: Normal | G165: Cartão ativo | H165: Portador de Cartão | I165: Sem permissão
D166: EDIBERTO GEORGE RELIQUIAS | E166: ediberto@eqseng.com.br | F166: Normal | G166: Cartão ativo | H166: Portador de Cartão | I166: Sem permissão
D167: EDILENE CRISTIANA DA SILVA ZIMMERMANN | E167: cristiana.zimmermann@eqsengenharia.com.br | F167: Normal | G167: Cartão ativo | H167: Portador de Cartão | I167: Sem permissão
... D205: FABIO MARTINS BORGES | E205: fabinhomborges0304@gmail.com | F205: Normal | G205: Cartão ativo | H205: Portador de Cartão | I205: Sem permissão
C206: Cobrança | D206: Nome | E206: E-mail | F206: Tipo de usuário | G206: Status do Cartão | H206: Permissão de Uso | I206: Permissão de Gestão | J206: Ações
D207: FABIO PROVESI | E207: provesi85@gmail.com | F207: Normal | G207: Cartão ativo | H207: Portador de Cartão | I207: Sem permissão
D208: FABIO RAFAEL RIBEIRO | E208: fabiorafael.email@gmail.com | F208: Normal | G208: Cartão não vinculado | H208: Portador de Cartão | I208: Sem permissão
D209: FABIO RODRIGUES JUREVICZ | E209: frj3455@gmail.com | F209: Normal | G209: Cadastro pendente | H209: Portador de Cartão | I209: Sem permissão
D210: FABRICIO SANTOS DA COSTA | E210: fscsantos82@yahoo.com.br | F210: Normal | G210: Cartão não vinculado | H210: Portador de Cartão | I210: Sem permissão
D211: FELIPE JOSE DE ALBUQUERQUE OLIVEIRA | E211: felipe.albuquerque@eqsengenharia.com.br | F211: Normal | G211: Cartão ativo | H211: Portador de Cartão | I211: Sem permissão
D212: FELIPE MELILLO FONTAN | E212: felipe.fontan@eqsengenharia.com.br | F212: Intermediário | G212: Cadastro pendente | H212: Portador de Cartão | I212: Sem permissão
D213: FELIPE MORAES COSTA DE BRITTO | E213: FELIPE-BRITTO@HOTMAIL.COM | F213: Normal | G213: Cartão ativo | H213: Portador de Cartão | I213: Sem permissão
D214: FERNANDA ARAGAO | E214: fernanda@eqsengenharia.com.br | F214: Intermediário | G214: Cadastro pendente | H214: Portador de Cartão | I214: Gestor Financeiro
D215: FERNANDO DE MELO | E215: ffernandinhodmelo@gmail.com | F215: Normal | G215: Cartão não habilitado | H215: Sem permissão | I215: Sem permissão
D216: FERNANDO RODRIGUES DUARTE | E216: fernando.duarte@eqsengenharia.com.br | F216: Normal | G216: Cartão ativo | H216: Portador de Cartão | I216: Sem permissão
D217: FILIPE MENEZES KLING | E217: filipekling.eqs@petrobras.com.br | F217: Normal | G217: Cartão ativo | H217: Portador de Cartão | I217: Sem permissão
D218: FLAVIO FERNANDES DOS REIS LIMA | E218: flavio.fernandes@eqsengenharia.com.br | F218: Normal | G218: Cartão ativo | H218: Portador de Cartão | I218: Sem permissão
... D405: MARCELA CARVALHO LEITAO | E405: marcela.carvalho@eqsengenharia.com.br | F405: Normal | G405: Cartão ativo | H405: Portador de Cartão | I405: Sem permissão
E406: marcela.carvalho@eqsengenharia.com.br
D407: MARCELO BRIG CAMPINA | E407: marcelocampina77@gmail.com | F407: Normal | G407: Cartão ativo | H407: Portador de Cartão | I407: Sem permissão
D408: MARCELO CARVALHO DA SILVA | E408: marcelo.silva@eqsengenharia.com.br | F408: Normal | G408: Cartão ativo | H408: Portador de Cartão | I408: Sem permissão
D409: MARCELO DE ANDRADE CALVETTI | E409: marcelo.calvertti@eqsengenharia.com.br | F409: Normal | G409: Cartão ativo | H409: Portador de Cartão | I409: Sem permissão
D410: MARCELO DE SOUZA DALA VEDOVA | E410: marcelo.vedova@yahoo.com.br | F410: Normal | G410: Cartão ativo | H410: Portador de Cartão | I410: Sem permissão
D411: MARCELO GIMENEZ ARGEMON | E411: marcelo.argemon@eqseng.com.br | F411: Normal | G411: Cartão ativo | H411: Portador de Cartão | I411: Sem permissão
D412: MARCELO JUNIOR DE AZEVEDO TEIXEIRA | E412: marcelo.teixeira@eqseng.com.br | F412: Normal | G412: Cadastro pendente | H412: Portador de Cartão | I412: Sem permissão
D413: MARCELO MARCHI DURIGON JUNIOR | E413: marcelo.junior@eqsengenharia.com.br | F413: Intermediário | G413: Cadastro pendente | H413: Portador de Cartão | I413: Sem permissão
D414: MARCELO PEREIRA LIMA | E414: mpllima13@gmail.com | F414: Normal | G414: Cartão ativo | H414: Portador de Cartão | I414: Sem permissão
D415: MARCELO WELTER | E415: welter1377@gmail.com | F415: Normal | G415: Cartão ativo | H415: Portador de Cartão | I415: Sem permissão
D416: MARCIA CRISTINA DA CUNHA SCATAMBULO | E416: marcia.s@eqsengenharia.com.br | F416: Intermediário | G416: Cadastro pendente | H416: Portador de Cartão | I416: Sem permissão
D417: MARCIO BOUZAS FERREIRA | E417: marcio.ferreira@eqseng.com.br | F417: Normal | G417: Cartão ativo | H417: Portador de Cartão | I417: Sem permissão
D418: MARCIO CAMPOS RIBEIRO | E418: marcio.ribeiro@eqsengenharia.com.br | F418: Intermediário | G418: Cartão ativo | H418: Portador de Cartão | I418: Sem permissão
... D607: WILSON LUIZ CABRAL | E607: wilson.cabral@eqsengenharia.com.br | F607: Normal | G607: Cartão ativo | H607: Portador de Cartão | I607: Sem permissão
