Workbook

Sheet FECHAMENTO
B4: FECHAMENTO DE PRESTAÇÃO DE CONTAS
B6: BEATRIZ SILVA DE SIQUEIRA
B7: Ano | C7: Mês | D7: Carga | E7: Transferência | F7: Taxa | G7: Prest. Contas | H7: Saldo | I7: Acumulado | K7: STATUS | L7: VALOR
B8: 2025 | C8: MAIO | D8: =SUMIFS(EXTRATO!I:I,EXTRATO!G:G,FECHAMENTO!$D$7,EXTRATO!B:B,FECHAMENTO!C8,EXTRATO!A:A,FECHAMENTO!B8) -> 1183.02 | E8: =SUMIFS(EXTRATO!I:I,EXTRATO!G:G,FECHAMENTO!$E$7,EXTRATO!B:B,FECHAMENTO!C8,EXTRATO!A:A,FECHAMENTO!B8) -> 0 | F8: =SUMIFS(EXTRATO!I:I,EXTRATO!G:G,FECHAMENTO!$F$7,EXTRATO!B:B,FECHAMENTO!C8,EXTRATO!A:A,FECHAMENTO!B8) -> 0 | G8: =SUMIFS('PREST. CONTAS'!AB:AB,'PREST. CONTAS'!B:B,FECHAMENTO!C8,'PREST. CONTAS'!A:A,FECHAMENTO!B8,'PREST. CONTAS'!I:I,"<>Aberto",'PREST. CONTAS'!I:I,"<>Reprovado") -> 215.69 | H8: =D8+E8+F8-G8 -> 967.33 | I8: =H8 -> 967.33 | K8: Aberto | L8: 2082.4
B9: 2025 | C9: JUNHO | D9: =SUMIFS(EXTRATO!I:I,EXTRATO!G:G,FECHAMENTO!$D$7,EXTRATO!B:B,FECHAMENTO!C9,EXTRATO!A:A,FECHAMENTO!B9) -> 1210.98 | E9: =SUMIFS(EXTRATO!I:I,EXTRATO!G:G,FECHAMENTO!$E$7,EXTRATO!B:B,FECHAMENTO!C9,EXTRATO!A:A,FECHAMENTO!B9) -> 0 | F9: =SUMIFS(EXTRATO!I:I,EXTRATO!G:G,FECHAMENTO!$F$7,EXTRATO!B:B,FECHAMENTO!C9,EXTRATO!A:A,FECHAMENTO!B9) -> -21 | G9: =SUMIFS('PREST. CONTAS'!AB:AB,'PREST. CONTAS'!B:B,C9,'PREST. CONTAS'!A:A,B9,'PREST. CONTAS'!I:I,"<>Aberto",'PREST. CONTAS'!I:I,"<>Reprovado") -> 983.32 | H9: =D9+E9+F9-G9 -> 206.66 | I9: =H9+I8 -> 1173.99 | K9: Aprovado | L9: 24955.93
B10: 2025 | C10: JULHO | D10: =SUMIFS(EXTRATO!I:I,EXTRATO!G:G,FECHAMENTO!$D$7,EXTRATO!B:B,FECHAMENTO!C10,EXTRATO!A:A,FECHAMENTO!B10) -> 2953.46 | E10: =SUMIFS(EXTRATO!I:I,EXTRATO!G:G,FECHAMENTO!$E$7,EXTRATO!B:B,FECHAMENTO!C10,EXTRATO!A:A,FECHAMENTO!B10) -> 0 | F10: =SUMIFS(EXTRATO!I:I,EXTRATO!G:G,FECHAMENTO!$F$7,EXTRATO!B:B,FECHAMENTO!C10,EXTRATO!A:A,FECHAMENTO!B10) -> -28 | G10: =SUMIFS('PREST. CONTAS'!AB:AB,'PREST. CONTAS'!B:B,C10,'PREST. CONTAS'!A:A,B10,'PREST. CONTAS'!I:I,"<>Aberto",'PREST. CONTAS'!I:I,"<>Reprovado") -> 1553.88 | H10: =D10+E10+F10-G10 -> 1371.58 | I10: =H10+I9 -> 2545.57 | K10: Total Geral | L10: 27038.33
B11: 2025 | C11: AGOSTO | D11: =SUMIFS(EXTRATO!I:I,EXTRATO!G:G,FECHAMENTO!$D$7,EXTRATO!B:B,FECHAMENTO!C11,EXTRATO!A:A,FECHAMENTO!B11) -> 0 | E11: =SUMIFS(EXTRATO!I:I,EXTRATO!G:G,FECHAMENTO!$E$7,EXTRATO!B:B,FECHAMENTO!C11,EXTRATO!A:A,FECHAMENTO!B11) -> 0 | F11: =SUMIFS(EXTRATO!I:I,EXTRATO!G:G,FECHAMENTO!$F$7,EXTRATO!B:B,FECHAMENTO!C11,EXTRATO!A:A,FECHAMENTO!B11) -> 0 | G11: =SUMIFS('PREST. CONTAS'!AB:AB,'PREST. CONTAS'!B:B,C11,'PREST. CONTAS'!A:A,B11,'PREST. CONTAS'!I:I,"<>Aberto",'PREST. CONTAS'!I:I,"<>Reprovado") -> 2352.96 | H11: =D11+E11+F11-G11 -> -2352.96 | I11: =H11+I10 -> 192.61
B12: 2025 | C12: SETEMBRO | D12: =SUMIFS(EXTRATO!I:I,EXTRATO!G:G,FECHAMENTO!$D$7,EXTRATO!B:B,FECHAMENTO!C12,EXTRATO!A:A,FECHAMENTO!B12) -> 4195.54 | E12: =SUMIFS(EXTRATO!I:I,EXTRATO!G:G,FECHAMENTO!$E$7,EXTRATO!B:B,FECHAMENTO!C12,EXTRATO!A:A,FECHAMENTO!B12) -> 0 | F12: =SUMIFS(EXTRATO!I:I,EXTRATO!G:G,FECHAMENTO!$F$7,EXTRATO!B:B,FECHAMENTO!C12,EXTRATO!A:A,FECHAMENTO!B12) -> -28 | G12: =SUMIFS('PREST. CONTAS'!AB:AB,'PREST. CONTAS'!B:B,C12,'PREST. CONTAS'!A:A,B12,'PREST. CONTAS'!I:I,"<>Aberto",'PREST. CONTAS'!I:I,"<>Reprovado") -> 2698.15 | H12: =D12+E12+F12-G12 -> 1469.39 | I12: =H12+I11 -> 1662
B13: 2025 | C13: OUTUBRO | D13: =SUMIFS(EXTRATO!I:I,EXTRATO!G:G,FECHAMENTO!$D$7,EXTRATO!B:B,FECHAMENTO!C13,EXTRATO!A:A,FECHAMENTO!B13) -> 2957.62 | E13: =SUMIFS(EXTRATO!I:I,EXTRATO!G:G,FECHAMENTO!$E$7,EXTRATO!B:B,FECHAMENTO!C13,EXTRATO!A:A,FECHAMENTO!B13) -> 0 | F13: =SUMIFS(EXTRATO!I:I,EXTRATO!G:G,FECHAMENTO!$F$7,EXTRATO!B:B,FECHAMENTO!C13,EXTRATO!A:A,FECHAMENTO!B13) -> -28 | G13: =SUMIFS('PREST. CONTAS'!AB:AB,'PREST. CONTAS'!B:B,C13,'PREST. CONTAS'!A:A,B13,'PREST. CONTAS'!I:I,"<>Aberto",'PREST. CONTAS'!I:I,"<>Reprovado") -> 2527.06 | H13: =D13+E13+F13-G13 -> 402.56 | I13: =H13+I12 -> 2064.56
B14: 2025 | C14: NOVEMBRO | D14: =SUMIFS(EXTRATO!I:I,EXTRATO!G:G,FECHAMENTO!$D$7,EXTRATO!B:B,FECHAMENTO!C14,EXTRATO!A:A,FECHAMENTO!B14) -> 688.07 | E14: =SUMIFS(EXTRATO!I:I,EXTRATO!G:G,FECHAMENTO!$E$7,EXTRATO!B:B,FECHAMENTO!C14,EXTRATO!A:A,FECHAMENTO!B14) -> 0 | F14: =SUMIFS(EXTRATO!I:I,EXTRATO!G:G,FECHAMENTO!$F$7,EXTRATO!B:B,FECHAMENTO!C14,EXTRATO!A:A,FECHAMENTO!B14) -> -7 | G14: =SUMIFS('PREST. CONTAS'!AB:AB,'PREST. CONTAS'!B:B,C14,'PREST. CONTAS'!A:A,B14,'PREST. CONTAS'!I:I,"<>Aberto",'PREST. CONTAS'!I:I,"<>Reprovado") -> 2044.35 | H14: =D14+E14+F14-G14 -> -1363.28 | I14: =H14+I13 -> 701.28
B15: 2025 | C15: DEZEMBRO | D15: =SUMIFS(EXTRATO!I:I,EXTRATO!G:G,FECHAMENTO!$D$7,EXTRATO!B:B,FECHAMENTO!C15,EXTRATO!A:A,FECHAMENTO!B15) -> 1588.74 | E15: =SUMIFS(EXTRATO!I:I,EXTRATO!G:G,FECHAMENTO!$E$7,EXTRATO!B:B,FECHAMENTO!C15,EXTRATO!A:A,FECHAMENTO!B15) -> 0 | F15: =SUMIFS(EXTRATO!I:I,EXTRATO!G:G,FECHAMENTO!$F$7,EXTRATO!B:B,FECHAMENTO!C15,EXTRATO!A:A,FECHAMENTO!B15) -> -14 | G15: =SUMIFS('PREST. CONTAS'!AB:AB,'PREST. CONTAS'!B:B,C15,'PREST. CONTAS'!A:A,B15,'PREST. CONTAS'!I:I,"<>Aberto",'PREST. CONTAS'!I:I,"<>Reprovado") -> 2448.35 | H15: =D15+E15+F15-G15 -> -873.61 | I15: =H15+I14 -> -172.33
B16: 2026 | C16: JANEIRO | D16: =SUMIFS(EXTRATO!I:I,EXTRATO!G:G,FECHAMENTO!$D$7,EXTRATO!B:B,FECHAMENTO!C16,EXTRATO!A:A,FECHAMENTO!B16) -> 4306 | E16: =SUMIFS(EXTRATO!I:I,EXTRATO!G:G,FECHAMENTO!$E$7,EXTRATO!B:B,FECHAMENTO!C16,EXTRATO!A:A,FECHAMENTO!B16) -> -6.43 | F16: =SUMIFS(EXTRATO!I:I,EXTRATO!G:G,FECHAMENTO!$F$7,EXTRATO!B:B,FECHAMENTO!C16,EXTRATO!A:A,FECHAMENTO!B16) -> -35 | G16: =SUMIFS('PREST. CONTAS'!AB:AB,'PREST. CONTAS'!B:B,C16,'PREST. CONTAS'!A:A,B16,'PREST. CONTAS'!I:I,"<>Aberto",'PREST. CONTAS'!I:I,"<>Reprovado") -> 1845.73 | H16: =D16+E16+F16-G16 -> 2418.84 | I16: =H16+I15 -> 2246.51
B17: 2026 | C17: FEVEREIRO | D17: =SUMIFS(EXTRATO!I:I,EXTRATO!G:G,FECHAMENTO!$D$7,EXTRATO!B:B,FECHAMENTO!C17,EXTRATO!A:A,FECHAMENTO!B17) -> 2013.46 | E17: =SUMIFS(EXTRATO!I:I,EXTRATO!G:G,FECHAMENTO!$E$7,EXTRATO!B:B,FECHAMENTO!C17,EXTRATO!A:A,FECHAMENTO!B17) -> 0 | F17: =SUMIFS(EXTRATO!I:I,EXTRATO!G:G,FECHAMENTO!$F$7,EXTRATO!B:B,FECHAMENTO!C17,EXTRATO!A:A,FECHAMENTO!B17) -> -21 | G17: =SUMIFS('PREST. CONTAS'!AB:AB,'PREST. CONTAS'!B:B,C17,'PREST. CONTAS'!A:A,B17,'PREST. CONTAS'!I:I,"<>Aberto",'PREST. CONTAS'!I:I,"<>Reprovado") -> 2889.99 | H17: =D17+E17+F17-G17 -> -897.53 | I17: =H17+I16 -> 1348.98
B18: 2026 | C18: MARÇO | D18: =SUMIFS(EXTRATO!I:I,EXTRATO!G:G,FECHAMENTO!$D$7,EXTRATO!B:B,FECHAMENTO!C18,EXTRATO!A:A,FECHAMENTO!B18) -> 1812.44 | E18: =SUMIFS(EXTRATO!I:I,EXTRATO!G:G,FECHAMENTO!$E$7,EXTRATO!B:B,FECHAMENTO!C18,EXTRATO!A:A,FECHAMENTO!B18) -> 0 | F18: =SUMIFS(EXTRATO!I:I,EXTRATO!G:G,FECHAMENTO!$F$7,EXTRATO!B:B,FECHAMENTO!C18,EXTRATO!A:A,FECHAMENTO!B18) -> -14 | G18: =SUMIFS('PREST. CONTAS'!AB:AB,'PREST. CONTAS'!B:B,C18,'PREST. CONTAS'!A:A,B18,'PREST. CONTAS'!I:I,"<>Aberto",'PREST. CONTAS'!I:I,"<>Reprovado") -> 1925.92 | H18: =D18+E18+F18-G18 -> -127.48 | I18: =H18+I17 -> 1221.5
B19: 2026 | C19: ABRIL | D19: =SUMIFS(EXTRATO!I:I,EXTRATO!G:G,FECHAMENTO!$D$7,EXTRATO!B:B,FECHAMENTO!C19,EXTRATO!A:A,FECHAMENTO!B19) -> 1810.16 | E19: =SUMIFS(EXTRATO!I:I,EXTRATO!G:G,FECHAMENTO!$E$7,EXTRATO!B:B,FECHAMENTO!C19,EXTRATO!A:A,FECHAMENTO!B19) -> 0 | F19: =SUMIFS(EXTRATO!I:I,EXTRATO!G:G,FECHAMENTO!$F$7,EXTRATO!B:B,FECHAMENTO!C19,EXTRATO!A:A,FECHAMENTO!B19) -> -14 | G19: =SUMIFS('PREST. CONTAS'!AB:AB,'PREST. CONTAS'!B:B,C19,'PREST. CONTAS'!A:A,B19,'PREST. CONTAS'!I:I,"<>Aberto",'PREST. CONTAS'!I:I,"<>Reprovado") -> 1434.83 | H19: =D19+E19+F19-G19 -> 361.33 | I19: =H19+I18 -> 1582.83
B20: 2026 | C20: MAIO | D20: =SUMIFS(EXTRATO!I:I,EXTRATO!G:G,FECHAMENTO!$D$7,EXTRATO!B:B,FECHAMENTO!C20,EXTRATO!A:A,FECHAMENTO!B20) -> 1594.15 | E20: =SUMIFS(EXTRATO!I:I,EXTRATO!G:G,FECHAMENTO!$E$7,EXTRATO!B:B,FECHAMENTO!C20,EXTRATO!A:A,FECHAMENTO!B20) -> 0 | F20: =SUMIFS(EXTRATO!I:I,EXTRATO!G:G,FECHAMENTO!$F$7,EXTRATO!B:B,FECHAMENTO!C20,EXTRATO!A:A,FECHAMENTO!B20) -> -28 | G20: =SUMIFS('PREST. CONTAS'!AB:AB,'PREST. CONTAS'!B:B,C20,'PREST. CONTAS'!A:A,B20,'PREST. CONTAS'!I:I,"<>Aberto",'PREST. CONTAS'!I:I,"<>Reprovado") -> 1178.31 | H20: =D20+E20+F20-G20 -> 387.84 | I20: =H20+I19 -> 1970.67
B21: 2026 | C21: JUNHO | D21: =SUMIFS(EXTRATO!I:I,EXTRATO!G:G,FECHAMENTO!$D$7,EXTRATO!B:B,FECHAMENTO!C21,EXTRATO!A:A,FECHAMENTO!B21) -> 391.86 | E21: =SUMIFS(EXTRATO!I:I,EXTRATO!G:G,FECHAMENTO!$E$7,EXTRATO!B:B,FECHAMENTO!C21,EXTRATO!A:A,FECHAMENTO!B21) -> 0 | F21: =SUMIFS(EXTRATO!I:I,EXTRATO!G:G,FECHAMENTO!$F$7,EXTRATO!B:B,FECHAMENTO!C21,EXTRATO!A:A,FECHAMENTO!B21) -> -7 | G21: =SUMIFS('PREST. CONTAS'!AB:AB,'PREST. CONTAS'!B:B,C21,'PREST. CONTAS'!A:A,B21,'PREST. CONTAS'!I:I,"<>Aberto",'PREST. CONTAS'!I:I,"<>Reprovado") -> 857.39 | H21: =D21+E21+F21-G21 -> -472.53 | I21: =H21+I20 -> 1498.14
B22: 2026 | C22: JULHO | D22: =SUMIFS(EXTRATO!I:I,EXTRATO!G:G,FECHAMENTO!$D$7,EXTRATO!B:B,FECHAMENTO!C22,EXTRATO!A:A,FECHAMENTO!B22) -> 985.93 | E22: =SUMIFS(EXTRATO!I:I,EXTRATO!G:G,FECHAMENTO!$E$7,EXTRATO!B:B,FECHAMENTO!C22,EXTRATO!A:A,FECHAMENTO!B22) -> 0 | F22: =SUMIFS(EXTRATO!I:I,EXTRATO!G:G,FECHAMENTO!$F$7,EXTRATO!B:B,FECHAMENTO!C22,EXTRATO!A:A,FECHAMENTO!B22) -> -7 | G22: =SUMIFS('PREST. CONTAS'!AB:AB,'PREST. CONTAS'!B:B,C22,'PREST. CONTAS'!A:A,B22,'PREST. CONTAS'!I:I,"<>Aberto",'PREST. CONTAS'!I:I,"<>Reprovado") -> 0 | H22: =D22+E22+F22-G22 -> 978.93 | I22: =H22+I21 -> 2477.07
D23: =SUM(D8:D22) -> 27691.43 | E23: =SUM(E8:E22) -> -6.43 | F23: =SUM(F8:F22) -> -252 | G23: =SUM(G8:G22) -> 24955.93 | H23: =SUM(H8:H22) -> 2477.07
B25: SALDO FINAL | H25: =H23 -> 2477.07 | K25: LEGENDA SINAIS
B26: (+) SALDO DISPONIVEL | H26: =D23+E23+F23 -> 27433 | K26: NEGATIVO | L26: A REEMBOLSAR
B27: (-) PRESTAÇÃO DE CONTAS | H27: =G23 -> 24955.93 | K27: POSITIVO | L27: A PRESTAR
B28: = FECHAMENTO PRESTE CONTAS | H28: =H26-H27 -> 2477.07
B29: = SALDO CARTÃO | H29: 3
B30: FECHAMENTO FINAL - SALDO PENDENTE | H30: =H28-H29 -> 2474.07

Sheet PREST. CONTAS
A1: Ano | B1: Mês | C1: ID da Despesa | D1: ID do Relatório | E1: Nome do relatório | F1: Data | G1: Nome do membro de equipe | H1: CPF/CNPJ | I1: Status | J1: Data de Pagamento | K1: Descrição da despesa | L1: Tipo de Despesa | M1: Reembolsável | N1: Anotação da Despesa | O1: Anotação de Rateio | P1: Centro de Custos | Q1: Forma de pagamento | R1: Projeto | S1: Percentual de projeto | T1: Início do Percurso por GPS | U1: Fim do Percurso por GPS | V1: Valor do KM | W1: Kilômetros Percorridos | X1: Moeda do Relatório | Y1: Valor | Z1: Moeda da Conversão | AA1: Valor Convertido | AB1: Valor Total | AC1: Ultrapassou Política
A2: =YEAR(F2) -> 2026 | B2: =UPPER(TEXT(F2,"MMMM")) -> JULHO | C2: 87556404 | D2: 10906730 | E2: CAIXA 07/2026 | F2: 46227 | G2: BEATRIZ SILVA DE SIQUEIRA | H2: 35575473880 | I2: Aberto | K2: Material | L2: MATERIAL | M2: Não | N2: Atendimento de chamado caixa economica | P2: CEF SP SUL | Q2: Saque VExpenses | R2: REGIONAL SP | S2: 1 | X2: BRL | Y2: 45 | AB2: 45 | AC2: Não
A3: =YEAR(F3) -> 2026 | B3: =UPPER(TEXT(F3,"MMMM")) -> JULHO | C3: 87002054 | D3: 10906730 | E3: CAIXA 07/2026 | F3: 46221 | G3: BEATRIZ SILVA DE SIQUEIRA | H3: 35575473880 | I3: Aberto | K3: Material | L3: MATERIAL | M3: Não | N3: Atendimento de chamado caixa economica | P3: CEF SP SUL | Q3: Saque VExpenses | R3: REGIONAL SP | S3: 1 | X3: BRL | Y3: 74.5 | AB3: 74.5 | AC3: Não
A4: =YEAR(F4) -> 2026 | B4: =UPPER(TEXT(F4,"MMMM")) -> JULHO | C4: 87001977 | D4: 10906730 | E4: CAIXA 07/2026 | F4: 46221 | G4: BEATRIZ SILVA DE SIQUEIRA | H4: 35575473880 | I4: Aberto | K4: Material | L4: MATERIAL | M4: Não | N4: Atendimento de chamado caixa economica | P4: CEF SP SUL | Q4: Saque VExpenses | R4: REGIONAL SP | S4: 1 | X4: BRL | Y4: 83.1 | AB4: 83.1 | AC4: Não
A5: =YEAR(F5) -> 2026 | B5: =UPPER(TEXT(F5,"MMMM")) -> JULHO | C5: 87001778 | D5: 10906730 | E5: CAIXA 07/2026 | F5: 46221 | G5: BEATRIZ SILVA DE SIQUEIRA | H5: 35575473880 | I5: Aberto | K5: Material | L5: MATERIAL | M5: Não | N5: Atendimento de chamado caixa economica | P5: CEF SP SUL | Q5: Saque VExpenses | R5: REGIONAL SP | S5: 1 | X5: BRL | Y5: 62.8 | AB5: 62.8 | AC5: Não
A6: =YEAR(F6) -> 2026 | B6: =UPPER(TEXT(F6,"MMMM")) -> JULHO | C6: 87001416 | D6: 10906730 | E6: CAIXA 07/2026 | F6: 46221 | G6: BEATRIZ SILVA DE SIQUEIRA | H6: 35575473880 | I6: Aberto | K6: Material | L6: MATERIAL | M6: Não | N6: Atendimento de chamado caixa economica | P6: CEF SP SUL | Q6: Saque VExpenses | R6: REGIONAL SP | S6: 1 | X6: BRL | Y6: 53.33 | AB6: 53.33 | AC6: Não
A7: =YEAR(F7) -> 2026 | B7: =UPPER(TEXT(F7,"MMMM")) -> JULHO | C7: 87002136 | D7: 10906730 | E7: CAIXA 07/2026 | F7: 46220 | G7: BEATRIZ SILVA DE SIQUEIRA | H7: 35575473880 | I7: Aberto | K7: Material | L7: MATERIAL | M7: Não | N7: Atendimento de chamado caixa economica | P7: CEF SP SUL | Q7: Saque VExpenses | R7: REGIONAL SP | S7: 1 | X7: BRL | Y7: 51.21 | AB7: 51.21 | AC7: Não
A8: =YEAR(F8) -> 2026 | B8: =UPPER(TEXT(F8,"MMMM")) -> JULHO | C8: 87001089 | D8: 10906730 | E8: CAIXA 07/2026 | F8: 46217 | G8: BEATRIZ SILVA DE SIQUEIRA | H8: 35575473880 | I8: Aberto | K8: Material | L8: MATERIAL | M8: Não | N8: Atendimento de chamado caixa economica | P8: CEF SP SUL | Q8: Saque VExpenses | R8: REGIONAL SP | S8: 1 | X8: BRL | Y8: 110 | AB8: 110 | AC8: Não
A9: =YEAR(F9) -> 2026 | B9: =UPPER(TEXT(F9,"MMMM")) -> JULHO | C9: 87000987 | D9: 10906730 | E9: CAIXA 07/2026 | F9: 46216 | G9: BEATRIZ SILVA DE SIQUEIRA | H9: 35575473880 | I9: Aberto | K9: Material | L9: MATERIAL | M9: Não | N9: Atendimento de chamado caixa economica | P9: CEF SP SUL | Q9: Saque VExpenses | R9: REGIONAL SP | S9: 1 | X9: BRL | Y9: 25 | AB9: 25 | AC9: Não
A10: =YEAR(F10) -> 2026 | B10: =UPPER(TEXT(F10,"MMMM")) -> JULHO | C10: 87001218 | D10: 10906730 | E10: CAIXA 07/2026 | F10: 46210 | G10: BEATRIZ SILVA DE SIQUEIRA | H10: 35575473880 | I10: Aberto | K10: Material | L10: MATERIAL | M10: Não | N10: Atendimento de chamado caixa economica | P10: CEF SP SUL | Q10: Saque VExpenses | R10: REGIONAL SP | S10: 1 | X10: BRL | Y10: 6 | AB10: 6 | AC10: Não
A11: =YEAR(F11) -> 2026 | B11: =UPPER(TEXT(F11,"MMMM")) -> JULHO | C11: 87001310 | D11: 10906730 | E11: CAIXA 07/2026 | F11: 46209 | G11: BEATRIZ SILVA DE SIQUEIRA | H11: 35575473880 | I11: Aberto | K11: Material | L11: MATERIAL | M11: Não | N11: Atendimento de chamado caixa economica | P11: CEF SP SUL | Q11: Saque VExpenses | R11: REGIONAL SP | S11: 1 | X11: BRL | Y11: 40 | AB11: 40 | AC11: Não
A12: =YEAR(F12) -> 2026 | B12: =UPPER(TEXT(F12,"MMMM")) -> JULHO | C12: 86328704 | D12: 10906730 | E12: CAIXA 07/2026 | F12: 46207 | G12: BEATRIZ SILVA DE SIQUEIRA | H12: 35575473880 | I12: Aberto | K12: Nota 7 | L12: MATERIAL | M12: Não | N12: Nota 7 | P12: CEF SP SUL | Q12: Saque VExpenses | R12: REGIONAL SP | S12: 1 | X12: BRL | Y12: 31 | AB12: 31 | AC12: Não
A13: =YEAR(F13) -> 2026 | B13: =UPPER(TEXT(F13,"MMMM")) -> JULHO | C13: 86057697 | D13: 10906730 | E13: CAIXA 07/2026 | F13: 46206 | G13: BEATRIZ SILVA DE SIQUEIRA | H13: 35575473880 | I13: Aberto | K13: Nota 02 | L13: MATERIAL | M13: Não | N13: Nota 2 | P13: CEF SP SUL | Q13: Saque VExpenses | R13: REGIONAL SP | S13: 1 | X13: BRL | Y13: 60 | AB13: 60 | AC13: Não
... A19: =YEAR(F19) -> 2026 | B19: =UPPER(TEXT(F19,"MMMM")) -> JUNHO | C19: 87146033 | D19: 10906730 | E19: CAIXA 07/2026 | F19: 46198 | G19: BEATRIZ SILVA DE SIQUEIRA | H19: 35575473880 | I19: Aberto | K19: MATERIAL | L19: MATERIAL | M19: Não | N19: Atendimento de chamado caixa economica | P19: CEF SP SUL | Q19: Saque VExpenses | R19: REGIONAL SP | S19: 1 | X19: BRL | Y19: 70 | AB19: 70 | AC19: Não
A20: =YEAR(F20) -> 2026 | B20: =UPPER(TEXT(F20,"MMMM")) -> JUNHO | C20: 87144760 | D20: 10906730 | E20: CAIXA 07/2026 | F20: 46189 | G20: BEATRIZ SILVA DE SIQUEIRA | H20: 35575473880 | I20: Aberto | K20: Material | L20: MATERIAL | M20: Não | N20: A nota fiscal foi anexada ao cartão de crédito de forma equivocada. Esclarecemos que a referida despesa é referente ao caixa, não estando vinculada ao cartão de crédito. Inserida no caixa do mês 07 pelo motivo do caixa 06 estar aprovado e fechado. Não sendo possível inserir DEMANDA EMEEGENCIAL DE FURTO NA AGENCIA | P20: CEF SP SUL | Q20: Saque VExpenses | R20: REGIONAL SP | S20: 1 | W20: 0 | X20: BRL | Y20: 690 | AB20: 690 | AC20: Sim
A21: =YEAR(F21) -> 2026 | B21: =UPPER(TEXT(F21,"MMMM")) -> MARÇO | C21: 81660359 | D21: 10906730 | E21: CAIXA 07/2026 | F21: 46111 | G21: BEATRIZ SILVA DE SIQUEIRA | H21: 35575473880 | I21: Aberto | K21: Recibo | L21: MATERIAL | M21: Não | N21: Identificadas notas desvinculadas do caixa no período de 03/2026, desvinculados sem apresentação de justificativa. Caixa de 03/26 já fechado impossibilitado vinculação no mesmo no caixa | P21: CEF SP SUL | Q21: Saque VExpenses | R21: REGIONAL SP | S21: 1 | W21: 0 | X21: BRL | Y21: 139.98 | AB21: 139.98 | AC21: Não
A22: =YEAR(F22) -> 2026 | B22: =UPPER(TEXT(F22,"MMMM")) -> MARÇO | C22: 81659592 | D22: 10906730 | E22: CAIXA 07/2026 | F22: 46102 | G22: BEATRIZ SILVA DE SIQUEIRA | H22: 35575473880 | I22: Aberto | K22: Material | L22: MATERIAL | M22: Não | N22: Identificadas notas desvinculadas do caixa no período de 03/2026, sem apresentação de justificativa. . Caixa de 03/26 já fechado impossibilitado vinculação no mesmo no caixa correto | P22: CEF SP SUL | Q22: Saque VExpenses | R22: REGIONAL SP | S22: 1 | W22: 0 | X22: BRL | Y22: 27.39 | AB22: 27.39 | AC22: Não
A23: =YEAR(F23) -> 2026 | B23: =UPPER(TEXT(F23,"MMMM")) -> JUNHO | C23: 85799387 | D23: 10657027 | E23: CAIXA 06/2026 | F23: 46203 | G23: BEATRIZ SILVA DE SIQUEIRA | H23: 35575473880 | I23: Aprovado | K23: Material | L23: MATERIAL | M23: Não | N23: Atendimento de chamado caixa economica | P23: CEF SP SUL | Q23: Saque VExpenses | R23: REGIONAL SP | S23: 1 | X23: BRL | Y23: 125 | AB23: 125 | AC23: Não
A24: =YEAR(F24) -> 2026 | B24: =UPPER(TEXT(F24,"MMMM")) -> JUNHO | C24: 85718404 | D24: 10657027 | E24: CAIXA 06/2026 | F24: 46203 | G24: BEATRIZ SILVA DE SIQUEIRA | H24: 35575473880 | I24: Aprovado | K24: Material | L24: MATERIAL | M24: Não | N24: Atendimento de chamado caixa economica | P24: CEF SP SUL | Q24: Saque VExpenses | R24: REGIONAL SP | S24: 1 | X24: BRL | Y24: 14.99 | AB24: 14.99 | AC24: Não
A25: =YEAR(F25) -> 2026 | B25: =UPPER(TEXT(F25,"MMMM")) -> JUNHO | C25: 86057174 | D25: 10657027 | E25: CAIXA 06/2026 | F25: 46202 | G25: BEATRIZ SILVA DE SIQUEIRA | H25: 35575473880 | I25: Aprovado | K25: Nota 2 | L25: ESTACIONAMENTO | M25: Não | N25: Nota 2 | P25: CEF SP SUL | Q25: Tarifa de Saque | R25: REGIONAL SP | S25: 1 | X25: BRL | Y25: 8 | AB25: 8 | AC25: Não
A26: =YEAR(F26) -> 2026 | B26: =UPPER(TEXT(F26,"MMMM")) -> JUNHO | C26: 85799326 | D26: 10657027 | E26: CAIXA 06/2026 | F26: 46202 | G26: BEATRIZ SILVA DE SIQUEIRA | H26: 35575473880 | I26: Aprovado | K26: Material | L26: MATERIAL | M26: Não | N26: Atendimento de chamado caixa economica | P26: CEF SP SUL | Q26: Saque VExpenses | R26: REGIONAL SP | S26: 1 | X26: BRL | Y26: 69 | AB26: 69 | AC26: Não
A27: =YEAR(F27) -> 2026 | B27: =UPPER(TEXT(F27,"MMMM")) -> JUNHO | C27: 86056975 | D27: 10657027 | E27: CAIXA 06/2026 | F27: 46201 | G27: BEATRIZ SILVA DE SIQUEIRA | H27: 35575473880 | I27: Aprovado | K27: Nota 03 | L27: MATERIAL | M27: Não | N27: Nota 3 | P27: CEF SP SUL | Q27: Tarifa de Saque | R27: REGIONAL SP | S27: 1 | X27: BRL | Y27: 23.4 | AB27: 23.4 | AC27: Não
A28: =YEAR(F28) -> 2026 | B28: =UPPER(TEXT(F28,"MMMM")) -> JUNHO | C28: 86056713 | D28: 10657027 | E28: CAIXA 06/2026 | F28: 46199 | G28: BEATRIZ SILVA DE SIQUEIRA | H28: 35575473880 | I28: Aprovado | K28: Nota 1 | L28: MATERIAL | M28: Não | N28: Nota | P28: CEF SP SUL | Q28: Tarifa de Saque | R28: REGIONAL SP | S28: 1 | X28: BRL | Y28: 42.66 | AB28: 42.66 | AC28: Não
A29: =YEAR(F29) -> 2026 | B29: =UPPER(TEXT(F29,"MMMM")) -> JUNHO | C29: 85799448 | D29: 10657027 | E29: CAIXA 06/2026 | F29: 46198 | G29: BEATRIZ SILVA DE SIQUEIRA | H29: 35575473880 | I29: Aprovado | K29: Material | L29: MATERIAL | M29: Não | N29: Atendimento de chamado caixa economica | P29: CEF SP SUL | Q29: Saque VExpenses | R29: REGIONAL SP | S29: 1 | X29: BRL | Y29: 14.4 | AB29: 14.4 | AC29: Não
A30: =YEAR(F30) -> 2026 | B30: =UPPER(TEXT(F30,"MMMM")) -> JUNHO | C30: 85799274 | D30: 10657027 | E30: CAIXA 06/2026 | F30: 46195 | G30: BEATRIZ SILVA DE SIQUEIRA | H30: 35575473880 | I30: Aprovado | K30: Material | L30: MATERIAL | M30: Não | N30: Atendimento de chamado caixa economica | P30: CEF SP SUL | Q30: Saque VExpenses | R30: REGIONAL SP | S30: 1 | X30: BRL | Y30: 49.9 | AB30: 49.9 | AC30: Não
A31: =YEAR(F31) -> 2026 | B31: =UPPER(TEXT(F31,"MMMM")) -> JUNHO | C31: 85325892 | D31: 10657027 | E31: CAIXA 06/2026 | F31: 46190 | G31: BEATRIZ SILVA DE SIQUEIRA | H31: 35575473880 | I31: Aprovado | K31: Material | L31: MATERIAL | M31: Não | N31: Atendimento de chamado caixa economica | P31: CEF SP SUL | Q31: Saque VExpenses | R31: REGIONAL SP | S31: 1 | X31: BRL | Y31: 39 | AB31: 39 | AC31: Não
A32: =YEAR(F32) -> 2026 | B32: =UPPER(TEXT(F32,"MMMM")) -> JUNHO | C32: 85325789 | D32: 10657027 | E32: CAIXA 06/2026 | F32: 46183 | G32: BEATRIZ SILVA DE SIQUEIRA | H32: 35575473880 | I32: Aprovado | K32: Material | L32: MATERIAL | M32: Não | N32: Atendimento de chamado caixa economica | P32: CEF SP SUL | Q32: Saque VExpenses | R32: REGIONAL SP | S32: 1 | X32: BRL | Y32: 36 | AB32: 36 | AC32: Não
A33: =YEAR(F33) -> 2026 | B33: =UPPER(TEXT(F33,"MMMM")) -> JUNHO | C33: 84256192 | D33: 10657027 | E33: CAIXA 06/2026 | F33: 46182 | G33: BEATRIZ SILVA DE SIQUEIRA | H33: 35575473880 | I33: Aprovado | K33: Material | L33: MATERIAL | M33: Não | N33: AtendImento de chamado caixa economica | P33: CEF SP SUL | Q33: Saque VExpenses | R33: REGIONAL SP | S33: 1 | X33: BRL | Y33: 75.94 | AB33: 75.94 | AC33: Não
A34: =YEAR(F34) -> 2026 | B34: =UPPER(TEXT(F34,"MMMM")) -> JUNHO | C34: 85342217 | D34: 10657027 | E34: CAIXA 06/2026 | F34: 46174 | G34: BEATRIZ SILVA DE SIQUEIRA | H34: 35575473880 | I34: Aprovado | K34: Estacionamento e Pedagio | L34: ESTACIONAMENTO | M34: Não | N34: Atendimento de chamado caixa economica | P34: CEF SP SUL | Q34: Saque VExpenses | R34: REGIONAL SP | S34: 1 | X34: BRL | Y34: 217.3 | AB34: 217.3 | AC34: Não
... A58: =YEAR(F58) -> 2026 | B58: =UPPER(TEXT(F58,"MMMM")) -> ABRIL | C58: 81660193 | D58: 10306286 | E58: CAIXA 04/2026 | F58: 46130 | G58: BEATRIZ SILVA DE SIQUEIRA | H58: 35575473880 | I58: Aprovado | K58: Recibo | L58: MATERIAL | M58: Não | N58: Atendimento de chamado caixa econômica | P58: CEF SP SUL | Q58: Saque VExpenses | R58: REGIONAL SP | S58: 1 | X58: BRL | Y58: 9.8 | AB58: 9.8 | AC58: Não
A59: =YEAR(F59) -> 2026 | B59: =UPPER(TEXT(F59,"MMMM")) -> ABRIL | C59: 81660593 | D59: 10306286 | E59: CAIXA 04/2026 | F59: 46128 | G59: BEATRIZ SILVA DE SIQUEIRA | H59: 35575473880 | I59: Aprovado | K59: Recibo | L59: MATERIAL | M59: Não | N59: Atendimento de chamado caixa econômica | P59: CEF SP SUL | Q59: Saque VExpenses | R59: REGIONAL SP | S59: 1 | W59: 0 | X59: BRL | Y59: 37.89 | AB59: 37.89 | AC59: Não
A60: =YEAR(F60) -> 2026 | B60: =UPPER(TEXT(F60,"MMMM")) -> ABRIL | C60: 81659514 | D60: 10306286 | E60: CAIXA 04/2026 | F60: 46128 | G60: BEATRIZ SILVA DE SIQUEIRA | H60: 35575473880 | I60: Aprovado | K60: Recibo | L60: MATERIAL | M60: Não | N60: Atendimento de chamado caixa econômica | P60: CEF SP SUL | Q60: Saque VExpenses | R60: REGIONAL SP | S60: 1 | X60: BRL | Y60: 37.89 | AB60: 37.89 | AC60: Não
A61: =YEAR(F61) -> 2026 | B61: =UPPER(TEXT(F61,"MMMM")) -> ABRIL | C61: 81660479 | D61: 10306286 | E61: CAIXA 04/2026 | F61: 46120 | G61: BEATRIZ SILVA DE SIQUEIRA | H61: 35575473880 | I61: Aprovado | K61: Recibo | L61: MATERIAL | M61: Não | N61: Atendimento de chamado caixa econômica | P61: CEF SP SUL | Q61: Saque VExpenses | R61: REGIONAL SP | S61: 1 | X61: BRL | Y61: 39.5 | AB61: 39.5 | AC61: Não
A62: =YEAR(F62) -> 2026 | B62: =UPPER(TEXT(F62,"MMMM")) -> ABRIL | C62: 81660253 | D62: 10306286 | E62: CAIXA 04/2026 | F62: 46120 | G62: BEATRIZ SILVA DE SIQUEIRA | H62: 35575473880 | I62: Aprovado | K62: Recibo | L62: MATERIAL | M62: Não | N62: Atendimento de chamado caixa econômica | P62: CEF SP SUL | Q62: Saque VExpenses | R62: REGIONAL SP | S62: 1 | X62: BRL | Y62: 10.7 | AB62: 10.7 | AC62: Não
A63: =YEAR(F63) -> 2026 | B63: =UPPER(TEXT(F63,"MMMM")) -> ABRIL | C63: 81666536 | D63: 10306286 | E63: CAIXA 04/2026 | F63: 46114 | G63: BEATRIZ SILVA DE SIQUEIRA | H63: 35575473880 | I63: Aprovado | K63: Material | L63: MATERIAL | M63: Não | N63: Atendimento de chamado caixa econômica | P63: CEF SP SUL | Q63: Saque VExpenses | R63: REGIONAL SP | S63: 1 | X63: BRL | Y63: 44.6 | AB63: 44.6 | AC63: Não
A64: =YEAR(F64) -> 2026 | B64: =UPPER(TEXT(F64,"MMMM")) -> ABRIL | C64: 81660043 | D64: 10306286 | E64: CAIXA 04/2026 | F64: 46114 | G64: BEATRIZ SILVA DE SIQUEIRA | H64: 35575473880 | I64: Aprovado | K64: Recibo | L64: MATERIAL | M64: Não | N64: Atendimento de chamado caixa econômica | P64: CEF SP SUL | Q64: Saque VExpenses | R64: REGIONAL SP | S64: 1 | X64: BRL | Y64: 88.9 | AB64: 88.9 | AC64: Não
A65: =YEAR(F65) -> 2026 | B65: =UPPER(TEXT(F65,"MMMM")) -> ABRIL | C65: 81783947 | D65: 10306286 | E65: CAIXA 04/2026 | F65: 46113 | G65: BEATRIZ SILVA DE SIQUEIRA | H65: 35575473880 | I65: Aprovado | K65: Recibo | L65: MATERIAL | M65: Não | N65: Atendimento de chamado caixa economica | P65: CEF SP SUL | Q65: Saque VExpenses | R65: REGIONAL SP | S65: 1 | X65: BRL | Y65: 173 | AB65: 173 | AC65: Não
A66: =YEAR(F66) -> 2026 | B66: =UPPER(TEXT(F66,"MMMM")) -> ABRIL | C66: 81680496 | D66: 10306286 | E66: CAIXA 04/2026 | F66: 46113 | G66: BEATRIZ SILVA DE SIQUEIRA | H66: 35575473880 | I66: Aprovado | K66: Estacionamento e Pedagio | L66: PEDAGIO | M66: Não | N66: Atendimento de chamado caixa economica | P66: CEF SP SUL | Q66: Saque VExpenses | R66: REGIONAL SP | S66: 1 | X66: BRL | Y66: 593.45 | AB66: 593.45 | AC66: Não
A67: =YEAR(F67) -> 2026 | B67: =UPPER(TEXT(F67,"MMMM")) -> ABRIL | C67: 81666645 | D67: 10306286 | E67: CAIXA 04/2026 | F67: 46113 | G67: BEATRIZ SILVA DE SIQUEIRA | H67: 35575473880 | I67: Aprovado | K67: Recibo | L67: MATERIAL | M67: Não | N67: Atendimento de chamado caixa econômica | P67: CEF SP SUL | Q67: Saque VExpenses | R67: REGIONAL SP | S67: 1 | X67: BRL | Y67: 128.9 | AB67: 128.9 | AC67: Não
A68: =YEAR(F68) -> 2026 | B68: =UPPER(TEXT(F68,"MMMM")) -> ABRIL | C68: 81659718 | D68: 10306286 | E68: CAIXA 04/2026 | F68: 46113 | G68: BEATRIZ SILVA DE SIQUEIRA | H68: 35575473880 | I68: Aprovado | K68: Recibo | L68: MATERIAL | M68: Não | N68: Atendimento de chamado caixa econômica | P68: CEF SP SUL | Q68: Saque VExpenses | R68: REGIONAL SP | S68: 1 | X68: BRL | Y68: 128.9 | AB68: 128.9 | AC68: Não
A69: =YEAR(F69) -> 2026 | B69: =UPPER(TEXT(F69,"MMMM")) -> MARÇO | C69: 79662281 | D69: 9847728 | E69: CAIXA 03/2026 | F69: 46112 | G69: BEATRIZ SILVA DE SIQUEIRA | H69: 35575473880 | I69: Aprovado | K69: Material | L69: MATERIAL | M69: Não | N69: Atendimento de chamado Caixa Econômica | P69: CEF SP SUL | Q69: Saque VExpenses | R69: REGIONAL SP | S69: 1 | X69: BRL | Y69: 77.65 | AB69: 77.65 | AC69: Não
A70: =YEAR(F70) -> 2026 | B70: =UPPER(TEXT(F70,"MMMM")) -> MARÇO | C70: 79662624 | D70: 9847728 | E70: CAIXA 03/2026 | F70: 46109 | G70: BEATRIZ SILVA DE SIQUEIRA | H70: 35575473880 | I70: Aprovado | K70: Material | L70: MATERIAL | M70: Não | N70: Atendimento de chamado Caixa Econômica | P70: CEF SP SUL | Q70: Saque VExpenses | R70: REGIONAL SP | S70: 1 | X70: BRL | Y70: 418.6 | AB70: 418.6 | AC70: Não
A71: =YEAR(F71) -> 2026 | B71: =UPPER(TEXT(F71,"MMMM")) -> MARÇO | C71: 79662492 | D71: 9847728 | E71: CAIXA 03/2026 | F71: 46109 | G71: BEATRIZ SILVA DE SIQUEIRA | H71: 35575473880 | I71: Aprovado | K71: Material | L71: MATERIAL | M71: Não | N71: Atendimento de chamado Caixa Econômica | P71: CEF SP SUL | Q71: Saque VExpenses | R71: REGIONAL SP | S71: 1 | X71: BRL | Y71: 48.9 | AB71: 48.9 | AC71: Não
... A170: =YEAR(F170) -> 2025 | B170: =UPPER(TEXT(F170,"MMMM")) -> DEZEMBRO | C170: 74530661 | D170: 9115050 | E170: Caixa - 12/2025 | F170: 46020 | G170: BEATRIZ SILVA DE SIQUEIRA | H170: 35575473880 | I170: Aprovado | K170: Nota 19 | L170: MATERIAL | M170: Não | N170: Nota 19 | P170: CEF SP SUL | Q170: Saque VExpenses | R170: REGIONAL SP | S170: 1 | X170: BRL | Y170: 168 | AB170: 168 | AC170: Não
A171: =YEAR(F171) -> 2025 | B171: =UPPER(TEXT(F171,"MMMM")) -> DEZEMBRO | C171: 74530612 | D171: 9115050 | E171: Caixa - 12/2025 | F171: 46020 | G171: BEATRIZ SILVA DE SIQUEIRA | H171: 35575473880 | I171: Aprovado | K171: Nota 18 | L171: MATERIAL | M171: Não | N171: Nota 18 | P171: CEF SP SUL | Q171: Saque VExpenses | R171: REGIONAL SP | S171: 1 | W171: 0 | X171: BRL | Y171: 9.9 | AB171: 9.9 | AC171: Não
A172: =YEAR(F172) -> 2025 | B172: =UPPER(TEXT(F172,"MMMM")) -> DEZEMBRO | C172: 74530559 | D172: 9115050 | E172: Caixa - 12/2025 | F172: 46020 | G172: BEATRIZ SILVA DE SIQUEIRA | H172: 35575473880 | I172: Aprovado | K172: Nota 17 | L172: MATERIAL | M172: Não | N172: Nota 17 | P172: CEF SP SUL | Q172: Saque VExpenses | R172: REGIONAL SP | S172: 1 | X172: BRL | Y172: 34.99 | AB172: 34.99 | AC172: Não
A173: =YEAR(F173) -> 2025 | B173: =UPPER(TEXT(F173,"MMMM")) -> DEZEMBRO | C173: 74144317 | D173: 9115050 | E173: Caixa - 12/2025 | F173: 46020 | G173: BEATRIZ SILVA DE SIQUEIRA | H173: 35575473880 | I173: Aprovado | K173: Estacionamento 5 | L173: ESTACIONAMENTO | M173: Não | N173: Atendimento de chamado Caixa Econômica Federal | P173: CEF SP SUL | Q173: Saque VExpenses | R173: REGIONAL SP | S173: 1 | X173: BRL | Y173: 44 | AB173: 44 | AC173: Não
A174: =YEAR(F174) -> 2025 | B174: =UPPER(TEXT(F174,"MMMM")) -> DEZEMBRO | C174: 74144280 | D174: 9115050 | E174: Caixa - 12/2025 | F174: 46020 | G174: BEATRIZ SILVA DE SIQUEIRA | H174: 35575473880 | I174: Aprovado | K174: Estacionamento 4 | L174: ESTACIONAMENTO | M174: Não | N174: Atendimento de chamado Caixa Econômica Federal | P174: CEF SP SUL | Q174: Saque VExpenses | R174: REGIONAL SP | S174: 1 | X174: BRL | Y174: 34 | AB174: 34 | AC174: Não
A175: =YEAR(F175) -> 2025 | B175: =UPPER(TEXT(F175,"MMMM")) -> DEZEMBRO | C175: 74144257 | D175: 9115050 | E175: Caixa - 12/2025 | F175: 46020 | G175: BEATRIZ SILVA DE SIQUEIRA | H175: 35575473880 | I175: Aprovado | K175: Estacionamento 3 | L175: ESTACIONAMENTO | M175: Não | N175: Atendimento de chamado Caixa Econômica Federal | P175: CEF SP SUL | Q175: Saque VExpenses | R175: REGIONAL SP | S175: 1 | X175: BRL | Y175: 96 | AB175: 96 | AC175: Não
A176: =YEAR(F176) -> 2025 | B176: =UPPER(TEXT(F176,"MMMM")) -> DEZEMBRO | C176: 74144233 | D176: 9115050 | E176: Caixa - 12/2025 | F176: 46020 | G176: BEATRIZ SILVA DE SIQUEIRA | H176: 35575473880 | I176: Aprovado | K176: Pedagio 2 | L176: PEDAGIO | M176: Não | N176: Atendimento de chamado Caixa Econômica Federal | P176: CEF SP SUL | Q176: Saque VExpenses | R176: REGIONAL SP | S176: 1 | X176: BRL | Y176: 32.4 | AB176: 32.4 | AC176: Não
A177: =YEAR(F177) -> 2025 | B177: =UPPER(TEXT(F177,"MMMM")) -> DEZEMBRO | C177: 74144208 | D177: 9115050 | E177: Caixa - 12/2025 | F177: 46020 | G177: BEATRIZ SILVA DE SIQUEIRA | H177: 35575473880 | I177: Aprovado | K177: Pedagio 1 | L177: PEDAGIO | M177: Não | N177: Atendimento de chamado Caixa Econômica Federal | P177: CEF SP SUL | Q177: Saque VExpenses | R177: REGIONAL SP | S177: 1 | X177: BRL | Y177: 30.7 | AB177: 30.7 | AC177: Não
A178: =YEAR(F178) -> 2025 | B178: =UPPER(TEXT(F178,"MMMM")) -> DEZEMBRO | C178: 74530720 | D178: 9115050 | E178: Caixa - 12/2025 | F178: 46018 | G178: BEATRIZ SILVA DE SIQUEIRA | H178: 35575473880 | I178: Aprovado | K178: Nota 20 | L178: MATERIAL | M178: Não | N178: Nota 20 | P178: CEF SP SUL | Q178: Saque VExpenses | R178: REGIONAL SP | S178: 1 | X178: BRL | Y178: 35.7 | AB178: 35.7 | AC178: Não
A179: =YEAR(F179) -> 2025 | B179: =UPPER(TEXT(F179,"MMMM")) -> DEZEMBRO | C179: 74531393 | D179: 9115050 | E179: Caixa - 12/2025 | F179: 46009 | G179: BEATRIZ SILVA DE SIQUEIRA | H179: 35575473880 | I179: Aprovado | K179: Nota 31 | L179: MATERIAL | M179: Não | N179: Nota 31 | P179: CEF SP SUL | Q179: Saque VExpenses | R179: REGIONAL SP | S179: 1 | X179: BRL | Y179: 24 | AB179: 24 | AC179: Não
A180: =YEAR(F180) -> 2025 | B180: =UPPER(TEXT(F180,"MMMM")) -> DEZEMBRO | C180: 74531231 | D180: 9115050 | E180: Caixa - 12/2025 | F180: 46009 | G180: BEATRIZ SILVA DE SIQUEIRA | H180: 35575473880 | I180: Aprovado | K180: Nota 28 | L180: MATERIAL | M180: Não | N180: Nota 28 | P180: CEF SP SUL | Q180: Saque VExpenses | R180: REGIONAL SP | S180: 1 | X180: BRL | Y180: 40 | AB180: 40 | AC180: Não
A181: =YEAR(F181) -> 2025 | B181: =UPPER(TEXT(F181,"MMMM")) -> DEZEMBRO | C181: 74530979 | D181: 9115050 | E181: Caixa - 12/2025 | F181: 46008 | G181: BEATRIZ SILVA DE SIQUEIRA | H181: 35575473880 | I181: Aprovado | K181: Nota 25 | L181: MATERIAL | M181: Não | N181: Nota 25 | P181: CEF SP SUL | Q181: Saque VExpenses | R181: REGIONAL SP | S181: 1 | X181: BRL | Y181: 18.8 | AB181: 18.8 | AC181: Não
A182: =YEAR(F182) -> 2025 | B182: =UPPER(TEXT(F182,"MMMM")) -> DEZEMBRO | C182: 74530921 | D182: 9115050 | E182: Caixa - 12/2025 | F182: 46007 | G182: BEATRIZ SILVA DE SIQUEIRA | H182: 35575473880 | I182: Aprovado | K182: Nota 24 | L182: MATERIAL | M182: Não | N182: Nota 24 | P182: CEF SP SUL | Q182: Saque VExpenses | R182: REGIONAL SP | S182: 1 | X182: BRL | Y182: 24.49 | AB182: 24.49 | AC182: Não
A183: =YEAR(F183) -> 2025 | B183: =UPPER(TEXT(F183,"MMMM")) -> DEZEMBRO | C183: 74531043 | D183: 9115050 | E183: Caixa - 12/2025 | F183: 46006 | G183: BEATRIZ SILVA DE SIQUEIRA | H183: 35575473880 | I183: Aprovado | K183: Nota 27 | L183: MATERIAL | M183: Não | N183: Nota 27 | P183: CEF SP SUL | Q183: Saque VExpenses | R183: REGIONAL SP | S183: 1 | X183: BRL | Y183: 36.23 | AB183: 36.23 | AC183: Não
... A202: =YEAR(F202) -> 2025 | B202: =UPPER(TEXT(F202,"MMMM")) -> DEZEMBRO | C202: 72556432 | D202: 8982679 | E202: Caixa - 11/2025 | F202: 45992 | G202: BEATRIZ SILVA DE SIQUEIRA | H202: 35575473880 | I202: Aprovado | K202: Nota 34 | L202: MATERIAL | M202: Não | N202: Nota 34 | P202: CEF SP SUL | Q202: Saque VExpenses | R202: REGIONAL SP | S202: 1 | X202: BRL | Y202: 232.4 | AB202: 232.4 | AC202: Não
A203: =YEAR(F203) -> 2025 | B203: =UPPER(TEXT(F203,"MMMM")) -> NOVEMBRO | C203: 72554200 | D203: 8982679 | E203: Caixa - 11/2025 | F203: 45991 | G203: BEATRIZ SILVA DE SIQUEIRA | H203: 35575473880 | I203: Aprovado | K203: Nota 25 | L203: MATERIAL | M203: Não | N203: Nota 25 | P203: CEF SP SUL | Q203: Saque VExpenses | R203: REGIONAL SP | S203: 1 | W203: 0 | X203: BRL | Y203: 119.96 | AB203: 119.96 | AC203: Não
A204: =YEAR(F204) -> 2025 | B204: =UPPER(TEXT(F204,"MMMM")) -> NOVEMBRO | C204: 72553875 | D204: 8982679 | E204: Caixa - 11/2025 | F204: 45991 | G204: BEATRIZ SILVA DE SIQUEIRA | H204: 35575473880 | I204: Aprovado | K204: Nota 24 | L204: MATERIAL | M204: Não | N204: Nota 24 | P204: CEF SP SUL | Q204: Saque VExpenses | R204: REGIONAL SP | S204: 1 | W204: 0 | X204: BRL | Y204: 150.2 | AB204: 150.2 | AC204: Não
A205: =YEAR(F205) -> 2025 | B205: =UPPER(TEXT(F205,"MMMM")) -> NOVEMBRO | C205: 72556308 | D205: 8982679 | E205: Caixa - 11/2025 | F205: 45987 | G205: BEATRIZ SILVA DE SIQUEIRA | H205: 35575473880 | I205: Aprovado | K205: Nota 33 | L205: MATERIAL | M205: Não | N205: Nota 33 | P205: CEF SP SUL | Q205: Saque VExpenses | R205: REGIONAL SP | S205: 1 | X205: BRL | Y205: 55.5 | AB205: 55.5 | AC205: Não
A206: =YEAR(F206) -> 2025 | B206: =UPPER(TEXT(F206,"MMMM")) -> NOVEMBRO | C206: 72556064 | D206: 8982679 | E206: Caixa - 11/2025 | F206: 45986 | G206: BEATRIZ SILVA DE SIQUEIRA | H206: 35575473880 | I206: Aprovado | K206: Nota 31 | L206: MATERIAL | M206: Não | N206: Nota 31 | P206: CEF SP SUL | Q206: Saque VExpenses | R206: REGIONAL SP | S206: 1 | X206: BRL | Y206: 392.72 | AB206: 392.72 | AC206: Não
A207: =YEAR(F207) -> 2025 | B207: =UPPER(TEXT(F207,"MMMM")) -> NOVEMBRO | C207: 72124812 | D207: 8982679 | E207: Caixa - 11/2025 | F207: 45986 | G207: BEATRIZ SILVA DE SIQUEIRA | H207: 35575473880 | I207: Aprovado | K207: Nota 22 | L207: ESTACIONAMENTO | M207: Não | N207: Nota 22 | P207: CEF SP SUL | Q207: Saque VExpenses | R207: REGIONAL SP | S207: 1 | W207: 0 | X207: BRL | Y207: 55 | AB207: 55 | AC207: Não
A208: =YEAR(F208) -> 2025 | B208: =UPPER(TEXT(F208,"MMMM")) -> NOVEMBRO | C208: 72124473 | D208: 8982679 | E208: Caixa - 11/2025 | F208: 45986 | G208: BEATRIZ SILVA DE SIQUEIRA | H208: 35575473880 | I208: Aprovado | K208: Nota 20 | L208: ESTACIONAMENTO | M208: Não | N208: Nota 20 | P208: CEF SP SUL | Q208: Saque VExpenses | R208: REGIONAL SP | S208: 1 | W208: 0 | X208: BRL | Y208: 60 | AB208: 60 | AC208: Não
A209: =YEAR(F209) -> 2025 | B209: =UPPER(TEXT(F209,"MMMM")) -> NOVEMBRO | C209: 72118688 | D209: 8982679 | E209: Caixa - 11/2025 | F209: 45986 | G209: BEATRIZ SILVA DE SIQUEIRA | H209: 35575473880 | I209: Aprovado | K209: Nota 17 | L209: ESTACIONAMENTO | M209: Não | N209: Nota 17 | P209: CEF SP SUL | Q209: Saque VExpenses | R209: REGIONAL SP | S209: 1 | W209: 0 | X209: BRL | Y209: 44 | AB209: 44 | AC209: Não
A210: =YEAR(F210) -> 2025 | B210: =UPPER(TEXT(F210,"MMMM")) -> NOVEMBRO | C210: 72085860 | D210: 8982679 | E210: Caixa - 11/2025 | F210: 45981 | G210: BEATRIZ SILVA DE SIQUEIRA | H210: 35575473880 | I210: Aprovado | K210: Nota 14 | L210: MATERIAL | M210: Não | N210: Nota 14 | P210: CEF SP SUL | Q210: Saque VExpenses | R210: REGIONAL SP | S210: 1 | X210: BRL | Y210: 72 | AB210: 72 | AC210: Não
A211: =YEAR(F211) -> 2025 | B211: =UPPER(TEXT(F211,"MMMM")) -> NOVEMBRO | C211: 72084089 | D211: 8982679 | E211: Caixa - 11/2025 | F211: 45981 | G211: BEATRIZ SILVA DE SIQUEIRA | H211: 35575473880 | I211: Aprovado | K211: Nota 01 | L211: MATERIAL | M211: Não | N211: Nota 01 | P211: CEF SP SUL | Q211: Saque VExpenses | R211: REGIONAL SP | S211: 1 | X211: BRL | Y211: 93.9 | AB211: 93.9 | AC211: Não
A212: =YEAR(F212) -> 2025 | B212: =UPPER(TEXT(F212,"MMMM")) -> NOVEMBRO | C212: 72085391 | D212: 8982679 | E212: Caixa - 11/2025 | F212: 45979 | G212: BEATRIZ SILVA DE SIQUEIRA | H212: 35575473880 | I212: Aprovado | K212: Nota 09 | L212: MATERIAL | M212: Não | N212: Nota09 | P212: CEF SP SUL | Q212: Saque VExpenses | R212: REGIONAL SP | S212: 1 | X212: BRL | Y212: 13.98 | AB212: 13.98 | AC212: Não
A213: =YEAR(F213) -> 2025 | B213: =UPPER(TEXT(F213,"MMMM")) -> NOVEMBRO | C213: 72084984 | D213: 8982679 | E213: Caixa - 11/2025 | F213: 45979 | G213: BEATRIZ SILVA DE SIQUEIRA | H213: 35575473880 | I213: Aprovado | K213: Nota 08 | L213: MATERIAL | M213: Não | N213: Nota 08 | P213: CEF SP SUL | Q213: Saque VExpenses | R213: REGIONAL SP | S213: 1 | X213: BRL | Y213: 24.1 | AB213: 24.1 | AC213: Não
A214: =YEAR(F214) -> 2025 | B214: =UPPER(TEXT(F214,"MMMM")) -> NOVEMBRO | C214: 72084384 | D214: 8982679 | E214: Caixa - 11/2025 | F214: 45979 | G214: BEATRIZ SILVA DE SIQUEIRA | H214: 35575473880 | I214: Aprovado | K214: Nota 05 | L214: MATERIAL | M214: Não | N214: Nota 05 | P214: CEF SP SUL | Q214: Saque VExpenses | R214: REGIONAL SP | S214: 1 | W214: 0 | X214: BRL | Y214: 45 | AB214: 45 | AC214: Não
A215: =YEAR(F215) -> 2025 | B215: =UPPER(TEXT(F215,"MMMM")) -> NOVEMBRO | C215: 72084150 | D215: 8982679 | E215: Caixa - 11/2025 | F215: 45979 | G215: BEATRIZ SILVA DE SIQUEIRA | H215: 35575473880 | I215: Aprovado | K215: Nota 02 | L215: MATERIAL | M215: Não | N215: Nota 02 | P215: CEF SP SUL | Q215: Saque VExpenses | R215: REGIONAL SP | S215: 1 | X215: BRL | Y215: 35 | AB215: 35 | AC215: Não
A216: =YEAR(F216) -> 2025 | B216: =UPPER(TEXT(F216,"MMMM")) -> NOVEMBRO | C216: 72084860 | D216: 8982679 | E216: Caixa - 11/2025 | F216: 45978 | G216: BEATRIZ SILVA DE SIQUEIRA | H216: 35575473880 | I216: Aprovado | K216: Nota 06 | L216: MATERIAL | M216: Não | N216: Nota 06 | P216: CEF SP SUL | Q216: Saque VExpenses | R216: REGIONAL SP | S216: 1 | W216: 0 | X216: BRL | Y216: 40 | AB216: 40 | AC216: Não
A217: =YEAR(F217) -> 2025 | B217: =UPPER(TEXT(F217,"MMMM")) -> NOVEMBRO | C217: 72085949 | D217: 8982679 | E217: Caixa - 11/2025 | F217: 45974 | G217: BEATRIZ SILVA DE SIQUEIRA | H217: 35575473880 | I217: Aprovado | K217: Nota 15 | L217: MATERIAL | M217: Não | N217: Nota 15 | P217: CEF SP SUL | Q217: Saque VExpenses | R217: REGIONAL SP | S217: 1 | X217: BRL | Y217: 15.4 | AB217: 15.4 | AC217: Não
A218: =YEAR(F218) -> 2025 | B218: =UPPER(TEXT(F218,"MMMM")) -> NOVEMBRO | C218: 72555911 | D218: 8982679 | E218: Caixa - 11/2025 | F218: 45973 | G218: BEATRIZ SILVA DE SIQUEIRA | H218: 35575473880 | I218: Aprovado | K218: Nota 30 | L218: MATERIAL | M218: Não | N218: Nota 30 | P218: CEF SP SUL | Q218: Saque VExpenses | R218: REGIONAL SP | S218: 1 | X218: BRL | Y218: 10.5 | AB218: 10.5 | AC218: Não
A219: =YEAR(F219) -> 2025 | B219: =UPPER(TEXT(F219,"MMMM")) -> NOVEMBRO | C219: 72555638 | D219: 8982679 | E219: Caixa - 11/2025 | F219: 45973 | G219: BEATRIZ SILVA DE SIQUEIRA | H219: 35575473880 | I219: Aprovado | K219: Nota 28 | L219: MATERIAL | M219: Não | N219: Nota 28 | P219: CEF SP SUL | Q219: Saque VExpenses | R219: REGIONAL SP | S219: 1 | X219: BRL | Y219: 10.5 | AB219: 10.5 | AC219: Não
A220: =YEAR(F220) -> 2025 | B220: =UPPER(TEXT(F220,"MMMM")) -> NOVEMBRO | C220: 72555161 | D220: 8982679 | E220: Caixa - 11/2025 | F220: 45973 | G220: BEATRIZ SILVA DE SIQUEIRA | H220: 35575473880 | I220: Aprovado | K220: Nota 28 | L220: MATERIAL | M220: Não | N220: Nota 28 | P220: CEF SP SUL | Q220: Saque VExpenses | R220: REGIONAL SP | S220: 1 | X220: BRL | Y220: 11.99 | AB220: 11.99 | AC220: Não
A221: =YEAR(F221) -> 2025 | B221: =UPPER(TEXT(F221,"MMMM")) -> NOVEMBRO | C221: 72555002 | D221: 8982679 | E221: Caixa - 11/2025 | F221: 45973 | G221: BEATRIZ SILVA DE SIQUEIRA | H221: 35575473880 | I221: Aprovado | K221: Nota 26 | L221: MATERIAL | M221: Não | N221: Nota 25 | P221: CEF SP SUL | Q221: Saque VExpenses | R221: REGIONAL SP | S221: 1 | X221: BRL | Y221: 13 | AB221: 13 | AC221: Não
A222: =YEAR(F222) -> 2025 | B222: =UPPER(TEXT(F222,"MMMM")) -> NOVEMBRO | C222: 72085635 | D222: 8982679 | E222: Caixa - 11/2025 | F222: 45973 | G222: BEATRIZ SILVA DE SIQUEIRA | H222: 35575473880 | I222: Aprovado | K222: Nota 12 | L222: MATERIAL | M222: Não | N222: Nota 12 | P222: CEF SP SUL | Q222: Saque VExpenses | R222: REGIONAL SP | S222: 1 | X222: BRL | Y222: 2.25 | AB222: 2.25 | AC222: Não
A223: =YEAR(F223) -> 2025 | B223: =UPPER(TEXT(F223,"MMMM")) -> NOVEMBRO | C223: 72085487 | D223: 8982679 | E223: Caixa - 11/2025 | F223: 45972 | G223: BEATRIZ SILVA DE SIQUEIRA | H223: 35575473880 | I223: Aprovado | K223: Nota 10 | L223: MATERIAL | M223: Não | N223: Nota 10 | P223: CEF SP SUL | Q223: Saque VExpenses | R223: REGIONAL SP | S223: 1 | X223: BRL | Y223: 113.8 | AB223: 113.8 | AC223: Não
A224: =YEAR(F224) -> 2025 | B224: =UPPER(TEXT(F224,"MMMM")) -> NOVEMBRO | C224: 72555313 | D224: 8982679 | E224: Caixa - 11/2025 | F224: 45971 | G224: BEATRIZ SILVA DE SIQUEIRA | H224: 35575473880 | I224: Aprovado | K224: Nota 29 | L224: MATERIAL | M224: Não | N224: Nota 29 | P224: CEF SP SUL | Q224: Saque VExpenses | R224: REGIONAL SP | S224: 1 | X224: BRL | Y224: 23 | AB224: 23 | AC224: Não
A225: =YEAR(F225) -> 2025 | B225: =UPPER(TEXT(F225,"MMMM")) -> NOVEMBRO | C225: 72085742 | D225: 8982679 | E225: Caixa - 11/2025 | F225: 45968 | G225: BEATRIZ SILVA DE SIQUEIRA | H225: 35575473880 | I225: Aprovado | K225: Nota 13 | L225: MATERIAL | M225: Não | N225: Nota 13 | P225: CEF SP SUL | Q225: Saque VExpenses | R225: REGIONAL SP | S225: 1 | X225: BRL | Y225: 42.5 | AB225: 42.5 | AC225: Não
A226: =YEAR(F226) -> 2025 | B226: =UPPER(TEXT(F226,"MMMM")) -> NOVEMBRO | C226: 72085554 | D226: 8982679 | E226: Caixa - 11/2025 | F226: 45968 | G226: BEATRIZ SILVA DE SIQUEIRA | H226: 35575473880 | I226: Aprovado | K226: Nota 11 | L226: MATERIAL | M226: Não | N226: Nota 11 | P226: CEF SP SUL | Q226: Saque VExpenses | R226: REGIONAL SP | S226: 1 | X226: BRL | Y226: 4.5 | AB226: 4.5 | AC226: Não
A227: =YEAR(F227) -> 2025 | B227: =UPPER(TEXT(F227,"MMMM")) -> NOVEMBRO | C227: 72084320 | D227: 8982679 | E227: Caixa - 11/2025 | F227: 45967 | G227: BEATRIZ SILVA DE SIQUEIRA | H227: 35575473880 | I227: Aprovado | K227: Nota 04 | L227: MATERIAL | M227: Não | N227: Nota 04 | P227: CEF SP SUL | Q227: Saque VExpenses | R227: REGIONAL SP | S227: 1 | X227: BRL | Y227: 7.9 | AB227: 7.9 | AC227: Não
A228: =YEAR(F228) -> 2025 | B228: =UPPER(TEXT(F228,"MMMM")) -> NOVEMBRO | C228: 72084222 | D228: 8982679 | E228: Caixa - 11/2025 | F228: 45967 | G228: BEATRIZ SILVA DE SIQUEIRA | H228: 35575473880 | I228: Aprovado | K228: Nota 03 | L228: MATERIAL | M228: Não | N228: Nota 03 | P228: CEF SP SUL | Q228: Saque VExpenses | R228: REGIONAL SP | S228: 1 | X228: BRL | Y228: 114.9 | AB228: 114.9 | AC228: Não
A229: =YEAR(F229) -> 2025 | B229: =UPPER(TEXT(F229,"MMMM")) -> NOVEMBRO | C229: 72086038 | D229: 8982679 | E229: Caixa - 11/2025 | F229: 45966 | G229: BEATRIZ SILVA DE SIQUEIRA | H229: 35575473880 | I229: Aprovado | K229: Nota 16 | L229: MATERIAL | M229: Não | N229: Nota 16 | P229: CEF SP SUL | Q229: Saque VExpenses | R229: REGIONAL SP | S229: 1 | X229: BRL | Y229: 22.5 | AB229: 22.5 | AC229: Não
A230: =YEAR(F230) -> 2025 | B230: =UPPER(TEXT(F230,"MMMM")) -> NOVEMBRO | C230: 72084581 | D230: 8982679 | E230: Caixa - 11/2025 | F230: 45965 | G230: BEATRIZ SILVA DE SIQUEIRA | H230: 35575473880 | I230: Aprovado | K230: Nota 07 | L230: MATERIAL | M230: Não | N230: Nota 07 | P230: CEF SP SUL | Q230: Saque VExpenses | R230: REGIONAL SP | S230: 1 | W230: 0 | X230: BRL | Y230: 27.5 | AB230: 27.5 | AC230: Não
A231: =YEAR(F231) -> 2025 | B231: =UPPER(TEXT(F231,"MMMM")) -> NOVEMBRO | C231: 72556202 | D231: 8982679 | E231: Caixa - 11/2025 | F231: 45964 | G231: BEATRIZ SILVA DE SIQUEIRA | H231: 35575473880 | I231: Aprovado | K231: Nota 32 | L231: MATERIAL | M231: Não | N231: Nota 32 | P231: CEF SP SUL | Q231: Saque VExpenses | R231: REGIONAL SP | S231: 1 | X231: BRL | Y231: 17.8 | AB231: 17.8 | AC231: Não
A232: =YEAR(F232) -> 2025 | B232: =UPPER(TEXT(F232,"MMMM")) -> NOVEMBRO | C232: 72569462 | D232: 8982679 | E232: Caixa - 11/2025 | F232: 45962 | G232: BEATRIZ SILVA DE SIQUEIRA | H232: 35575473880 | I232: Aprovado | K232: Nota 38 | L232: ESTACIONAMENTO | M232: Não | N232: Nota 38 | P232: CEF SP SUL | Q232: Saque VExpenses | R232: REGIONAL SP | S232: 1 | W232: 0 | X232: BRL | Y232: 15 | AB232: 15 | AC232: Não
A233: =YEAR(F233) -> 2025 | B233: =UPPER(TEXT(F233,"MMMM")) -> NOVEMBRO | C233: 72569308 | D233: 8982679 | E233: Caixa - 11/2025 | F233: 45962 | G233: BEATRIZ SILVA DE SIQUEIRA | H233: 35575473880 | I233: Aprovado | K233: Nota 35 | L233: ESTACIONAMENTO | M233: Não | N233: Nota 35 | P233: CEF SP SUL | Q233: Saque VExpenses | R233: REGIONAL SP | S233: 1 | W233: 0 | X233: BRL | Y233: 45.4 | AB233: 45.4 | AC233: Não
A234: =YEAR(F234) -> 2025 | B234: =UPPER(TEXT(F234,"MMMM")) -> NOVEMBRO | C234: 72569091 | D234: 8982679 | E234: Caixa - 11/2025 | F234: 45962 | G234: BEATRIZ SILVA DE SIQUEIRA | H234: 35575473880 | I234: Aprovado | K234: Nota 34 | L234: ESTACIONAMENTO | M234: Não | N234: Nota 34 | P234: CEF SP SUL | Q234: Saque VExpenses | R234: REGIONAL SP | S234: 1 | W234: 0 | X234: BRL | Y234: 70.8 | AB234: 70.8 | AC234: Não
A235: =YEAR(F235) -> 2025 | B235: =UPPER(TEXT(F235,"MMMM")) -> NOVEMBRO | C235: 72124705 | D235: 8982679 | E235: Caixa - 11/2025 | F235: 45962 | G235: BEATRIZ SILVA DE SIQUEIRA | H235: 35575473880 | I235: Aprovado | K235: Nota 21 | L235: ESTACIONAMENTO | M235: Não | N235: Nota 21 | P235: CEF SP SUL | Q235: Saque VExpenses | R235: REGIONAL SP | S235: 1 | W235: 0 | X235: BRL | Y235: 24.5 | AB235: 24.5 | AC235: Não
A236: =YEAR(F236) -> 2025 | B236: =UPPER(TEXT(F236,"MMMM")) -> NOVEMBRO | C236: 72118815 | D236: 8982679 | E236: Caixa - 11/2025 | F236: 45962 | G236: BEATRIZ SILVA DE SIQUEIRA | H236: 35575473880 | I236: Aprovado | K236: Nota 19 | L236: ESTACIONAMENTO | M236: Não | N236: Nota 19 | P236: CEF SP SUL | Q236: Saque VExpenses | R236: REGIONAL SP | S236: 1 | W236: 0 | X236: BRL | Y236: 27 | AB236: 27 | AC236: Não
A237: =YEAR(F237) -> 2025 | B237: =UPPER(TEXT(F237,"MMMM")) -> NOVEMBRO | C237: 72118754 | D237: 8982679 | E237: Caixa - 11/2025 | F237: 45962 | G237: BEATRIZ SILVA DE SIQUEIRA | H237: 35575473880 | I237: Aprovado | K237: Nota 18 | L237: ESTACIONAMENTO | M237: Não | N237: Nota 18 | P237: CEF SP SUL | Q237: Saque VExpenses | R237: REGIONAL SP | S237: 1 | W237: 0 | X237: BRL | Y237: 58 | AB237: 58 | AC237: Não
A238: =YEAR(F238) -> 2025 | B238: =UPPER(TEXT(F238,"MMMM")) -> OUTUBRO | C238: 72082048 | D238: 8982679 | E238: Caixa - 11/2025 | F238: 45946 | G238: BEATRIZ SILVA DE SIQUEIRA | H238: 35575473880 | I238: Aprovado | K238: Nota 17 | L238: MATERIAL | M238: Não | N238: Nota 17 | P238: CEF SP SUL | Q238: Saque VExpenses | R238: REGIONAL SP | S238: 1 | W238: 0 | X238: BRL | Y238: 29.9 | AB238: 29.9 | AC238: Não
A239: =YEAR(F239) -> 2025 | B239: =UPPER(TEXT(F239,"MMMM")) -> OUTUBRO | C239: 72083034 | D239: 8981940 | E239: Caixa - 10/2025 | F239: 45961 | G239: BEATRIZ SILVA DE SIQUEIRA | H239: 35575473880 | I239: Aprovado | K239: Nota 29 | L239: MATERIAL | M239: Não | N239: Nota 29 | P239: CEF SP SUL | Q239: Saque VExpenses | R239: REGIONAL SP | S239: 1 | X239: BRL | Y239: 9.9 | AB239: 9.9 | AC239: Não
A240: =YEAR(F240) -> 2025 | B240: =UPPER(TEXT(F240,"MMMM")) -> OUTUBRO | C240: 72081670 | D240: 8981940 | E240: Caixa - 10/2025 | F240: 45961 | G240: BEATRIZ SILVA DE SIQUEIRA | H240: 35575473880 | I240: Aprovado | K240: Nota 12 | L240: MATERIAL | M240: Não | N240: Nota 12 | P240: CEF SP SUL | Q240: Saque VExpenses | R240: REGIONAL SP | S240: 1 | X240: BRL | Y240: 56.74 | AB240: 56.74 | AC240: Não
A241: =YEAR(F241) -> 2025 | B241: =UPPER(TEXT(F241,"MMMM")) -> OUTUBRO | C241: 72082790 | D241: 8981940 | E241: Caixa - 10/2025 | F241: 45960 | G241: BEATRIZ SILVA DE SIQUEIRA | H241: 35575473880 | I241: Aprovado | K241: Nota 25 | L241: MATERIAL | M241: Não | N241: Nota 25 | P241: CEF SP SUL | Q241: Saque VExpenses | R241: REGIONAL SP | S241: 1 | X241: BRL | Y241: 13.77 | AB241: 13.77 | AC241: Não
A242: =YEAR(F242) -> 2025 | B242: =UPPER(TEXT(F242,"MMMM")) -> OUTUBRO | C242: 72082631 | D242: 8981940 | E242: Caixa - 10/2025 | F242: 45960 | G242: BEATRIZ SILVA DE SIQUEIRA | H242: 35575473880 | I242: Aprovado | K242: Nota 23 | L242: MATERIAL | M242: Não | N242: Nota 23 | P242: CEF SP SUL | Q242: Saque VExpenses | R242: REGIONAL SP | S242: 1 | X242: BRL | Y242: 119.96 | AB242: 119.96 | AC242: Não
A243: =YEAR(F243) -> 2025 | B243: =UPPER(TEXT(F243,"MMMM")) -> OUTUBRO | C243: 72081812 | D243: 8981940 | E243: Caixa - 10/2025 | F243: 45960 | G243: BEATRIZ SILVA DE SIQUEIRA | H243: 35575473880 | I243: Aprovado | K243: Nota 13 | L243: MATERIAL | M243: Não | N243: Nota 13 | P243: CEF SP SUL | Q243: Saque VExpenses | R243: REGIONAL SP | S243: 1 | X243: BRL | Y243: 19.8 | AB243: 19.8 | AC243: Não
A244: =YEAR(F244) -> 2025 | B244: =UPPER(TEXT(F244,"MMMM")) -> OUTUBRO | C244: 72083111 | D244: 8981940 | E244: Caixa - 10/2025 | F244: 45959 | G244: BEATRIZ SILVA DE SIQUEIRA | H244: 35575473880 | I244: Aprovado | K244: Nota 30 | L244: MATERIAL | M244: Não | N244: Nota 30 | P244: CEF SP SUL | Q244: Saque VExpenses | R244: REGIONAL SP | S244: 1 | X244: BRL | Y244: 32.33 | AB244: 32.33 | AC244: Não
...

Sheet EXTRATO
A1: ANO | B1: MÊS | C1: Data | D1: Hora | E1: Código de Transação | F1: Usuário | G1: Tipo | H1: Descrição | I1: Valor | K1: Soma de Valor | L1: Rótulos de Coluna
A2: =YEAR(C2) -> 2025 | B2: =UPPER(TEXT(C2,"MMMM")) -> MAIO | C2: 45805.443 | D2: 10:37:53 | E2: 3B2E367253EF8CA8E83B7A5A0A5FA3EA | F2: Beatriz Silva de Siqueira | G2: Carga | H2: Transf. EQS > Beatriz S. d. Siqueira: 2 QUINZENA - MAIO/2025 | I2: 1183.02 | K2: Rótulos de Linha | L2: Carga | M2: Saque | N2: Taxa | O2: Transferência | P2: Total Geral
A3: =YEAR(C3) -> 2025 | B3: =UPPER(TEXT(C3,"MMMM")) -> JUNHO | C3: 45819.749 | D3: 17:57:52 | E3: 6CC895AB9D844418520C750FC20F1192 | F3: Beatriz Silva de Siqueira | G3: Carga | H3: Transf. EQS > Beatriz S. d. Siqueira | I3: 16.98 | K3: 2025 | L3: 14777.43 | M3: -14640 | N3: -126 | P3: 11.43
A4: =YEAR(C4) -> 2025 | B4: =UPPER(TEXT(C4,"MMMM")) -> JUNHO | C4: 45824.754 | D4: 18:05:58 | E4: 3C9F00EDCE014FBD8D62E371A1889A16 | F4: Beatriz Silva de Siqueira | G4: Saque | H4: TECBAN-MOOCA PLAZA SHO | I4: -1000 | K4: mai | L4: 1183.02 | P4: 1183.02
A5: =YEAR(C5) -> 2025 | B5: =UPPER(TEXT(C5,"MMMM")) -> JUNHO | C5: 45824.755 | D5: 18:06:56 | E5: 5446F8D96F787419D3864F73C9DF89CB | F5: Beatriz Silva de Siqueira | G5: Saque | H5: TECBAN-MOOCA PLAZA SHO | I5: -180 | K5: jun | L5: 1210.98 | M5: -2180 | N5: -21 | P5: -990.02
A6: =YEAR(C6) -> 2025 | B6: =UPPER(TEXT(C6,"MMMM")) -> JUNHO | C6: 45824.764 | D6: 18:20:25 | E6: 625B05FFFEA456DEA35C7C79E56DE386 | F6: Beatriz Silva de Siqueira | G6: Taxa | H6: Taxa de saque | I6: -7 | K6: jul | L6: 2953.46 | M6: -3100 | N6: -28 | P6: -174.54
A7: =YEAR(C7) -> 2025 | B7: =UPPER(TEXT(C7,"MMMM")) -> JUNHO | C7: 45824.764 | D7: 18:20:37 | E7: 71BC5C5D6727F3D25B3F1ED2B57011BB | F7: Beatriz Silva de Siqueira | G7: Taxa | H7: Taxa de saque | I7: -7 | K7: set | L7: 4195.54 | M7: -4000 | N7: -28 | P7: 167.54
A8: =YEAR(C8) -> 2025 | B8: =UPPER(TEXT(C8,"MMMM")) -> JUNHO | C8: 45833.707 | D8: 16:57:30 | E8: 0AAB4CEC1E1640E0EC2962B907DE6EC9 | F8: Beatriz Silva de Siqueira | G8: Carga | H8: Transf. EQS > Beatriz S. d. Siqueira | I8: 1194 | K8: out | L8: 2957.62 | M8: -3110 | N8: -28 | P8: -180.38
A9: =YEAR(C9) -> 2025 | B9: =UPPER(TEXT(C9,"MMMM")) -> JUNHO | C9: 45834.73 | D9: 17:30:34 | E9: F7EEC84E9CFE8F5856FC9F4367FA9B72 | F9: Beatriz Silva de Siqueira | G9: Saque | H9: TECBAN-MOOCA PLAZA SHO | I9: -1000 | K9: nov | L9: 688.07 | M9: -680 | N9: -7 | P9: 1.07
A10: =YEAR(C10) -> 2025 | B10: =UPPER(TEXT(C10,"MMMM")) -> JUNHO | C10: 45834.758 | D10: 18:11:16 | E10: A7D4C6FB4F0F0F497BA8262E922B302C | F10: Beatriz Silva de Siqueira | G10: Taxa | H10: Taxa de saque | I10: -7 | K10: dez | L10: 1588.74 | M10: -1570 | N10: -14 | P10: 4.74
A11: =YEAR(C11) -> 2025 | B11: =UPPER(TEXT(C11,"MMMM")) -> JULHO | C11: 45849.66 | D11: 15:49:54 | E11: D4A808FA2449A8946B3F309D124CDD05 | F11: Beatriz Silva de Siqueira | G11: Carga | H11: Transf. EQS > Beatriz S. d. Siqueira | I11: 1026.01 | K11: 2026 | L11: 12914 | M11: -12790 | N11: -126 | O11: -6.43 | P11: -8.43
A12: =YEAR(C12) -> 2025 | B12: =UPPER(TEXT(C12,"MMMM")) -> JULHO | C12: 45849.706 | D12: 16:56:09 | E12: 464BAD8451A9F8050B92FB44450257E8 | F12: Beatriz Silva de Siqueira | G12: Saque | H12: TECBAN-AP NOVO BRILHOA | I12: -1000 | K12: jan | L12: 4306 | M12: -4090 | N12: -35 | O12: -6.43 | P12: 174.57
A13: =YEAR(C13) -> 2025 | B13: =UPPER(TEXT(C13,"MMMM")) -> JULHO | C13: 45849.706 | D13: 16:57:14 | E13: 00442BEA4336339D7EFAE2BF1026CEDE | F13: Beatriz Silva de Siqueira | G13: Saque | H13: TECBAN-AP NOVO BRILHOA | I13: -200 | K13: fev | L13: 2013.46 | M13: -2170 | N13: -21 | P13: -177.54
A14: =YEAR(C14) -> 2025 | B14: =UPPER(TEXT(C14,"MMMM")) -> JULHO | C14: 45849.715 | D14: 17:09:53 | E14: 8FBCD955A516D74EB813F05AD0274A46 | F14: Beatriz Silva de Siqueira | G14: Taxa | H14: Taxa de saque | I14: -7 | K14: mar | L14: 1812.44 | M14: -1800 | N14: -14 | P14: -1.56
A15: =YEAR(C15) -> 2025 | B15: =UPPER(TEXT(C15,"MMMM")) -> JULHO | C15: 45849.716 | D15: 17:10:20 | E15: 97E9E9BE620FE3AFB49771CC1D1DBBEC | F15: Beatriz Silva de Siqueira | G15: Taxa | H15: Taxa de saque | I15: -7 | K15: abr | L15: 1810.16 | M15: -1800 | N15: -14 | P15: -3.84
A16: =YEAR(C16) -> 2025 | B16: =UPPER(TEXT(C16,"MMMM")) -> JULHO | C16: 45863.666 | D16: 15:59:27 | E16: AAB86613620AB63465EA3CBD7A3A03EC | F16: Beatriz Silva de Siqueira | G16: Carga | H16: Transf. EQS > Beatriz S. d. Siqueira | I16: 1927.45 | K16: mai | L16: 1594.15 | M16: -1560 | N16: -28 | P16: 6.15
A17: =YEAR(C17) -> 2025 | B17: =UPPER(TEXT(C17,"MMMM")) -> JULHO | C17: 45869.496 | D17: 11:53:39 | E17: 18374CA515DC33AE05550F9BF9B389C6 | F17: Beatriz Silva de Siqueira | G17: Saque | H17: TECBAN-SONDA CARRAO II | I17: -1000 | K17: jun | L17: 391.86 | M17: -380 | N17: -7 | P17: 4.86
A18: =YEAR(C18) -> 2025 | B18: =UPPER(TEXT(C18,"MMMM")) -> JULHO | C18: 45869.496 | D18: 11:54:48 | E18: 2EC89539A2833F8F8C69128B755F1430 | F18: Beatriz Silva de Siqueira | G18: Saque | H18: TECBAN-SONDA CARRAO II | I18: -900 | K18: jul | L18: 985.93 | M18: -990 | N18: -7 | P18: -11.07
A19: =YEAR(C19) -> 2025 | B19: =UPPER(TEXT(C19,"MMMM")) -> JULHO | C19: 45869.501 | D19: 12:02:09 | E19: BBBE6C9431921475F44F05F98E670F69 | F19: Beatriz Silva de Siqueira | G19: Taxa | H19: Taxa de saque | I19: -7 | K19: Total Geral | L19: 27691.43 | M19: -27430 | N19: -252 | O19: -6.43 | P19: 3
A20: =YEAR(C20) -> 2025 | B20: =UPPER(TEXT(C20,"MMMM")) -> JULHO | C20: 45869.502 | D20: 12:02:36 | E20: 8B887FAC7780181AA39797F7C42125C2 | F20: Beatriz Silva de Siqueira | G20: Taxa | H20: Taxa de saque | I20: -7
A21: =YEAR(C21) -> 2025 | B21: =UPPER(TEXT(C21,"MMMM")) -> SETEMBRO | C21: 45911.688 | D21: 16:30:27 | E21: 88B68D4FC8B377BCCFFB314AF617F449 | F21: Beatriz Silva de Siqueira | G21: Carga | H21: Transf. EQS > Beatriz S. d. Siqueira | I21: 2181.54
A22: =YEAR(C22) -> 2025 | B22: =UPPER(TEXT(C22,"MMMM")) -> SETEMBRO | C22: 45913.682 | D22: 16:21:29 | E22: E135C626166E2808F99BA49EFC549822 | F22: Beatriz Silva de Siqueira | G22: Saque | H22: TECBAN-CARREFOUR SCS I | I22: -1000
A23: =YEAR(C23) -> 2025 | B23: =UPPER(TEXT(C23,"MMMM")) -> SETEMBRO | C23: 45913.682 | D23: 16:21:57 | E23: F893E17394162C0198BF1EE7006A0101 | F23: Beatriz Silva de Siqueira | G23: Taxa | H23: Taxa de saque | I23: -7
A24: =YEAR(C24) -> 2025 | B24: =UPPER(TEXT(C24,"MMMM")) -> SETEMBRO | C24: 45913.683 | D24: 16:23:30 | E24: C4365B707920100EE3526ACFE0373A9F | F24: Beatriz Silva de Siqueira | G24: Saque | H24: TECBAN-CARREFOUR SCS I | I24: -1000
A25: =YEAR(C25) -> 2025 | B25: =UPPER(TEXT(C25,"MMMM")) -> SETEMBRO | C25: 45913.683 | D25: 16:23:57 | E25: 341DB4A6711C556245A483D2436CDAC9 | F25: Beatriz Silva de Siqueira | G25: Taxa | H25: Taxa de saque | I25: -7
A26: =YEAR(C26) -> 2025 | B26: =UPPER(TEXT(C26,"MMMM")) -> SETEMBRO | C26: 45925.706 | D26: 16:57:21 | E26: ABC85FAB8B75C6014CD864C095F66C29 | F26: Beatriz Silva de Siqueira | G26: Carga | H26: Transf. EQS > Beatriz S. d. Siqueira | I26: 2014
A27: =YEAR(C27) -> 2025 | B27: =UPPER(TEXT(C27,"MMMM")) -> SETEMBRO | C27: 45925.748 | D27: 17:57:00 | E27: 3622E47A201D701FF773523BC8C4118F | F27: Beatriz Silva de Siqueira | G27: Saque | H27: TECBAN-MOOCA PLAZA SHO | I27: -1000
A28: =YEAR(C28) -> 2025 | B28: =UPPER(TEXT(C28,"MMMM")) -> SETEMBRO | C28: 45925.749 | D28: 17:57:59 | E28: A0C51E12EE3405BB01BBE1EBDA1F2D91 | F28: Beatriz Silva de Siqueira | G28: Saque | H28: TECBAN-MOOCA PLAZA SHO | I28: -1000
A29: =YEAR(C29) -> 2025 | B29: =UPPER(TEXT(C29,"MMMM")) -> SETEMBRO | C29: 45925.75 | D29: 17:59:59 | E29: 9247D0152B6C54B4F9784B15F34C1FB3 | F29: Beatriz Silva de Siqueira | G29: Taxa | H29: Taxa de saque | I29: -7
A30: =YEAR(C30) -> 2025 | B30: =UPPER(TEXT(C30,"MMMM")) -> SETEMBRO | C30: 45925.751 | D30: 18:00:48 | E30: 3176B58A01A077807DBFA8F2E1A95F05 | F30: Beatriz Silva de Siqueira | G30: Taxa | H30: Taxa de saque | I30: -7
A31: =YEAR(C31) -> 2025 | B31: =UPPER(TEXT(C31,"MMMM")) -> OUTUBRO | C31: 45943.7 | D31: 16:48:42 | E31: 3A1EBC8703A72CFB1FA11D5794365B17 | F31: Beatriz Silva de Siqueira | G31: Carga | H31: Transf. EQS > Beatriz S. d. Siqueira | I31: 1471.81
... A98: =YEAR(C98) -> 2026 | B98: =UPPER(TEXT(C98,"MMMM")) -> JULHO | C98: 46218.634 | D98: 15:12:58 | E98: 81E0ED60717A7B7827C572A99E532C61 | F98: Beatriz Silva de Siqueira | G98: Taxa | H98: Taxa de saque | I98: -7
