Workbook
Name SegmentaçãodeDados_GESTOR: #N/A

Sheet 1 QZ VEXPENSES 04_2026
I5: =SUBTOTAL(9,I7:I1048576) -> -55059.77 | J5: =SUBTOTAL(9,J7:J1048576) -> 292255.22 | K5: =SUBTOTAL(9,K7:K1048576) -> 455630 | L5: =SUBTOTAL(9,L7:L1048576) -> 75298.19 | M5: =SUBTOTAL(9,M7:M1048576) -> 0 | N5: =SUBTOTAL(9,N332:N1048576) -> -492.85 | O5: =SUBTOTAL(9,O7:O1048576) -> 19919 | P5: =SUBTOTAL(9,P7:P1048576) -> 225885.72
B6: PORTADOR | C6: CPF | D6: STATUS COLAB | E6: CENTRO CUSTO | F6: COD CENTRO CUSTO | G6: GESTOR | H6: DIREÇÃO | I6: SALDO REEMBOLSAR | J6: SALDO FINAL | K6: 1QZ DE ABRIL 26 | L6: SALDO CARTAO | M6: ADIANTAMENTO | N6: CARGA PARCIAL | O6: REEMBOLSO | P6: CARGA FINAL | Q6: STATUS DO CARTAO | R6: OBS
B7: RAFAEL AMORIM VELLO | C7: 01677920599 | D7: =_xlfn.XLOOKUP(Tabela1[[#This Row],[CPF]],[1]Funcionário!$B:$B,[1]Funcionário!$H:$H) -> ATIVO | E7: CEF NORTE OESTE BA | G7: GERSON OLIVEIRA | H7: ROGERIO SCATAMBULO | J7: 291.66 | K7: 16000 | L7: 20 | N7: =Tabela1[[#This Row],[1QZ DE ABRIL 26]]-Tabela1[[#This Row],[SALDO FINAL]]-Tabela1[[#This Row],[SALDO CARTAO]]-Tabela1[[#This Row],[ADIANTAMENTO]] -> 15688.34 | O7: 0 | P7: =IF(Tabela1[[#This Row],[CARGA PARCIAL]]<0,0,Tabela1[[#This Row],[CARGA PARCIAL]])+Tabela1[[#This Row],[REEMBOLSO]] -> 15688.34 | Q7: Cartão ativo
B8: ABNER ANDRADE CAVALCANTE | C8: 02027745203 | D8: =_xlfn.XLOOKUP(Tabela1[[#This Row],[CPF]],[1]Funcionário!$B:$B,[1]Funcionário!$H:$H) -> ATIVO | E8: CEF AM AC RR | G8: ANGELICA SOARES | H8: ROGERIO SCATAMBULO | I8: -98.92 | J8: 0 | K8: 9840 | L8: 5 | N8: =Tabela1[[#This Row],[1QZ DE ABRIL 26]]-Tabela1[[#This Row],[SALDO FINAL]]-Tabela1[[#This Row],[SALDO CARTAO]]-Tabela1[[#This Row],[ADIANTAMENTO]] -> 9835 | O8: 0 | P8: =IF(Tabela1[[#This Row],[CARGA PARCIAL]]<0,0,Tabela1[[#This Row],[CARGA PARCIAL]])+Tabela1[[#This Row],[REEMBOLSO]] -> 9835 | Q8: Cartão ativo
B9: ANDRE ARANHA MEISTER | C9: 03032275326 | D9: =_xlfn.XLOOKUP(Tabela1[[#This Row],[CPF]],[1]Funcionário!$B:$B,[1]Funcionário!$H:$H) -> ATIVO | E9: BB MARANHAO MA | G9: ANGELICA SOARES | H9: ROGERIO SCATAMBULO | J9: 18329.5 | K9: 9000 | L9: 1154.94 | N9: =Tabela1[[#This Row],[1QZ DE ABRIL 26]]-Tabela1[[#This Row],[SALDO FINAL]]-Tabela1[[#This Row],[SALDO CARTAO]]-Tabela1[[#This Row],[ADIANTAMENTO]] -> -10484.44 | O9: 0 | P9: =IF(Tabela1[[#This Row],[CARGA PARCIAL]]<0,0,Tabela1[[#This Row],[CARGA PARCIAL]])+Tabela1[[#This Row],[REEMBOLSO]] -> 0 | Q9: Cartão ativo
B10: JAEDER RODRIGUES JUNIOR | C10: 07505987607 | D10: =_xlfn.XLOOKUP(Tabela1[[#This Row],[CPF]],[1]Funcionário!$B:$B,[1]Funcionário!$H:$H) -> ATIVO | E10: CEF NORDESTE MG | G10: HUGO ALEXANDRE | H10: MARCOS CARIAS | J10: 1614.44 | K10: 7000 | L10: 2 | N10: =Tabela1[[#This Row],[1QZ DE ABRIL 26]]-Tabela1[[#This Row],[SALDO FINAL]]-Tabela1[[#This Row],[SALDO CARTAO]]-Tabela1[[#This Row],[ADIANTAMENTO]] -> 5383.56 | O10: 0 | P10: =IF(Tabela1[[#This Row],[CARGA PARCIAL]]<0,0,Tabela1[[#This Row],[CARGA PARCIAL]])+Tabela1[[#This Row],[REEMBOLSO]] -> 5383.56 | Q10: Cartão ativo
B11: JUSTINO NOGUEIRA PEIXOTO JUNIOR | C11: 09246793790 | D11: =_xlfn.XLOOKUP(Tabela1[[#This Row],[CPF]],[1]Funcionário!$B:$B,[1]Funcionário!$H:$H) -> ATIVO | E11: PTB EDISE RJ | G11: ALLAN JEFFERSON | H11: ROGERIO SCATAMBULO | I11: -428.82 | J11: 0 | K11: 7000 | L11: 7000 | N11: =Tabela1[[#This Row],[1QZ DE ABRIL 26]]-Tabela1[[#This Row],[SALDO FINAL]]-Tabela1[[#This Row],[SALDO CARTAO]]-Tabela1[[#This Row],[ADIANTAMENTO]] -> 0 | O11: 0 | P11: =IF(Tabela1[[#This Row],[CARGA PARCIAL]]<0,0,Tabela1[[#This Row],[CARGA PARCIAL]])+Tabela1[[#This Row],[REEMBOLSO]] -> 0 | Q11: Cartão ativo
B12: EDSON VEIGA SILVEIRA | C12: 62063774072 | D12: =_xlfn.XLOOKUP(Tabela1[[#This Row],[CPF]],[1]Funcionário!$B:$B,[1]Funcionário!$H:$H) -> ATIVO | E12: CLARO CO | G12: ANGELICA SOARES | H12: ROGERIO SCATAMBULO | J12: 226.65 | K12: 6800 | L12: 4635.66 | N12: =Tabela1[[#This Row],[1QZ DE ABRIL 26]]-Tabela1[[#This Row],[SALDO FINAL]]-Tabela1[[#This Row],[SALDO CARTAO]]-Tabela1[[#This Row],[ADIANTAMENTO]] -> 1937.69 | O12: 0 | P12: =IF(Tabela1[[#This Row],[CARGA PARCIAL]]<0,0,Tabela1[[#This Row],[CARGA PARCIAL]])+Tabela1[[#This Row],[REEMBOLSO]] -> 1937.69 | Q12: Cartão ativo
B13: LUDGERO HORACIO DE OLIVEIRA | C13: 06576198922 | D13: =_xlfn.XLOOKUP(Tabela1[[#This Row],[CPF]],[1]Funcionário!$B:$B,[1]Funcionário!$H:$H) -> ATIVO | E13: CEF NORTE PR | G13: LEANDRO MARCUSSO | H13: EVERSON GAIDSTIECHI | J13: 3693.1 | K13: 6500 | L13: 981.69 | N13: =Tabela1[[#This Row],[1QZ DE ABRIL 26]]-Tabela1[[#This Row],[SALDO FINAL]]-Tabela1[[#This Row],[SALDO CARTAO]]-Tabela1[[#This Row],[ADIANTAMENTO]] -> 1825.21 | O13: 0 | P13: =IF(Tabela1[[#This Row],[CARGA PARCIAL]]<0,0,Tabela1[[#This Row],[CARGA PARCIAL]])+Tabela1[[#This Row],[REEMBOLSO]] -> 1825.21 | Q13: Cartão ativo
B14: BRUNO OLIVEIRA DIAS | C14: 11992259755 | D14: =_xlfn.XLOOKUP(Tabela1[[#This Row],[CPF]],[1]Funcionário!$B:$B,[1]Funcionário!$H:$H) -> ATIVO | E14: PTB TIC INFRA | G14: VINICIUS LOCATELLY | H14: MARCOS CARIAS | J14: 4637.6 | K14: 6200 | L14: 4283.83 | N14: =Tabela1[[#This Row],[1QZ DE ABRIL 26]]-Tabela1[[#This Row],[SALDO FINAL]]-Tabela1[[#This Row],[SALDO CARTAO]]-Tabela1[[#This Row],[ADIANTAMENTO]] -> -2721.43 | O14: 0 | P14: =IF(Tabela1[[#This Row],[CARGA PARCIAL]]<0,0,Tabela1[[#This Row],[CARGA PARCIAL]])+Tabela1[[#This Row],[REEMBOLSO]] -> 0 | Q14: Cartão ativo
B15: JOSE CARLOS BATISTA | C15: 26652452804 | D15: =_xlfn.XLOOKUP(Tabela1[[#This Row],[CPF]],[1]Funcionário!$B:$B,[1]Funcionário!$H:$H) -> ATIVO | E15: PTB INFRA SUDESTE | G15: LEANDRO NUNES | H15: EVERSON GAIDSTIECHI | J15: 1674.27 | K15: 6000 | L15: 58 | N15: =Tabela1[[#This Row],[1QZ DE ABRIL 26]]-Tabela1[[#This Row],[SALDO FINAL]]-Tabela1[[#This Row],[SALDO CARTAO]]-Tabela1[[#This Row],[ADIANTAMENTO]] -> 4267.73 | O15: 0 | P15: =IF(Tabela1[[#This Row],[CARGA PARCIAL]]<0,0,Tabela1[[#This Row],[CARGA PARCIAL]])+Tabela1[[#This Row],[REEMBOLSO]] -> 4267.73 | Q15: Cartão ativo
B16: LUCAS MARTINS MACAN | C16: 00975748998 | D16: =_xlfn.XLOOKUP(Tabela1[[#This Row],[CPF]],[1]Funcionário!$B:$B,[1]Funcionário!$H:$H) -> ATIVO | E16: CEF CEARA | G16: GERSON OLIVEIRA | H16: ROGERIO SCATAMBULO | J16: 1784.53 | K16: 6000 | L16: 4.06 | N16: =Tabela1[[#This Row],[1QZ DE ABRIL 26]]-Tabela1[[#This Row],[SALDO FINAL]]-Tabela1[[#This Row],[SALDO CARTAO]]-Tabela1[[#This Row],[ADIANTAMENTO]] -> 4211.41 | O16: 0 | P16: =IF(Tabela1[[#This Row],[CARGA PARCIAL]]<0,0,Tabela1[[#This Row],[CARGA PARCIAL]])+Tabela1[[#This Row],[REEMBOLSO]] -> 4211.41 | Q16: Cartão ativo
B17: SAULO ARAUJO DE PAULA | C17: 31040091806 | D17: =_xlfn.XLOOKUP(Tabela1[[#This Row],[CPF]],[1]Funcionário!$B:$B,[1]Funcionário!$H:$H) -> ATIVO | E17: CEF SP SUL | G17: LEANDRO NUNES | H17: EVERSON GAIDSTIECHI | J17: 3099.95 | K17: 5750 | L17: 62.3 | N17: =Tabela1[[#This Row],[1QZ DE ABRIL 26]]-Tabela1[[#This Row],[SALDO FINAL]]-Tabela1[[#This Row],[SALDO CARTAO]]-Tabela1[[#This Row],[ADIANTAMENTO]] -> 2587.75 | O17: 12084 | P17: =IF(Tabela1[[#This Row],[CARGA PARCIAL]]<0,0,Tabela1[[#This Row],[CARGA PARCIAL]])+Tabela1[[#This Row],[REEMBOLSO]] -> 14671.75 | Q17: Cartão ativo
B18: FLAVIO FERNANDES DOS REIS LIMA | C18: 01767960107 | D18: =_xlfn.XLOOKUP(Tabela1[[#This Row],[CPF]],[1]Funcionário!$B:$B,[1]Funcionário!$H:$H) -> ATIVO | E18: TELEFONICA CO | G18: ANGELICA SOARES | H18: ROGERIO SCATAMBULO | J18: 7169.96 | K18: 5700 | L18: 284.08 | N18: =Tabela1[[#This Row],[1QZ DE ABRIL 26]]-Tabela1[[#This Row],[SALDO FINAL]]-Tabela1[[#This Row],[SALDO CARTAO]]-Tabela1[[#This Row],[ADIANTAMENTO]] -> -1754.04 | O18: 0 | P18: =IF(Tabela1[[#This Row],[CARGA PARCIAL]]<0,0,Tabela1[[#This Row],[CARGA PARCIAL]])+Tabela1[[#This Row],[REEMBOLSO]] -> 0 | Q18: Cartão ativo
B19: WALTER DE CAMPOS NUNES NETO | C19: 99114160030 | D19: =_xlfn.XLOOKUP(Tabela1[[#This Row],[CPF]],[1]Funcionário!$B:$B,[1]Funcionário!$H:$H) -> ATIVO | E19: CLARO INFRA RS | G19: BRUNO EDUARDO | H19: EVERSON GAIDSTIECHI | I19: -324.54 | J19: 0 | K19: 5600 | L19: 317.49 | N19: =Tabela1[[#This Row],[1QZ DE ABRIL 26]]-Tabela1[[#This Row],[SALDO FINAL]]-Tabela1[[#This Row],[SALDO CARTAO]]-Tabela1[[#This Row],[ADIANTAMENTO]] -> 5282.51 | O19: 0 | P19: =IF(Tabela1[[#This Row],[CARGA PARCIAL]]<0,0,Tabela1[[#This Row],[CARGA PARCIAL]])+Tabela1[[#This Row],[REEMBOLSO]] -> 5282.51 | Q19: Cartão ativo
B20: ANTONIO FERREIRA DE MENDONCA NETO | C20: 05766838760 | D20: =_xlfn.XLOOKUP(Tabela1[[#This Row],[CPF]],[1]Funcionário!$B:$B,[1]Funcionário!$H:$H) -> ATIVO | E20: TRIBUNAL DE JUSTICA RJ | G20: ALLAN JEFFERSON | H20: ROGERIO SCATAMBULO | J20: 3904.24 | K20: 5000 | L20: 695.1 | N20: =Tabela1[[#This Row],[1QZ DE ABRIL 26]]-Tabela1[[#This Row],[SALDO FINAL]]-Tabela1[[#This Row],[SALDO CARTAO]]-Tabela1[[#This Row],[ADIANTAMENTO]] -> 400.66 | O20: 0 | P20: =IF(Tabela1[[#This Row],[CARGA PARCIAL]]<0,0,Tabela1[[#This Row],[CARGA PARCIAL]])+Tabela1[[#This Row],[REEMBOLSO]] -> 400.66 | Q20: Cartão ativo
B21: BRUNO FERREIRA DE SOUZA RODRIGUES | C21: 16306431730 | D21: =_xlfn.XLOOKUP(Tabela1[[#This Row],[CPF]],[1]Funcionário!$B:$B,[1]Funcionário!$H:$H) -> ATIVO | E21: TELEFONICA RJ | G21: ALLAN JEFFERSON | H21: ROGERIO SCATAMBULO | I21: -31.87 | J21: 0 | K21: 5000 | L21: 5 | N21: =Tabela1[[#This Row],[1QZ DE ABRIL 26]]-Tabela1[[#This Row],[SALDO FINAL]]-Tabela1[[#This Row],[SALDO CARTAO]]-Tabela1[[#This Row],[ADIANTAMENTO]] -> 4995 | O21: 0 | P21: =IF(Tabela1[[#This Row],[CARGA PARCIAL]]<0,0,Tabela1[[#This Row],[CARGA PARCIAL]])+Tabela1[[#This Row],[REEMBOLSO]] -> 4995 | Q21: Cartão ativo
B22: JOELSON FERREIRA DOS SANTOS | C22: 07690263623 | D22: =_xlfn.XLOOKUP(Tabela1[[#This Row],[CPF]],[1]Funcionário!$B:$B,[1]Funcionário!$H:$H) -> ATIVO | E22: CEF SUDESTE MG | G22: HUGO ALEXANDRE | H22: MARCOS CARIAS | J22: 5903.25 | K22: 5000 | L22: 57.18 | N22: =Tabela1[[#This Row],[1QZ DE ABRIL 26]]-Tabela1[[#This Row],[SALDO FINAL]]-Tabela1[[#This Row],[SALDO CARTAO]]-Tabela1[[#This Row],[ADIANTAMENTO]] -> -960.43 | O22: 0 | P22: =IF(Tabela1[[#This Row],[CARGA PARCIAL]]<0,0,Tabela1[[#This Row],[CARGA PARCIAL]])+Tabela1[[#This Row],[REEMBOLSO]] -> 0 | Q22: Cartão ativo
B23: MARCO AURELIO DE ANDRADE MORAES | C23: 72756284220 | D23: =_xlfn.XLOOKUP(Tabela1[[#This Row],[CPF]],[1]Funcionário!$B:$B,[1]Funcionário!$H:$H) -> ATIVO | E23: CEF AM AC RR | G23: ANGELICA SOARES | H23: ROGERIO SCATAMBULO | J23: 2658.66 | K23: 5000 | L23: 5 | N23: =Tabela1[[#This Row],[1QZ DE ABRIL 26]]-Tabela1[[#This Row],[SALDO FINAL]]-Tabela1[[#This Row],[SALDO CARTAO]]-Tabela1[[#This Row],[ADIANTAMENTO]] -> 2336.34 | O23: 0 | P23: =IF(Tabela1[[#This Row],[CARGA PARCIAL]]<0,0,Tabela1[[#This Row],[CARGA PARCIAL]])+Tabela1[[#This Row],[REEMBOLSO]] -> 2336.34 | Q23: Cartão ativo
B24: VICTOR SIGOLO PINHEIRO PIMENTA | C24: 12237490619 | D24: =_xlfn.XLOOKUP(Tabela1[[#This Row],[CPF]],[1]Funcionário!$B:$B,[1]Funcionário!$H:$H) -> ATIVO | E24: INSS SP | G24: LEANDRO NUNES | H24: EVERSON GAIDSTIECHI | J24: 3076.02 | K24: 5000 | L24: 20.13 | N24: =Tabela1[[#This Row],[1QZ DE ABRIL 26]]-Tabela1[[#This Row],[SALDO FINAL]]-Tabela1[[#This Row],[SALDO CARTAO]]-Tabela1[[#This Row],[ADIANTAMENTO]] -> 1903.85 | O24: 0 | P24: =IF(Tabela1[[#This Row],[CARGA PARCIAL]]<0,0,Tabela1[[#This Row],[CARGA PARCIAL]])+Tabela1[[#This Row],[REEMBOLSO]] -> 1903.85 | Q24: Cartão ativo
B25: SANDRO BARRETO DE SOUZA | C25: 78021324953 | D25: =_xlfn.XLOOKUP(Tabela1[[#This Row],[CPF]],[1]Funcionário!$B:$B,[1]Funcionário!$H:$H) -> ATIVO | E25: CEF SUL SC | G25: LEANDRO MARCUSSO | H25: EVERSON GAIDSTIECHI | J25: 1167.34 | K25: 4240 | L25: 9 | N25: =Tabela1[[#This Row],[1QZ DE ABRIL 26]]-Tabela1[[#This Row],[SALDO FINAL]]-Tabela1[[#This Row],[SALDO CARTAO]]-Tabela1[[#This Row],[ADIANTAMENTO]] -> 3063.66 | O25: 0 | P25: =IF(Tabela1[[#This Row],[CARGA PARCIAL]]<0,0,Tabela1[[#This Row],[CARGA PARCIAL]])+Tabela1[[#This Row],[REEMBOLSO]] -> 3063.66 | Q25: Cartão ativo
B26: CHARLES NEVES MATTIUZZI | C26: 12547938790 | D26: =_xlfn.XLOOKUP(Tabela1[[#This Row],[CPF]],[1]Funcionário!$B:$B,[1]Funcionário!$H:$H) -> ATIVO | E26: TELEFONICA ES | G26: VINICIUS LOCATELLY | H26: MARCOS CARIAS | J26: 3430.11 | K26: 4200 | L26: 19.73 | N26: =Tabela1[[#This Row],[1QZ DE ABRIL 26]]-Tabela1[[#This Row],[SALDO FINAL]]-Tabela1[[#This Row],[SALDO CARTAO]]-Tabela1[[#This Row],[ADIANTAMENTO]] -> 750.16 | O26: 0 | P26: =IF(Tabela1[[#This Row],[CARGA PARCIAL]]<0,0,Tabela1[[#This Row],[CARGA PARCIAL]])+Tabela1[[#This Row],[REEMBOLSO]] -> 750.16 | Q26: Cartão ativo
B27: CARLOS NASCIMENTO NONATO JUNIOR | C27: 65973500225 | D27: =_xlfn.XLOOKUP(Tabela1[[#This Row],[CPF]],[1]Funcionário!$B:$B,[1]Funcionário!$H:$H) -> ATIVO | E27: CEF AM AC RR | G27: ANGELICA SOARES | H27: ROGERIO SCATAMBULO | J27: 7077.32 | K27: 4000 | L27: 582.28 | N27: =Tabela1[[#This Row],[1QZ DE ABRIL 26]]-Tabela1[[#This Row],[SALDO FINAL]]-Tabela1[[#This Row],[SALDO CARTAO]]-Tabela1[[#This Row],[ADIANTAMENTO]] -> -3659.6 | O27: 0 | P27: =IF(Tabela1[[#This Row],[CARGA PARCIAL]]<0,0,Tabela1[[#This Row],[CARGA PARCIAL]])+Tabela1[[#This Row],[REEMBOLSO]] -> 0 | Q27: Cartão ativo
B28: EDUARDO ANDREY VENSON SILVA | C28: 02960685946 | D28: =_xlfn.XLOOKUP(Tabela1[[#This Row],[CPF]],[1]Funcionário!$B:$B,[1]Funcionário!$H:$H) -> ATIVO | E28: CEF OESTE SC | G28: LEANDRO MARCUSSO | H28: EVERSON GAIDSTIECHI | I28: -743.83 | J28: 0 | K28: 4000 | L28: 14.73 | N28: =Tabela1[[#This Row],[1QZ DE ABRIL 26]]-Tabela1[[#This Row],[SALDO FINAL]]-Tabela1[[#This Row],[SALDO CARTAO]]-Tabela1[[#This Row],[ADIANTAMENTO]] -> 3985.27 | O28: 0 | P28: =IF(Tabela1[[#This Row],[CARGA PARCIAL]]<0,0,Tabela1[[#This Row],[CARGA PARCIAL]])+Tabela1[[#This Row],[REEMBOLSO]] -> 3985.27 | Q28: Cartão ativo
B29: ENZIO CARVALHO DA MOTA | C29: 38548259515 | D29: =_xlfn.XLOOKUP(Tabela1[[#This Row],[CPF]],[1]Funcionário!$B:$B,[1]Funcionário!$H:$H) -> ATIVO | E29: TELEFONICA BA | G29: GERSON OLIVEIRA | H29: ROGERIO SCATAMBULO | J29: 2472.9 | K29: 4000 | L29: 16.21 | N29: =Tabela1[[#This Row],[1QZ DE ABRIL 26]]-Tabela1[[#This Row],[SALDO FINAL]]-Tabela1[[#This Row],[SALDO CARTAO]]-Tabela1[[#This Row],[ADIANTAMENTO]] -> 1510.89 | O29: 0 | P29: =IF(Tabela1[[#This Row],[CARGA PARCIAL]]<0,0,Tabela1[[#This Row],[CARGA PARCIAL]])+Tabela1[[#This Row],[REEMBOLSO]] -> 1510.89 | Q29: Cartão ativo
B30: FRANCIELLY FELIX CAVALCANTE DE ANDRADE | C30: 09276240446 | D30: =_xlfn.XLOOKUP(Tabela1[[#This Row],[CPF]],[1]Funcionário!$B:$B,[1]Funcionário!$H:$H) -> ATIVO | E30: CEF AM AC RR | G30: ANGELICA SOARES | H30: ROGERIO SCATAMBULO | J30: 798.78 | K30: 4000 | L30: 4002 | N30: =Tabela1[[#This Row],[1QZ DE ABRIL 26]]-Tabela1[[#This Row],[SALDO FINAL]]-Tabela1[[#This Row],[SALDO CARTAO]]-Tabela1[[#This Row],[ADIANTAMENTO]] -> -800.78 | O30: 0 | P30: =IF(Tabela1[[#This Row],[CARGA PARCIAL]]<0,0,Tabela1[[#This Row],[CARGA PARCIAL]])+Tabela1[[#This Row],[REEMBOLSO]] -> 0 | Q30: Cartão ativo
B31: LEANDRO FIGUEREDO BELCHIOR | C31: 26513583802 | D31: =_xlfn.XLOOKUP(Tabela1[[#This Row],[CPF]],[1]Funcionário!$B:$B,[1]Funcionário!$H:$H) -> ATIVO | E31: INSS SP | G31: LEANDRO NUNES | H31: EVERSON GAIDSTIECHI | J31: 2786.98 | K31: 4000 | L31: 1213.02 | N31: =Tabela1[[#This Row],[1QZ DE ABRIL 26]]-Tabela1[[#This Row],[SALDO FINAL]]-Tabela1[[#This Row],[SALDO CARTAO]]-Tabela1[[#This Row],[ADIANTAMENTO]] -> -1.8189894e-12 | O31: 0 | P31: =IF(Tabela1[[#This Row],[CARGA PARCIAL]]<0,0,Tabela1[[#This Row],[CARGA PARCIAL]])+Tabela1[[#This Row],[REEMBOLSO]] -> 0 | Q31: Cartão ativo
B32: LUCIANO JOSE DO AMARAL PEREIRA | C32: 04434355708 | D32: =_xlfn.XLOOKUP(Tabela1[[#This Row],[CPF]],[1]Funcionário!$B:$B,[1]Funcionário!$H:$H) -> ATIVO | E32: CEF CENTRO NORTE SUL RJ | G32: ALLAN JEFFERSON | H32: ROGERIO SCATAMBULO | J32: 3591.91 | K32: 4000 | L32: 49.52 | N32: =Tabela1[[#This Row],[1QZ DE ABRIL 26]]-Tabela1[[#This Row],[SALDO FINAL]]-Tabela1[[#This Row],[SALDO CARTAO]]-Tabela1[[#This Row],[ADIANTAMENTO]] -> 358.57 | O32: 0 | P32: =IF(Tabela1[[#This Row],[CARGA PARCIAL]]<0,0,Tabela1[[#This Row],[CARGA PARCIAL]])+Tabela1[[#This Row],[REEMBOLSO]] -> 358.57 | Q32: Cartão ativo
B33: ORESTE BARBOSA DA SILVA JUNIOR | C33: 25075562850 | D33: =_xlfn.XLOOKUP(Tabela1[[#This Row],[CPF]],[1]Funcionário!$B:$B,[1]Funcionário!$H:$H) -> ATIVO | E33: CEF PIRACICABA SP | G33: LEANDRO NUNES | H33: EVERSON GAIDSTIECHI | I33: -2304.48 | J33: 0 | K33: 4000 | L33: 2.15 | N33: =Tabela1[[#This Row],[1QZ DE ABRIL 26]]-Tabela1[[#This Row],[SALDO FINAL]]-Tabela1[[#This Row],[SALDO CARTAO]]-Tabela1[[#This Row],[ADIANTAMENTO]] -> 3997.85 | O33: 0 | P33: =IF(Tabela1[[#This Row],[CARGA PARCIAL]]<0,0,Tabela1[[#This Row],[CARGA PARCIAL]])+Tabela1[[#This Row],[REEMBOLSO]] -> 3997.85 | Q33: Cartão ativo
B34: RONALDO RUFINO SANTANA | C34: 29758827855 | D34: =_xlfn.XLOOKUP(Tabela1[[#This Row],[CPF]],[1]Funcionário!$B:$B,[1]Funcionário!$H:$H) -> ATIVO | E34: CEF PIRACICABA SP | G34: LEANDRO NUNES | H34: EVERSON GAIDSTIECHI | I34: -927.02 | J34: 0 | K34: 4000 | L34: 6.59 | N34: =Tabela1[[#This Row],[1QZ DE ABRIL 26]]-Tabela1[[#This Row],[SALDO FINAL]]-Tabela1[[#This Row],[SALDO CARTAO]]-Tabela1[[#This Row],[ADIANTAMENTO]] -> 3993.41 | O34: 0 | P34: =IF(Tabela1[[#This Row],[CARGA PARCIAL]]<0,0,Tabela1[[#This Row],[CARGA PARCIAL]])+Tabela1[[#This Row],[REEMBOLSO]] -> 3993.41 | Q34: Cartão ativo
B35: SANDRO CAPISTRANO | C35: 16996346886 | D35: =_xlfn.XLOOKUP(Tabela1[[#This Row],[CPF]],[1]Funcionário!$B:$B,[1]Funcionário!$H:$H) -> ATIVO | E35: CEF BAURU SP | G35: LEANDRO NUNES | H35: EVERSON GAIDSTIECHI | J35: 3452.98 | K35: 4000 | L35: 15.15 | N35: =Tabela1[[#This Row],[1QZ DE ABRIL 26]]-Tabela1[[#This Row],[SALDO FINAL]]-Tabela1[[#This Row],[SALDO CARTAO]]-Tabela1[[#This Row],[ADIANTAMENTO]] -> 531.87 | O35: 0 | P35: =IF(Tabela1[[#This Row],[CARGA PARCIAL]]<0,0,Tabela1[[#This Row],[CARGA PARCIAL]])+Tabela1[[#This Row],[REEMBOLSO]] -> 531.87 | Q35: Cartão ativo
B36: TERCILA DA SILVA LOPES | C36: 67752721387 | D36: =_xlfn.XLOOKUP(Tabela1[[#This Row],[CPF]],[1]Funcionário!$B:$B,[1]Funcionário!$H:$H) -> ATIVO | E36: CEF CEARA | G36: GERSON OLIVEIRA | H36: ROGERIO SCATAMBULO | J36: 4162.21 | K36: 4000 | L36: 1.42 | N36: =Tabela1[[#This Row],[1QZ DE ABRIL 26]]-Tabela1[[#This Row],[SALDO FINAL]]-Tabela1[[#This Row],[SALDO CARTAO]]-Tabela1[[#This Row],[ADIANTAMENTO]] -> -163.63 | O36: 0 | P36: =IF(Tabela1[[#This Row],[CARGA PARCIAL]]<0,0,Tabela1[[#This Row],[CARGA PARCIAL]])+Tabela1[[#This Row],[REEMBOLSO]] -> 0 | Q36: Cartão ativo
B37: UBIRAJARA DE ARAUJO TEIXEIRA | C37: 74548565949 | D37: =_xlfn.XLOOKUP(Tabela1[[#This Row],[CPF]],[1]Funcionário!$B:$B,[1]Funcionário!$H:$H) -> ATIVO | E37: BB APOIO PR | G37: LEANDRO MARCUSSO | H37: EVERSON GAIDSTIECHI | J37: 3920.17 | K37: 4000 | L37: 6.94 | N37: =Tabela1[[#This Row],[1QZ DE ABRIL 26]]-Tabela1[[#This Row],[SALDO FINAL]]-Tabela1[[#This Row],[SALDO CARTAO]]-Tabela1[[#This Row],[ADIANTAMENTO]] -> 72.89 | O37: 0 | P37: =IF(Tabela1[[#This Row],[CARGA PARCIAL]]<0,0,Tabela1[[#This Row],[CARGA PARCIAL]])+Tabela1[[#This Row],[REEMBOLSO]] -> 72.89 | Q37: Cartão ativo
B38: CAIO FRANCESCONI RIBEIRO | C38: 08924586904 | D38: =_xlfn.XLOOKUP(Tabela1[[#This Row],[CPF]],[1]Funcionário!$B:$B,[1]Funcionário!$H:$H) -> ATIVO | E38: TJ APOIO PR | G38: LEANDRO MARCUSSO | H38: EVERSON GAIDSTIECHI | J38: 6499.38 | K38: 3900 | L38: 4.82 | N38: =Tabela1[[#This Row],[1QZ DE ABRIL 26]]-Tabela1[[#This Row],[SALDO FINAL]]-Tabela1[[#This Row],[SALDO CARTAO]]-Tabela1[[#This Row],[ADIANTAMENTO]] -> -2604.2 | O38: 0 | P38: =IF(Tabela1[[#This Row],[CARGA PARCIAL]]<0,0,Tabela1[[#This Row],[CARGA PARCIAL]])+Tabela1[[#This Row],[REEMBOLSO]] -> 0 | Q38: Cartão ativo
B39: MICHAEL RODRIGUES SANTOS | C39: 37425574837 | D39: =_xlfn.XLOOKUP(Tabela1[[#This Row],[CPF]],[1]Funcionário!$B:$B,[1]Funcionário!$H:$H) -> ATIVO | E39: CEF SP SUL | G39: LEANDRO NUNES | H39: EVERSON GAIDSTIECHI | J39: 1798.56 | K39: 3350 | L39: 2 | N39: =Tabela1[[#This Row],[1QZ DE ABRIL 26]]-Tabela1[[#This Row],[SALDO FINAL]]-Tabela1[[#This Row],[SALDO CARTAO]]-Tabela1[[#This Row],[ADIANTAMENTO]] -> 1549.44 | O39: 0 | P39: =IF(Tabela1[[#This Row],[CARGA PARCIAL]]<0,0,Tabela1[[#This Row],[CARGA PARCIAL]])+Tabela1[[#This Row],[REEMBOLSO]] -> 1549.44 | Q39: Cartão ativo
B40: FERNANDO RODRIGUES DUARTE | C40: 03377983112 | D40: =_xlfn.XLOOKUP(Tabela1[[#This Row],[CPF]],[1]Funcionário!$B:$B,[1]Funcionário!$H:$H) -> ATIVO | E40: CLARO CO | G40: ANGELICA SOARES | H40: ROGERIO SCATAMBULO | J40: 553.39 | K40: 3200 | L40: 2 | N40: =Tabela1[[#This Row],[1QZ DE ABRIL 26]]-Tabela1[[#This Row],[SALDO FINAL]]-Tabela1[[#This Row],[SALDO CARTAO]]-Tabela1[[#This Row],[ADIANTAMENTO]] -> 2644.61 | O40: 0 | P40: =IF(Tabela1[[#This Row],[CARGA PARCIAL]]<0,0,Tabela1[[#This Row],[CARGA PARCIAL]])+Tabela1[[#This Row],[REEMBOLSO]] -> 2644.61 | Q40: Cartão ativo
B41: ALESSANDRO DE OLIVEIRA AZEVEDO | C41: 27494577858 | D41: =_xlfn.XLOOKUP(Tabela1[[#This Row],[CPF]],[1]Funcionário!$B:$B,[1]Funcionário!$H:$H) -> ATIVO | E41: CEF BAURU SP | G41: LEANDRO NUNES | H41: EVERSON GAIDSTIECHI | I41: -807.61 | J41: 0 | K41: 3000 | L41: 337.99 | N41: =Tabela1[[#This Row],[1QZ DE ABRIL 26]]-Tabela1[[#This Row],[SALDO FINAL]]-Tabela1[[#This Row],[SALDO CARTAO]]-Tabela1[[#This Row],[ADIANTAMENTO]] -> 2662.01 | O41: 0 | P41: =IF(Tabela1[[#This Row],[CARGA PARCIAL]]<0,0,Tabela1[[#This Row],[CARGA PARCIAL]])+Tabela1[[#This Row],[REEMBOLSO]] -> 2662.01 | Q41: Cartão ativo
B42: CLERITON BACILA DOS SANTOS | C42: 05456615959 | D42: =_xlfn.XLOOKUP(Tabela1[[#This Row],[CPF]],[1]Funcionário!$B:$B,[1]Funcionário!$H:$H) -> ATIVO | E42: NET CTA PR | G42: LEANDRO MARCUSSO | H42: EVERSON GAIDSTIECHI | J42: 4815.38 | K42: 3000 | L42: 1087.63 | N42: =Tabela1[[#This Row],[1QZ DE ABRIL 26]]-Tabela1[[#This Row],[SALDO FINAL]]-Tabela1[[#This Row],[SALDO CARTAO]]-Tabela1[[#This Row],[ADIANTAMENTO]] -> -2903.01 | O42: 0 | P42: =IF(Tabela1[[#This Row],[CARGA PARCIAL]]<0,0,Tabela1[[#This Row],[CARGA PARCIAL]])+Tabela1[[#This Row],[REEMBOLSO]] -> 0 | Q42: Cartão ativo
B43: EMERSON LEITE DE BARROS | C43: 34168918807 | D43: =_xlfn.XLOOKUP(Tabela1[[#This Row],[CPF]],[1]Funcionário!$B:$B,[1]Funcionário!$H:$H) -> ATIVO | E43: PTB INFRA SUDESTE | G43: LEANDRO NUNES | H43: EVERSON GAIDSTIECHI | I43: -2799.19 | J43: 0 | K43: 3000 | L43: 0 | N43: =Tabela1[[#This Row],[1QZ DE ABRIL 26]]-Tabela1[[#This Row],[SALDO FINAL]]-Tabela1[[#This Row],[SALDO CARTAO]]-Tabela1[[#This Row],[ADIANTAMENTO]] -> 3000 | O43: 2800 | P43: =IF(Tabela1[[#This Row],[CARGA PARCIAL]]<0,0,Tabela1[[#This Row],[CARGA PARCIAL]])+Tabela1[[#This Row],[REEMBOLSO]] -> 5800 | Q43: Cartão ativo
B44: JESSICA DE MIRANDA MEDEIROS FELICIANO | C44: 10137575483 | D44: =_xlfn.XLOOKUP(Tabela1[[#This Row],[CPF]],[1]Funcionário!$B:$B,[1]Funcionário!$H:$H) -> ATIVO | E44: CEF PIRACICABA SP | G44: LEANDRO NUNES | H44: EVERSON GAIDSTIECHI | I44: -4.35 | J44: 0 | K44: 3000 | L44: 6.58 | N44: =Tabela1[[#This Row],[1QZ DE ABRIL 26]]-Tabela1[[#This Row],[SALDO FINAL]]-Tabela1[[#This Row],[SALDO CARTAO]]-Tabela1[[#This Row],[ADIANTAMENTO]] -> 2993.42 | O44: 0 | P44: =IF(Tabela1[[#This Row],[CARGA PARCIAL]]<0,0,Tabela1[[#This Row],[CARGA PARCIAL]])+Tabela1[[#This Row],[REEMBOLSO]] -> 2993.42 | Q44: Cartão ativo
B45: PAULO NILTON COSTA MOREIRA | C45: 45159599053 | D45: =_xlfn.XLOOKUP(Tabela1[[#This Row],[CPF]],[1]Funcionário!$B:$B,[1]Funcionário!$H:$H) -> ATIVO | E45: CEF EXTREMO SUL RS | G45: ALEXANDRE GROSS | H45: EVERSON GAIDSTIECHI | J45: 994.14 | K45: 3000 | L45: 402 | N45: =Tabela1[[#This Row],[1QZ DE ABRIL 26]]-Tabela1[[#This Row],[SALDO FINAL]]-Tabela1[[#This Row],[SALDO CARTAO]]-Tabela1[[#This Row],[ADIANTAMENTO]] -> 1603.86 | O45: 0 | P45: =IF(Tabela1[[#This Row],[CARGA PARCIAL]]<0,0,Tabela1[[#This Row],[CARGA PARCIAL]])+Tabela1[[#This Row],[REEMBOLSO]] -> 1603.86 | Q45: Cartão ativo
B46: ANDRE LUIZ SANTANA | C46: 11897381638 | D46: =_xlfn.XLOOKUP(Tabela1[[#This Row],[CPF]],[1]Funcionário!$B:$B,[1]Funcionário!$H:$H) -> ATIVO | E46: CEF SERRA GAUCHA RS | G46: ALEXANDRE GROSS | H46: EVERSON GAIDSTIECHI | I46: -476.1 | J46: 0 | K46: 2800 | L46: 9 | N46: =Tabela1[[#This Row],[1QZ DE ABRIL 26]]-Tabela1[[#This Row],[SALDO FINAL]]-Tabela1[[#This Row],[SALDO CARTAO]]-Tabela1[[#This Row],[ADIANTAMENTO]] -> 2791 | O46: 0 | P46: =IF(Tabela1[[#This Row],[CARGA PARCIAL]]<0,0,Tabela1[[#This Row],[CARGA PARCIAL]])+Tabela1[[#This Row],[REEMBOLSO]] -> 2791 | Q46: Cartão ativo
B47: CARLOS RENATO PACHECO DA SILVA | C47: 90443306087 | D47: =_xlfn.XLOOKUP(Tabela1[[#This Row],[CPF]],[1]Funcionário!$B:$B,[1]Funcionário!$H:$H) -> ATIVO | E47: CEF LESTE GAUCHO RS | G47: ALEXANDRE GROSS | H47: EVERSON GAIDSTIECHI | J47: 3205.39 | K47: 2800 | L47: 8.77 | N47: =Tabela1[[#This Row],[1QZ DE ABRIL 26]]-Tabela1[[#This Row],[SALDO FINAL]]-Tabela1[[#This Row],[SALDO CARTAO]]-Tabela1[[#This Row],[ADIANTAMENTO]] -> -414.16 | O47: 0 | P47: =IF(Tabela1[[#This Row],[CARGA PARCIAL]]<0,0,Tabela1[[#This Row],[CARGA PARCIAL]])+Tabela1[[#This Row],[REEMBOLSO]] -> 0 | Q47: Cartão ativo
B48: EVERTON CAMARGO DE LOURETO | C48: 91688205004 | D48: =_xlfn.XLOOKUP(Tabela1[[#This Row],[CPF]],[1]Funcionário!$B:$B,[1]Funcionário!$H:$H) -> ATIVO | E48: CEF VALE SINOS RS | G48: ALEXANDRE GROSS | H48: EVERSON GAIDSTIECHI | J48: 1624.31 | K48: 2800 | L48: 12.44 | N48: =Tabela1[[#This Row],[1QZ DE ABRIL 26]]-Tabela1[[#This Row],[SALDO FINAL]]-Tabela1[[#This Row],[SALDO CARTAO]]-Tabela1[[#This Row],[ADIANTAMENTO]] -> 1163.25 | O48: 0 | P48: =IF(Tabela1[[#This Row],[CARGA PARCIAL]]<0,0,Tabela1[[#This Row],[CARGA PARCIAL]])+Tabela1[[#This Row],[REEMBOLSO]] -> 1163.25 | Q48: Cartão ativo
B49: FABIO DIOGO BITTENCOURT | C49: 00526143959 | D49: =_xlfn.XLOOKUP(Tabela1[[#This Row],[CPF]],[1]Funcionário!$B:$B,[1]Funcionário!$H:$H) -> ATIVO | E49: CEF CENTRO GAUCHO RS | G49: ALEXANDRE GROSS | H49: EVERSON GAIDSTIECHI | I49: -5689.28 | J49: 0 | K49: 2800 | L49: 9 | N49: =Tabela1[[#This Row],[1QZ DE ABRIL 26]]-Tabela1[[#This Row],[SALDO FINAL]]-Tabela1[[#This Row],[SALDO CARTAO]]-Tabela1[[#This Row],[ADIANTAMENTO]] -> 2791 | O49: 0 | P49: =IF(Tabela1[[#This Row],[CARGA PARCIAL]]<0,0,Tabela1[[#This Row],[CARGA PARCIAL]])+Tabela1[[#This Row],[REEMBOLSO]] -> 2791 | Q49: Cartão ativo
B50: JAFER DA FONTOURA AHMAD | C50: 00041171071 | D50: =_xlfn.XLOOKUP(Tabela1[[#This Row],[CPF]],[1]Funcionário!$B:$B,[1]Funcionário!$H:$H) -> ATIVO | E50: CEF PORTO ALEGRE RS | G50: ALEXANDRE GROSS | H50: EVERSON GAIDSTIECHI | J50: 1709.01 | K50: 2800 | L50: 6.86 | N50: =Tabela1[[#This Row],[1QZ DE ABRIL 26]]-Tabela1[[#This Row],[SALDO FINAL]]-Tabela1[[#This Row],[SALDO CARTAO]]-Tabela1[[#This Row],[ADIANTAMENTO]] -> 1084.13 | O50: 0 | P50: =IF(Tabela1[[#This Row],[CARGA PARCIAL]]<0,0,Tabela1[[#This Row],[CARGA PARCIAL]])+Tabela1[[#This Row],[REEMBOLSO]] -> 1084.13 | Q50: Cartão ativo
B51: RODRIGO VANZETTA | C51: 99532344004 | D51: =_xlfn.XLOOKUP(Tabela1[[#This Row],[CPF]],[1]Funcionário!$B:$B,[1]Funcionário!$H:$H) -> ATIVO | E51: CEF NORTE GAUCHO RS | G51: ALEXANDRE GROSS | H51: EVERSON GAIDSTIECHI | J51: 52.87 | K51: 2800 | L51: 9 | N51: =Tabela1[[#This Row],[1QZ DE ABRIL 26]]-Tabela1[[#This Row],[SALDO FINAL]]-Tabela1[[#This Row],[SALDO CARTAO]]-Tabela1[[#This Row],[ADIANTAMENTO]] -> 2738.13 | O51: 0 | P51: =IF(Tabela1[[#This Row],[CARGA PARCIAL]]<0,0,Tabela1[[#This Row],[CARGA PARCIAL]])+Tabela1[[#This Row],[REEMBOLSO]] -> 2738.13 | Q51: Cartão ativo
B52: DANIEL DA SILVA LOPES | C52: 94288259053 | D52: =_xlfn.XLOOKUP(Tabela1[[#This Row],[CPF]],[1]Funcionário!$B:$B,[1]Funcionário!$H:$H) -> ATIVO | E52: NET APOIO SC | G52: LEANDRO MARCUSSO | H52: EVERSON GAIDSTIECHI | J52: 396.45 | K52: 2710 | L52: 289.55 | N52: =Tabela1[[#This Row],[1QZ DE ABRIL 26]]-Tabela1[[#This Row],[SALDO FINAL]]-Tabela1[[#This Row],[SALDO CARTAO]]-Tabela1[[#This Row],[ADIANTAMENTO]] -> 2024 | O52: 0 | P52: =IF(Tabela1[[#This Row],[CARGA PARCIAL]]<0,0,Tabela1[[#This Row],[CARGA PARCIAL]])+Tabela1[[#This Row],[REEMBOLSO]] -> 2024 | Q52: Cartão ativo
B53: WESLLEY GABRIEL DA SILVA CARDOSO | C53: 87813416015 | D53: =_xlfn.XLOOKUP(Tabela1[[#This Row],[CPF]],[1]Funcionário!$B:$B,[1]Funcionário!$H:$H) -> ATIVO | E53: TELEFONICA RS | G53: ALEXANDRE GROSS | H53: EVERSON GAIDSTIECHI | J53: 1574.69 | K53: 2700 | L53: 8.81 | N53: =Tabela1[[#This Row],[1QZ DE ABRIL 26]]-Tabela1[[#This Row],[SALDO FINAL]]-Tabela1[[#This Row],[SALDO CARTAO]]-Tabela1[[#This Row],[ADIANTAMENTO]] -> 1116.5 | O53: 0 | P53: =IF(Tabela1[[#This Row],[CARGA PARCIAL]]<0,0,Tabela1[[#This Row],[CARGA PARCIAL]])+Tabela1[[#This Row],[REEMBOLSO]] -> 1116.5 | Q53: Cartão ativo
B54: CAIOS VINICIUS NUNES BROERING | C54: 07053418952 | D54: =_xlfn.XLOOKUP(Tabela1[[#This Row],[CPF]],[1]Funcionário!$B:$B,[1]Funcionário!$H:$H) -> ATIVO | E54: CLARO INFRA SC | G54: BRUNO EDUARDO | H54: EVERSON GAIDSTIECHI | I54: -31.3 | J54: 0 | K54: 2520 | L54: 350.6 | N54: =Tabela1[[#This Row],[1QZ DE ABRIL 26]]-Tabela1[[#This Row],[SALDO FINAL]]-Tabela1[[#This Row],[SALDO CARTAO]]-Tabela1[[#This Row],[ADIANTAMENTO]] -> 2169.4 | O54: 0 | P54: =IF(Tabela1[[#This Row],[CARGA PARCIAL]]<0,0,Tabela1[[#This Row],[CARGA PARCIAL]])+Tabela1[[#This Row],[REEMBOLSO]] -> 2169.4 | Q54: Cartão ativo
B55: DAVID DE OLIVEIRA FRIGERIO | C55: 04817177900 | D55: =_xlfn.XLOOKUP(Tabela1[[#This Row],[CPF]],[1]Funcionário!$B:$B,[1]Funcionário!$H:$H) -> ATIVO | E55: CEF NORTE PR | G55: LEANDRO MARCUSSO | H55: EVERSON GAIDSTIECHI | J55: 1047.4 | K55: 2500 | L55: 2.84 | N55: =Tabela1[[#This Row],[1QZ DE ABRIL 26]]-Tabela1[[#This Row],[SALDO FINAL]]-Tabela1[[#This Row],[SALDO CARTAO]]-Tabela1[[#This Row],[ADIANTAMENTO]] -> 1449.76 | O55: 0 | P55: =IF(Tabela1[[#This Row],[CARGA PARCIAL]]<0,0,Tabela1[[#This Row],[CARGA PARCIAL]])+Tabela1[[#This Row],[REEMBOLSO]] -> 1449.76 | Q55: Cartão ativo
B56: EDUARDO SANTOS | C56: 91270529072 | D56: =_xlfn.XLOOKUP(Tabela1[[#This Row],[CPF]],[1]Funcionário!$B:$B,[1]Funcionário!$H:$H) -> ATIVO | E56: NET APOIO RS | G56: ALEXANDRE GROSS | H56: EVERSON GAIDSTIECHI | I56: -689.71 | J56: 0 | K56: 2500 | L56: 487.17 | N56: =Tabela1[[#This Row],[1QZ DE ABRIL 26]]-Tabela1[[#This Row],[SALDO FINAL]]-Tabela1[[#This Row],[SALDO CARTAO]]-Tabela1[[#This Row],[ADIANTAMENTO]] -> 2012.83 | O56: 0 | P56: =IF(Tabela1[[#This Row],[CARGA PARCIAL]]<0,0,Tabela1[[#This Row],[CARGA PARCIAL]])+Tabela1[[#This Row],[REEMBOLSO]] -> 2012.83 | Q56: Cartão ativo
B57: FELIPE MORAES COSTA DE BRITTO | C57: 04347084102 | D57: =_xlfn.XLOOKUP(Tabela1[[#This Row],[CPF]],[1]Funcionário!$B:$B,[1]Funcionário!$H:$H) -> ATIVO | E57: INSS MT | G57: ANGELICA SOARES | H57: ROGERIO SCATAMBULO | J57: 3194.48 | K57: 2500 | L57: 316.81 | N57: =Tabela1[[#This Row],[1QZ DE ABRIL 26]]-Tabela1[[#This Row],[SALDO FINAL]]-Tabela1[[#This Row],[SALDO CARTAO]]-Tabela1[[#This Row],[ADIANTAMENTO]] -> -1011.29 | O57: 0 | P57: =IF(Tabela1[[#This Row],[CARGA PARCIAL]]<0,0,Tabela1[[#This Row],[CARGA PARCIAL]])+Tabela1[[#This Row],[REEMBOLSO]] -> 0 | Q57: Cartão ativo
B58: CARLOS EDUARDO SCATAMBULO | C58: 22730778829 | D58: =_xlfn.XLOOKUP(Tabela1[[#This Row],[CPF]],[1]Funcionário!$B:$B,[1]Funcionário!$H:$H) -> ATIVO | E58: CEF LESTE SP | G58: LEANDRO NUNES | H58: EVERSON GAIDSTIECHI | J58: 2565.96 | K58: 2300 | L58: 142.37 | N58: =Tabela1[[#This Row],[1QZ DE ABRIL 26]]-Tabela1[[#This Row],[SALDO FINAL]]-Tabela1[[#This Row],[SALDO CARTAO]]-Tabela1[[#This Row],[ADIANTAMENTO]] -> -408.33 | O58: 0 | P58: =IF(Tabela1[[#This Row],[CARGA PARCIAL]]<0,0,Tabela1[[#This Row],[CARGA PARCIAL]])+Tabela1[[#This Row],[REEMBOLSO]] -> 0 | Q58: Cartão ativo
B59: BEATRIZ SILVA DE SIQUEIRA | C59: 35575473880 | D59: =_xlfn.XLOOKUP(Tabela1[[#This Row],[CPF]],[1]Funcionário!$B:$B,[1]Funcionário!$H:$H) -> ATIVO | E59: CEF SP SUL | G59: LEANDRO NUNES | H59: EVERSON GAIDSTIECHI | J59: 1288.02 | K59: 2200 | L59: 6.9 | N59: =Tabela1[[#This Row],[1QZ DE ABRIL 26]]-Tabela1[[#This Row],[SALDO FINAL]]-Tabela1[[#This Row],[SALDO CARTAO]]-Tabela1[[#This Row],[ADIANTAMENTO]] -> 905.08 | O59: 0 | P59: =IF(Tabela1[[#This Row],[CARGA PARCIAL]]<0,0,Tabela1[[#This Row],[CARGA PARCIAL]])+Tabela1[[#This Row],[REEMBOLSO]] -> 905.08 | Q59: Cartão ativo
B60: ADSON SANTOS DA SILVA | C60: 83058133553 | D60: =_xlfn.XLOOKUP(Tabela1[[#This Row],[CPF]],[1]Funcionário!$B:$B,[1]Funcionário!$H:$H) -> ATIVO | E60: TELEFONICA BA | G60: GERSON OLIVEIRA | H60: ROGERIO SCATAMBULO | J60: 1328.12 | K60: 2000 | L60: 50.06 | N60: =Tabela1[[#This Row],[1QZ DE ABRIL 26]]-Tabela1[[#This Row],[SALDO FINAL]]-Tabela1[[#This Row],[SALDO CARTAO]]-Tabela1[[#This Row],[ADIANTAMENTO]] -> 621.82 | O60: 0 | P60: =IF(Tabela1[[#This Row],[CARGA PARCIAL]]<0,0,Tabela1[[#This Row],[CARGA PARCIAL]])+Tabela1[[#This Row],[REEMBOLSO]] -> 621.82 | Q60: Cartão ativo
B61: ARLEY HENRIQUE DE SOUZA LUZ | C61: 01170402232 | D61: =_xlfn.XLOOKUP(Tabela1[[#This Row],[CPF]],[1]Funcionário!$B:$B,[1]Funcionário!$H:$H) -> ATIVO | E61: CEF GOIANIA CO | G61: ANGELICA SOARES | H61: ROGERIO SCATAMBULO | J61: 1979.11 | K61: 2000 | L61: 6 | N61: =Tabela1[[#This Row],[1QZ DE ABRIL 26]]-Tabela1[[#This Row],[SALDO FINAL]]-Tabela1[[#This Row],[SALDO CARTAO]]-Tabela1[[#This Row],[ADIANTAMENTO]] -> 14.89 | O61: 0 | P61: =IF(Tabela1[[#This Row],[CARGA PARCIAL]]<0,0,Tabela1[[#This Row],[CARGA PARCIAL]])+Tabela1[[#This Row],[REEMBOLSO]] -> 14.89 | Q61: Cartão ativo
B62: DHIEGO RIBEIRO DINIZ | C62: 00049250256 | D62: =_xlfn.XLOOKUP(Tabela1[[#This Row],[CPF]],[1]Funcionário!$B:$B,[1]Funcionário!$H:$H) -> ATIVO | E62: CEF GOIANIA CO | G62: ANGELICA SOARES | H62: ROGERIO SCATAMBULO | J62: 1667.46 | K62: 2000 | L62: 9 | N62: =Tabela1[[#This Row],[1QZ DE ABRIL 26]]-Tabela1[[#This Row],[SALDO FINAL]]-Tabela1[[#This Row],[SALDO CARTAO]]-Tabela1[[#This Row],[ADIANTAMENTO]] -> 323.54 | O62: 0 | P62: =IF(Tabela1[[#This Row],[CARGA PARCIAL]]<0,0,Tabela1[[#This Row],[CARGA PARCIAL]])+Tabela1[[#This Row],[REEMBOLSO]] -> 323.54 | Q62: Cartão ativo
B63: EVERSON ESTEVES DOS SANTOS | C63: 01755089090 | D63: =_xlfn.XLOOKUP(Tabela1[[#This Row],[CPF]],[1]Funcionário!$B:$B,[1]Funcionário!$H:$H) -> ATIVO | E63: PTB REDUC RJ | G63: ALLAN JEFFERSON | H63: ROGERIO SCATAMBULO | J63: 4000 | K63: 2000 | L63: 0 | N63: =Tabela1[[#This Row],[1QZ DE ABRIL 26]]-Tabela1[[#This Row],[SALDO FINAL]]-Tabela1[[#This Row],[SALDO CARTAO]]-Tabela1[[#This Row],[ADIANTAMENTO]] -> -2000 | O63: 0 | P63: =IF(Tabela1[[#This Row],[CARGA PARCIAL]]<0,0,Tabela1[[#This Row],[CARGA PARCIAL]])+Tabela1[[#This Row],[REEMBOLSO]] -> 0 | Q63: Cartão ativo
B64: FABIO APARECIDO DE SOUSA PEREIRA | C64: 02679643909 | D64: =_xlfn.XLOOKUP(Tabela1[[#This Row],[CPF]],[1]Funcionário!$B:$B,[1]Funcionário!$H:$H) -> ATIVO | E64: NET APOIO PR | G64: LEANDRO MARCUSSO | H64: EVERSON GAIDSTIECHI | J64: 1419.31 | K64: 2000 | L64: 619.59 | N64: =Tabela1[[#This Row],[1QZ DE ABRIL 26]]-Tabela1[[#This Row],[SALDO FINAL]]-Tabela1[[#This Row],[SALDO CARTAO]]-Tabela1[[#This Row],[ADIANTAMENTO]] -> -38.9 | O64: 0 | P64: =IF(Tabela1[[#This Row],[CARGA PARCIAL]]<0,0,Tabela1[[#This Row],[CARGA PARCIAL]])+Tabela1[[#This Row],[REEMBOLSO]] -> 0 | Q64: Cartão ativo
B65: FELIPE JOSE DE ALBUQUERQUE OLIVEIRA | C65: 73574031491 | D65: =_xlfn.XLOOKUP(Tabela1[[#This Row],[CPF]],[1]Funcionário!$B:$B,[1]Funcionário!$H:$H) -> ATIVO | E65: CLARO INFRA NORDESTE | G65: FELIPE JOSE | H65: ROGERIO SCATAMBULO | J65: 1710.29 | K65: 2000 | L65: 11.42 | N65: =Tabela1[[#This Row],[1QZ DE ABRIL 26]]-Tabela1[[#This Row],[SALDO FINAL]]-Tabela1[[#This Row],[SALDO CARTAO]]-Tabela1[[#This Row],[ADIANTAMENTO]] -> 278.29 | O65: 0 | P65: =IF(Tabela1[[#This Row],[CARGA PARCIAL]]<0,0,Tabela1[[#This Row],[CARGA PARCIAL]])+Tabela1[[#This Row],[REEMBOLSO]] -> 278.29 | Q65: Cartão ativo
B66: FILIPE MENEZES KLING | C66: 10664298710 | D66: =_xlfn.XLOOKUP(Tabela1[[#This Row],[CPF]],[1]Funcionário!$B:$B,[1]Funcionário!$H:$H) -> ATIVO | E66: PTB CENPES RJ | G66: ALLAN JEFFERSON | H66: ROGERIO SCATAMBULO | I66: 0 | J66: 0 | K66: 2000 | L66: 0 | N66: =Tabela1[[#This Row],[1QZ DE ABRIL 26]]-Tabela1[[#This Row],[SALDO FINAL]]-Tabela1[[#This Row],[SALDO CARTAO]]-Tabela1[[#This Row],[ADIANTAMENTO]] -> 2000 | O66: 0 | P66: =IF(Tabela1[[#This Row],[CARGA PARCIAL]]<0,0,Tabela1[[#This Row],[CARGA PARCIAL]])+Tabela1[[#This Row],[REEMBOLSO]] -> 2000 | Q66: Cartão ativo
B67: GUILHERME FERREIRA DA SILVA | C67: 41997553813 | D67: =_xlfn.XLOOKUP(Tabela1[[#This Row],[CPF]],[1]Funcionário!$B:$B,[1]Funcionário!$H:$H) -> ATIVO | E67: CEF RECIFE PE | G67: GERSON OLIVEIRA | H67: ROGERIO SCATAMBULO | I67: -1231.89 | J67: 0 | K67: 2000 | L67: 36 | N67: =Tabela1[[#This Row],[1QZ DE ABRIL 26]]-Tabela1[[#This Row],[SALDO FINAL]]-Tabela1[[#This Row],[SALDO CARTAO]]-Tabela1[[#This Row],[ADIANTAMENTO]] -> 1964 | O67: 0 | P67: =IF(Tabela1[[#This Row],[CARGA PARCIAL]]<0,0,Tabela1[[#This Row],[CARGA PARCIAL]])+Tabela1[[#This Row],[REEMBOLSO]] -> 1964 | Q67: Cartão ativo
B68: GUILHERME MOTTA RIBEIRO SILVA | C68: 11178519740 | D68: =_xlfn.XLOOKUP(Tabela1[[#This Row],[CPF]],[1]Funcionário!$B:$B,[1]Funcionário!$H:$H) -> ATIVO | E68: CEF ES | G68: VINICIUS LOCATELLY | H68: MARCOS CARIAS | J68: 1609.12 | K68: 2000 | L68: 37.64 | N68: =Tabela1[[#This Row],[1QZ DE ABRIL 26]]-Tabela1[[#This Row],[SALDO FINAL]]-Tabela1[[#This Row],[SALDO CARTAO]]-Tabela1[[#This Row],[ADIANTAMENTO]] -> 353.24 | O68: 0 | P68: =IF(Tabela1[[#This Row],[CARGA PARCIAL]]<0,0,Tabela1[[#This Row],[CARGA PARCIAL]])+Tabela1[[#This Row],[REEMBOLSO]] -> 353.24 | Q68: Cartão ativo
B69: LEANDRO SOUSA | C69: 00584427905 | D69: =_xlfn.XLOOKUP(Tabela1[[#This Row],[CPF]],[1]Funcionário!$B:$B,[1]Funcionário!$H:$H) -> ATIVO | E69: PTB AREAS VERDES SC | G69: LEANDRO MARCUSSO | H69: EVERSON GAIDSTIECHI | J69: 337.08 | K69: 2000 | L69: 1800 | N69: =Tabela1[[#This Row],[1QZ DE ABRIL 26]]-Tabela1[[#This Row],[SALDO FINAL]]-Tabela1[[#This Row],[SALDO CARTAO]]-Tabela1[[#This Row],[ADIANTAMENTO]] -> -137.08 | O69: 0 | P69: =IF(Tabela1[[#This Row],[CARGA PARCIAL]]<0,0,Tabela1[[#This Row],[CARGA PARCIAL]])+Tabela1[[#This Row],[REEMBOLSO]] -> 0 | Q69: Cartão ativo
B70: MARCELO GIMENEZ ARGEMON | C70: 95073272153 | D70: =_xlfn.XLOOKUP(Tabela1[[#This Row],[CPF]],[1]Funcionário!$B:$B,[1]Funcionário!$H:$H) -> ATIVO | E70: CEF FACILITIES CAMPINAS SP | G70: LEANDRO NUNES | H70: EVERSON GAIDSTIECHI | I70: -1029 | J70: 0 | K70: 2000 | L70: 6 | N70: =Tabela1[[#This Row],[1QZ DE ABRIL 26]]-Tabela1[[#This Row],[SALDO FINAL]]-Tabela1[[#This Row],[SALDO CARTAO]]-Tabela1[[#This Row],[ADIANTAMENTO]] -> 1994 | O70: 0 | P70: =IF(Tabela1[[#This Row],[CARGA PARCIAL]]<0,0,Tabela1[[#This Row],[CARGA PARCIAL]])+Tabela1[[#This Row],[REEMBOLSO]] -> 1994 | Q70: Cartão ativo
B71: MARCO AURELIO DE LIMA | C71: 01356318665 | D71: =_xlfn.XLOOKUP(Tabela1[[#This Row],[CPF]],[1]Funcionário!$B:$B,[1]Funcionário!$H:$H) -> ATIVO | E71: TELEFONICA MG | G71: HUGO ALEXANDRE | H71: MARCOS CARIAS | I71: -15.12 | J71: 0 | K71: 2000 | L71: 12 | N71: =Tabela1[[#This Row],[1QZ DE ABRIL 26]]-Tabela1[[#This Row],[SALDO FINAL]]-Tabela1[[#This Row],[SALDO CARTAO]]-Tabela1[[#This Row],[ADIANTAMENTO]] -> 1988 | O71: 0 | P71: =IF(Tabela1[[#This Row],[CARGA PARCIAL]]<0,0,Tabela1[[#This Row],[CARGA PARCIAL]])+Tabela1[[#This Row],[REEMBOLSO]] -> 1988 | Q71: Cartão ativo
B72: MATHEUS FERNANDES GUIMARAES | C72: 17996820724 | D72: =_xlfn.XLOOKUP(Tabela1[[#This Row],[CPF]],[1]Funcionário!$B:$B,[1]Funcionário!$H:$H) -> ATIVO | E72: CEF NORTE PR | G72: LEANDRO MARCUSSO | H72: EVERSON GAIDSTIECHI | J72: 62.89 | K72: 2000 | L72: 6 | N72: =Tabela1[[#This Row],[1QZ DE ABRIL 26]]-Tabela1[[#This Row],[SALDO FINAL]]-Tabela1[[#This Row],[SALDO CARTAO]]-Tabela1[[#This Row],[ADIANTAMENTO]] -> 1931.11 | O72: 0 | P72: =IF(Tabela1[[#This Row],[CARGA PARCIAL]]<0,0,Tabela1[[#This Row],[CARGA PARCIAL]])+Tabela1[[#This Row],[REEMBOLSO]] -> 1931.11 | Q72: Cartão ativo
B73: RODRIGO SANTOS DA SILVA | C73: 05504962706 | D73: =_xlfn.XLOOKUP(Tabela1[[#This Row],[CPF]],[1]Funcionário!$B:$B,[1]Funcionário!$H:$H) -> ATIVO | E73: BANCO ITAU RJ | G73: ALLAN JEFFERSON | H73: ROGERIO SCATAMBULO | J73: 2359.71 | K73: 2000 | L73: 65.35 | N73: =Tabela1[[#This Row],[1QZ DE ABRIL 26]]-Tabela1[[#This Row],[SALDO FINAL]]-Tabela1[[#This Row],[SALDO CARTAO]]-Tabela1[[#This Row],[ADIANTAMENTO]] -> -425.06 | O73: 0 | P73: =IF(Tabela1[[#This Row],[CARGA PARCIAL]]<0,0,Tabela1[[#This Row],[CARGA PARCIAL]])+Tabela1[[#This Row],[REEMBOLSO]] -> 0 | Q73: Cartão ativo
B74: SHELDA CRISTINE LIMA TRINDADE | C74: 06015233265 | D74: =_xlfn.XLOOKUP(Tabela1[[#This Row],[CPF]],[1]Funcionário!$B:$B,[1]Funcionário!$H:$H) -> ATIVO | E74: GESTAO DE PESSOAS | G74: CAROLINE SILVA | H74: THIAGO NEVES | I74: 0 | J74: 2000 | K74: 2000 | L74: 0 | N74: =Tabela1[[#This Row],[1QZ DE ABRIL 26]]-Tabela1[[#This Row],[SALDO FINAL]]-Tabela1[[#This Row],[SALDO CARTAO]]-Tabela1[[#This Row],[ADIANTAMENTO]] -> 0 | O74: 0 | P74: =IF(Tabela1[[#This Row],[CARGA PARCIAL]]<0,0,Tabela1[[#This Row],[CARGA PARCIAL]])+Tabela1[[#This Row],[REEMBOLSO]] -> 0 | Q74: Cadastro pendente
B75: MARIA EDUARDA ARAGAO | C75: 10363402950 | D75: =_xlfn.XLOOKUP(Tabela1[[#This Row],[CPF]],[1]Funcionário!$B:$B,[1]Funcionário!$H:$H) -> ATIVO | E75: CEF SUL SC | G75: LEANDRO MARCUSSO | H75: EVERSON GAIDSTIECHI | I75: -2510.69 | J75: 0 | K75: 1840 | L75: 3 | N75: =Tabela1[[#This Row],[1QZ DE ABRIL 26]]-Tabela1[[#This Row],[SALDO FINAL]]-Tabela1[[#This Row],[SALDO CARTAO]]-Tabela1[[#This Row],[ADIANTAMENTO]] -> 1837 | O75: 0 | P75: =IF(Tabela1[[#This Row],[CARGA PARCIAL]]<0,0,Tabela1[[#This Row],[CARGA PARCIAL]])+Tabela1[[#This Row],[REEMBOLSO]] -> 1837 | Q75: Cartão ativo
B76: RICARDO MURCIA GARCIA FILHO | C76: 27668763830 | D76: =_xlfn.XLOOKUP(Tabela1[[#This Row],[CPF]],[1]Funcionário!$B:$B,[1]Funcionário!$H:$H) -> ATIVO | E76: CEF BAURU SP | G76: LEANDRO NUNES | H76: EVERSON GAIDSTIECHI | I76: -878.55 | J76: 0 | K76: 1800 | L76: 2.14 | N76: =Tabela1[[#This Row],[1QZ DE ABRIL 26]]-Tabela1[[#This Row],[SALDO FINAL]]-Tabela1[[#This Row],[SALDO CARTAO]]-Tabela1[[#This Row],[ADIANTAMENTO]] -> 1797.86 | O76: 0 | P76: =IF(Tabela1[[#This Row],[CARGA PARCIAL]]<0,0,Tabela1[[#This Row],[CARGA PARCIAL]])+Tabela1[[#This Row],[REEMBOLSO]] -> 1797.86 | Q76: Cartão ativo
B77: THIAGO PEREIRA DE LIMA | C77: 06478105490 | D77: =_xlfn.XLOOKUP(Tabela1[[#This Row],[CPF]],[1]Funcionário!$B:$B,[1]Funcionário!$H:$H) -> ATIVO | E77: CLARO INFRA NORDESTE | G77: FELIPE JOSE | H77: ROGERIO SCATAMBULO | J77: 2167.77 | K77: 1800 | L77: 27.46 | N77: =Tabela1[[#This Row],[1QZ DE ABRIL 26]]-Tabela1[[#This Row],[SALDO FINAL]]-Tabela1[[#This Row],[SALDO CARTAO]]-Tabela1[[#This Row],[ADIANTAMENTO]] -> -395.23 | O77: 0 | P77: =IF(Tabela1[[#This Row],[CARGA PARCIAL]]<0,0,Tabela1[[#This Row],[CARGA PARCIAL]])+Tabela1[[#This Row],[REEMBOLSO]] -> 0 | Q77: Cartão ativo
B78: JONAS CAVALCANTI DE OLIVEIRA | C78: 01696239478 | D78: =_xlfn.XLOOKUP(Tabela1[[#This Row],[CPF]],[1]Funcionário!$B:$B,[1]Funcionário!$H:$H) -> ATIVO | E78: 3R PETROLEUM NE | G78: GERSON OLIVEIRA | H78: ROGERIO SCATAMBULO | J78: 1110.83 | K78: 1750 | L78: 12 | N78: =Tabela1[[#This Row],[1QZ DE ABRIL 26]]-Tabela1[[#This Row],[SALDO FINAL]]-Tabela1[[#This Row],[SALDO CARTAO]]-Tabela1[[#This Row],[ADIANTAMENTO]] -> 627.17 | O78: 0 | P78: =IF(Tabela1[[#This Row],[CARGA PARCIAL]]<0,0,Tabela1[[#This Row],[CARGA PARCIAL]])+Tabela1[[#This Row],[REEMBOLSO]] -> 627.17 | Q78: Cartão ativo
B79: JAIME ALVES DE ABREU SILVA | C79: 00965306186 | D79: =_xlfn.XLOOKUP(Tabela1[[#This Row],[CPF]],[1]Funcionário!$B:$B,[1]Funcionário!$H:$H) -> ATIVO | E79: CLARO CO | G79: ANGELICA SOARES | H79: ROGERIO SCATAMBULO | J79: 2081.47 | K79: 1700 | L79: 27.99 | N79: =Tabela1[[#This Row],[1QZ DE ABRIL 26]]-Tabela1[[#This Row],[SALDO FINAL]]-Tabela1[[#This Row],[SALDO CARTAO]]-Tabela1[[#This Row],[ADIANTAMENTO]] -> -409.46 | O79: 0 | P79: =IF(Tabela1[[#This Row],[CARGA PARCIAL]]<0,0,Tabela1[[#This Row],[CARGA PARCIAL]])+Tabela1[[#This Row],[REEMBOLSO]] -> 0 | Q79: Cartão ativo
B80: ADMILSON DOS SANTOS GALAN | C80: 04769973993 | D80: =_xlfn.XLOOKUP(Tabela1[[#This Row],[CPF]],[1]Funcionário!$B:$B,[1]Funcionário!$H:$H) -> ATIVO | E80: CEF NORTE SC | G80: LEANDRO MARCUSSO | H80: EVERSON GAIDSTIECHI | J80: 581.84 | K80: 1680 | L80: 0.53 | N80: =Tabela1[[#This Row],[1QZ DE ABRIL 26]]-Tabela1[[#This Row],[SALDO FINAL]]-Tabela1[[#This Row],[SALDO CARTAO]]-Tabela1[[#This Row],[ADIANTAMENTO]] -> 1097.63 | O80: 0 | P80: =IF(Tabela1[[#This Row],[CARGA PARCIAL]]<0,0,Tabela1[[#This Row],[CARGA PARCIAL]])+Tabela1[[#This Row],[REEMBOLSO]] -> 1097.63 | Q80: Cartão ativo
B81: ADSON ARAUJO DA SILVA | C81: 94551804304 | D81: =_xlfn.XLOOKUP(Tabela1[[#This Row],[CPF]],[1]Funcionário!$B:$B,[1]Funcionário!$H:$H) -> ATIVO | E81: CLARO INFRA NORDESTE | G81: FELIPE JOSE | H81: ROGERIO SCATAMBULO | J81: 246.24 | K81: 1600 | L81: 6 | N81: =Tabela1[[#This Row],[1QZ DE ABRIL 26]]-Tabela1[[#This Row],[SALDO FINAL]]-Tabela1[[#This Row],[SALDO CARTAO]]-Tabela1[[#This Row],[ADIANTAMENTO]] -> 1347.76 | O81: 0 | P81: =IF(Tabela1[[#This Row],[CARGA PARCIAL]]<0,0,Tabela1[[#This Row],[CARGA PARCIAL]])+Tabela1[[#This Row],[REEMBOLSO]] -> 1347.76 | Q81: Cartão ativo
B82: DEISE SOARES DE CAMPOS | C82: 69116709004 | D82: =_xlfn.XLOOKUP(Tabela1[[#This Row],[CPF]],[1]Funcionário!$B:$B,[1]Funcionário!$H:$H) -> ATIVO | E82: CEF NORTE SC | G82: LEANDRO MARCUSSO | H82: EVERSON GAIDSTIECHI | I82: -3445.04 | J82: 0 | K82: 1600 | L82: 5038.04 | N82: =Tabela1[[#This Row],[1QZ DE ABRIL 26]]-Tabela1[[#This Row],[SALDO FINAL]]-Tabela1[[#This Row],[SALDO CARTAO]]-Tabela1[[#This Row],[ADIANTAMENTO]] -> -3438.04 | O82: 0 | P82: =IF(Tabela1[[#This Row],[CARGA PARCIAL]]<0,0,Tabela1[[#This Row],[CARGA PARCIAL]])+Tabela1[[#This Row],[REEMBOLSO]] -> 0 | Q82: Cartão ativo
B83: EDIPO SANTOS BARRETO | C83: 37896893860 | D83: =_xlfn.XLOOKUP(Tabela1[[#This Row],[CPF]],[1]Funcionário!$B:$B,[1]Funcionário!$H:$H) -> ATIVO | E83: TRIBUNAL DE JUSTICA SP | G83: LEANDRO NUNES | H83: EVERSON GAIDSTIECHI | J83: 338.64 | K83: 1600 | L83: 599.04 | N83: =Tabela1[[#This Row],[1QZ DE ABRIL 26]]-Tabela1[[#This Row],[SALDO FINAL]]-Tabela1[[#This Row],[SALDO CARTAO]]-Tabela1[[#This Row],[ADIANTAMENTO]] -> 662.32 | O83: 0 | P83: =IF(Tabela1[[#This Row],[CARGA PARCIAL]]<0,0,Tabela1[[#This Row],[CARGA PARCIAL]])+Tabela1[[#This Row],[REEMBOLSO]] -> 662.32 | Q83: Cartão ativo
B84: DANIEL SANTOS DE ASSUNCAO | C84: 97592439549 | D84: =_xlfn.XLOOKUP(Tabela1[[#This Row],[CPF]],[1]Funcionário!$B:$B,[1]Funcionário!$H:$H) -> ATIVO | E84: BANCO ITAU BA | G84: GERSON OLIVEIRA | H84: ROGERIO SCATAMBULO | I84: -28.99 | J84: 0 | K84: 1500 | L84: 16 | N84: =Tabela1[[#This Row],[1QZ DE ABRIL 26]]-Tabela1[[#This Row],[SALDO FINAL]]-Tabela1[[#This Row],[SALDO CARTAO]]-Tabela1[[#This Row],[ADIANTAMENTO]] -> 1484 | O84: 0 | P84: =IF(Tabela1[[#This Row],[CARGA PARCIAL]]<0,0,Tabela1[[#This Row],[CARGA PARCIAL]])+Tabela1[[#This Row],[REEMBOLSO]] -> 1484 | Q84: Cartão ativo
B85: EDER AUGUSTO DE ARAUJO CARVALHO | C85: 03985382638 | D85: =_xlfn.XLOOKUP(Tabela1[[#This Row],[CPF]],[1]Funcionário!$B:$B,[1]Funcionário!$H:$H) -> ATIVO | E85: CLARO INFRA MG | G85: HUGO ALEXANDRE | H85: MARCOS CARIAS | J85: 883.21 | K85: 1500 | L85: 29 | N85: =Tabela1[[#This Row],[1QZ DE ABRIL 26]]-Tabela1[[#This Row],[SALDO FINAL]]-Tabela1[[#This Row],[SALDO CARTAO]]-Tabela1[[#This Row],[ADIANTAMENTO]] -> 587.79 | O85: 0 | P85: =IF(Tabela1[[#This Row],[CARGA PARCIAL]]<0,0,Tabela1[[#This Row],[CARGA PARCIAL]])+Tabela1[[#This Row],[REEMBOLSO]] -> 587.79 | Q85: Cartão ativo
B86: ERICSON PINHEIRO DOS SANTOS | C86: 29157549850 | D86: =_xlfn.XLOOKUP(Tabela1[[#This Row],[CPF]],[1]Funcionário!$B:$B,[1]Funcionário!$H:$H) -> ATIVO | E86: CEF FACILITIES SP | G86: LEANDRO NUNES | H86: EVERSON GAIDSTIECHI | J86: 814.91 | K86: 1500 | L86: 814.49 | N86: =Tabela1[[#This Row],[1QZ DE ABRIL 26]]-Tabela1[[#This Row],[SALDO FINAL]]-Tabela1[[#This Row],[SALDO CARTAO]]-Tabela1[[#This Row],[ADIANTAMENTO]] -> -129.4 | O86: 0 | P86: =IF(Tabela1[[#This Row],[CARGA PARCIAL]]<0,0,Tabela1[[#This Row],[CARGA PARCIAL]])+Tabela1[[#This Row],[REEMBOLSO]] -> 0 | Q86: Cartão ativo
B87: FABIO DA CONCEICAO LIMA | C87: 31275798888 | D87: =_xlfn.XLOOKUP(Tabela1[[#This Row],[CPF]],[1]Funcionário!$B:$B,[1]Funcionário!$H:$H) -> ATIVO | E87: PTB UTGCA SP | G87: LEANDRO NUNES | H87: EVERSON GAIDSTIECHI | J87: 5604.9 | K87: 1500 | L87: 7.97 | N87: =Tabela1[[#This Row],[1QZ DE ABRIL 26]]-Tabela1[[#This Row],[SALDO FINAL]]-Tabela1[[#This Row],[SALDO CARTAO]]-Tabela1[[#This Row],[ADIANTAMENTO]] -> -4112.87 | O87: 0 | P87: =IF(Tabela1[[#This Row],[CARGA PARCIAL]]<0,0,Tabela1[[#This Row],[CARGA PARCIAL]])+Tabela1[[#This Row],[REEMBOLSO]] -> 0 | Q87: Cartão ativo
B88: FABIO PROVESI | C88: 05731312958 | D88: =_xlfn.XLOOKUP(Tabela1[[#This Row],[CPF]],[1]Funcionário!$B:$B,[1]Funcionário!$H:$H) -> ATIVO | E88: BB SERET SC | G88: LEANDRO MARCUSSO | H88: EVERSON GAIDSTIECHI | J88: 1118.62 | K88: 1500 | L88: 64.48 | N88: =Tabela1[[#This Row],[1QZ DE ABRIL 26]]-Tabela1[[#This Row],[SALDO FINAL]]-Tabela1[[#This Row],[SALDO CARTAO]]-Tabela1[[#This Row],[ADIANTAMENTO]] -> 316.9 | O88: 0 | P88: =IF(Tabela1[[#This Row],[CARGA PARCIAL]]<0,0,Tabela1[[#This Row],[CARGA PARCIAL]])+Tabela1[[#This Row],[REEMBOLSO]] -> 316.9 | Q88: Cartão ativo
B89: ICARO MEDEIROS SILVA | C89: 01565661338 | D89: =_xlfn.XLOOKUP(Tabela1[[#This Row],[CPF]],[1]Funcionário!$B:$B,[1]Funcionário!$H:$H) -> ATIVO | E89: CLARO INFRA NORDESTE | G89: FELIPE JOSE | H89: ROGERIO SCATAMBULO | J89: 5351.83 | K89: 1500 | L89: 10 | N89: =Tabela1[[#This Row],[1QZ DE ABRIL 26]]-Tabela1[[#This Row],[SALDO FINAL]]-Tabela1[[#This Row],[SALDO CARTAO]]-Tabela1[[#This Row],[ADIANTAMENTO]] -> -3861.83 | O89: 0 | P89: =IF(Tabela1[[#This Row],[CARGA PARCIAL]]<0,0,Tabela1[[#This Row],[CARGA PARCIAL]])+Tabela1[[#This Row],[REEMBOLSO]] -> 0 | Q89: Cartão ativo
B90: JORGE NEGRI NETO | C90: 44997574600 | D90: =_xlfn.XLOOKUP(Tabela1[[#This Row],[CPF]],[1]Funcionário!$B:$B,[1]Funcionário!$H:$H) -> ATIVO | E90: PTB TIC NORDESTE | G90: GERSON OLIVEIRA | H90: ROGERIO SCATAMBULO | I90: -199.16 | J90: 0 | K90: 1500 | L90: 1.22 | N90: =Tabela1[[#This Row],[1QZ DE ABRIL 26]]-Tabela1[[#This Row],[SALDO FINAL]]-Tabela1[[#This Row],[SALDO CARTAO]]-Tabela1[[#This Row],[ADIANTAMENTO]] -> 1498.78 | O90: 0 | P90: =IF(Tabela1[[#This Row],[CARGA PARCIAL]]<0,0,Tabela1[[#This Row],[CARGA PARCIAL]])+Tabela1[[#This Row],[REEMBOLSO]] -> 1498.78 | Q90: Cartão ativo
B91: JOSE EUSTAQUIO DE SOUZA | C91: 27335364191 | D91: =_xlfn.XLOOKUP(Tabela1[[#This Row],[CPF]],[1]Funcionário!$B:$B,[1]Funcionário!$H:$H) -> ATIVO | E91: CLARO CO | G91: ANGELICA SOARES | H91: ROGERIO SCATAMBULO | I91: -493.72 | J91: 0 | K91: 1500 | L91: 4.62 | N91: =Tabela1[[#This Row],[1QZ DE ABRIL 26]]-Tabela1[[#This Row],[SALDO FINAL]]-Tabela1[[#This Row],[SALDO CARTAO]]-Tabela1[[#This Row],[ADIANTAMENTO]] -> 1495.38 | O91: 0 | P91: =IF(Tabela1[[#This Row],[CARGA PARCIAL]]<0,0,Tabela1[[#This Row],[CARGA PARCIAL]])+Tabela1[[#This Row],[REEMBOLSO]] -> 1495.38 | Q91: Cartão ativo
B92: LARISSA SANTOS DA SILVA | C92: 45120065830 | D92: =_xlfn.XLOOKUP(Tabela1[[#This Row],[CPF]],[1]Funcionário!$B:$B,[1]Funcionário!$H:$H) -> ATIVO | E92: BANCO ITAU SP | G92: LEANDRO NUNES | H92: EVERSON GAIDSTIECHI | J92: 2470.86 | K92: 1500 | L92: 0.22 | N92: =Tabela1[[#This Row],[1QZ DE ABRIL 26]]-Tabela1[[#This Row],[SALDO FINAL]]-Tabela1[[#This Row],[SALDO CARTAO]]-Tabela1[[#This Row],[ADIANTAMENTO]] -> -971.08 | O92: 0 | P92: =IF(Tabela1[[#This Row],[CARGA PARCIAL]]<0,0,Tabela1[[#This Row],[CARGA PARCIAL]])+Tabela1[[#This Row],[REEMBOLSO]] -> 0 | Q92: Cartão ativo
B93: LUCAS PEREIRA GONCALVES | C93: 11128978601 | D93: =_xlfn.XLOOKUP(Tabela1[[#This Row],[CPF]],[1]Funcionário!$B:$B,[1]Funcionário!$H:$H) -> ATIVO | E93: NET LESTE MG | G93: HUGO ALEXANDRE | H93: MARCOS CARIAS | J93: 1705.37 | K93: 1500 | L93: 0 | N93: =Tabela1[[#This Row],[1QZ DE ABRIL 26]]-Tabela1[[#This Row],[SALDO FINAL]]-Tabela1[[#This Row],[SALDO CARTAO]]-Tabela1[[#This Row],[ADIANTAMENTO]] -> -205.37 | O93: 0 | P93: =IF(Tabela1[[#This Row],[CARGA PARCIAL]]<0,0,Tabela1[[#This Row],[CARGA PARCIAL]])+Tabela1[[#This Row],[REEMBOLSO]] -> 0 | Q93: Cartão ativo
B94: MARCEL DA HORA CARVALHO | C94: 01730674500 | D94: =_xlfn.XLOOKUP(Tabela1[[#This Row],[CPF]],[1]Funcionário!$B:$B,[1]Funcionário!$H:$H) -> ATIVO | E94: POLICIA FEDERAL BA | G94: GERSON OLIVEIRA | H94: ROGERIO SCATAMBULO | I94: -1695.39 | J94: 0 | K94: 1500 | L94: 2.6 | N94: =Tabela1[[#This Row],[1QZ DE ABRIL 26]]-Tabela1[[#This Row],[SALDO FINAL]]-Tabela1[[#This Row],[SALDO CARTAO]]-Tabela1[[#This Row],[ADIANTAMENTO]] -> 1497.4 | O94: 0 | P94: =IF(Tabela1[[#This Row],[CARGA PARCIAL]]<0,0,Tabela1[[#This Row],[CARGA PARCIAL]])+Tabela1[[#This Row],[REEMBOLSO]] -> 1497.4 | Q94: Cartão ativo
B95: MILTON FERREIRA DAS NEVES JUNIOR | C95: 05100355581 | D95: =_xlfn.XLOOKUP(Tabela1[[#This Row],[CPF]],[1]Funcionário!$B:$B,[1]Funcionário!$H:$H) -> ATIVO | E95: ACELEN AR | G95: GERSON OLIVEIRA | H95: ROGERIO SCATAMBULO | J95: 2971.16 | K95: 1500 | L95: 3 | N95: =Tabela1[[#This Row],[1QZ DE ABRIL 26]]-Tabela1[[#This Row],[SALDO FINAL]]-Tabela1[[#This Row],[SALDO CARTAO]]-Tabela1[[#This Row],[ADIANTAMENTO]] -> -1474.16 | O95: 0 | P95: =IF(Tabela1[[#This Row],[CARGA PARCIAL]]<0,0,Tabela1[[#This Row],[CARGA PARCIAL]])+Tabela1[[#This Row],[REEMBOLSO]] -> 0 | Q95: Cartão ativo
B96: RAMON GOMES TEIXEIRA | C96: 83978054515 | D96: =_xlfn.XLOOKUP(Tabela1[[#This Row],[CPF]],[1]Funcionário!$B:$B,[1]Funcionário!$H:$H) -> ATIVO | E96: BB EDIFICIOS SP | G96: LEANDRO NUNES | H96: EVERSON GAIDSTIECHI | J96: 870.01 | K96: 1500 | L96: 10.26 | N96: =Tabela1[[#This Row],[1QZ DE ABRIL 26]]-Tabela1[[#This Row],[SALDO FINAL]]-Tabela1[[#This Row],[SALDO CARTAO]]-Tabela1[[#This Row],[ADIANTAMENTO]] -> 619.73 | O96: 0 | P96: =IF(Tabela1[[#This Row],[CARGA PARCIAL]]<0,0,Tabela1[[#This Row],[CARGA PARCIAL]])+Tabela1[[#This Row],[REEMBOLSO]] -> 619.73 | Q96: Cartão ativo
B97: RODRIGO ROBERTO DE SOUZA | C97: 05664820969 | D97: =_xlfn.XLOOKUP(Tabela1[[#This Row],[CPF]],[1]Funcionário!$B:$B,[1]Funcionário!$H:$H) -> ATIVO | E97: BB GRANDE FLORIANOPOLIS SC | G97: LEANDRO MARCUSSO | H97: EVERSON GAIDSTIECHI | J97: 239 | K97: 1500 | L97: 68.88 | N97: =Tabela1[[#This Row],[1QZ DE ABRIL 26]]-Tabela1[[#This Row],[SALDO FINAL]]-Tabela1[[#This Row],[SALDO CARTAO]]-Tabela1[[#This Row],[ADIANTAMENTO]] -> 1192.12 | O97: 0 | P97: =IF(Tabela1[[#This Row],[CARGA PARCIAL]]<0,0,Tabela1[[#This Row],[CARGA PARCIAL]])+Tabela1[[#This Row],[REEMBOLSO]] -> 1192.12 | Q97: Cartão ativo
B98: SARA ARAGAO DA SILVA BARBOSA | C98: 49637513809 | D98: =_xlfn.XLOOKUP(Tabela1[[#This Row],[CPF]],[1]Funcionário!$B:$B,[1]Funcionário!$H:$H) -> ATIVO | E98: BANCO ITAU SP | G98: LEANDRO NUNES | H98: EVERSON GAIDSTIECHI | J98: 1823.76 | K98: 1500 | L98: 9 | N98: =Tabela1[[#This Row],[1QZ DE ABRIL 26]]-Tabela1[[#This Row],[SALDO FINAL]]-Tabela1[[#This Row],[SALDO CARTAO]]-Tabela1[[#This Row],[ADIANTAMENTO]] -> -332.76 | O98: 0 | P98: =IF(Tabela1[[#This Row],[CARGA PARCIAL]]<0,0,Tabela1[[#This Row],[CARGA PARCIAL]])+Tabela1[[#This Row],[REEMBOLSO]] -> 0 | Q98: Cartão ativo
B99: SILMARA CHAVES | C99: 02706762950 | D99: =_xlfn.XLOOKUP(Tabela1[[#This Row],[CPF]],[1]Funcionário!$B:$B,[1]Funcionário!$H:$H) -> ATIVO | E99: BB TIRADENTES PR | G99: LEANDRO MARCUSSO | H99: EVERSON GAIDSTIECHI | I99: -15.89 | J99: 0 | K99: 1500 | L99: 8.06 | N99: =Tabela1[[#This Row],[1QZ DE ABRIL 26]]-Tabela1[[#This Row],[SALDO FINAL]]-Tabela1[[#This Row],[SALDO CARTAO]]-Tabela1[[#This Row],[ADIANTAMENTO]] -> 1491.94 | O99: 0 | P99: =IF(Tabela1[[#This Row],[CARGA PARCIAL]]<0,0,Tabela1[[#This Row],[CARGA PARCIAL]])+Tabela1[[#This Row],[REEMBOLSO]] -> 1491.94 | Q99: Cartão ativo
B100: THIAGO LEANDRO DOS SANTOS | C100: 33927651800 | D100: =_xlfn.XLOOKUP(Tabela1[[#This Row],[CPF]],[1]Funcionário!$B:$B,[1]Funcionário!$H:$H) -> ATIVO | E100: PROSEGUR SP | G100: LEANDRO NUNES | H100: EVERSON GAIDSTIECHI | J100: 6076.59 | K100: 1500 | L100: 14.33 | N100: =Tabela1[[#This Row],[1QZ DE ABRIL 26]]-Tabela1[[#This Row],[SALDO FINAL]]-Tabela1[[#This Row],[SALDO CARTAO]]-Tabela1[[#This Row],[ADIANTAMENTO]] -> -4590.92 | O100: 0 | P100: =IF(Tabela1[[#This Row],[CARGA PARCIAL]]<0,0,Tabela1[[#This Row],[CARGA PARCIAL]])+Tabela1[[#This Row],[REEMBOLSO]] -> 0 | Q100: Cartão ativo
B101: THIEGO LEANDRO ALVES DE OLIVEIRA | C101: 07198282440 | D101: =_xlfn.XLOOKUP(Tabela1[[#This Row],[CPF]],[1]Funcionário!$B:$B,[1]Funcionário!$H:$H) -> ATIVO | E101: CEF RECIFE PE | G101: GERSON OLIVEIRA | H101: ROGERIO SCATAMBULO | J101: 1011 | K101: 1500 | L101: 44.76 | N101: =Tabela1[[#This Row],[1QZ DE ABRIL 26]]-Tabela1[[#This Row],[SALDO FINAL]]-Tabela1[[#This Row],[SALDO CARTAO]]-Tabela1[[#This Row],[ADIANTAMENTO]] -> 444.24 | O101: 0 | P101: =IF(Tabela1[[#This Row],[CARGA PARCIAL]]<0,0,Tabela1[[#This Row],[CARGA PARCIAL]])+Tabela1[[#This Row],[REEMBOLSO]] -> 444.24 | Q101: Cartão ativo
B102: WELERSON PUFF RODRIGUES | C102: 04352219657 | D102: =_xlfn.XLOOKUP(Tabela1[[#This Row],[CPF]],[1]Funcionário!$B:$B,[1]Funcionário!$H:$H) -> ATIVO | E102: PROSEGUR MG | G102: HUGO ALEXANDRE | H102: MARCOS CARIAS | I102: -1019.95 | J102: 0 | K102: 1500 | L102: 6 | N102: =Tabela1[[#This Row],[1QZ DE ABRIL 26]]-Tabela1[[#This Row],[SALDO FINAL]]-Tabela1[[#This Row],[SALDO CARTAO]]-Tabela1[[#This Row],[ADIANTAMENTO]] -> 1494 | O102: 0 | P102: =IF(Tabela1[[#This Row],[CARGA PARCIAL]]<0,0,Tabela1[[#This Row],[CARGA PARCIAL]])+Tabela1[[#This Row],[REEMBOLSO]] -> 1494 | Q102: Cartão ativo
B103: GIOVANNA SIDOTI MARQUES ROLLO | C103: 42391813805 | D103: =_xlfn.XLOOKUP(Tabela1[[#This Row],[CPF]],[1]Funcionário!$B:$B,[1]Funcionário!$H:$H) -> ATIVO | E103: TELEFONICA SP | G103: LEANDRO NUNES | H103: EVERSON GAIDSTIECHI | I103: 0 | J103: 0 | K103: 1500 | L103: 0 | N103: =Tabela1[[#This Row],[1QZ DE ABRIL 26]]-Tabela1[[#This Row],[SALDO FINAL]]-Tabela1[[#This Row],[SALDO CARTAO]]-Tabela1[[#This Row],[ADIANTAMENTO]] -> 1500 | O103: 0 | P103: =IF(Tabela1[[#This Row],[CARGA PARCIAL]]<0,0,Tabela1[[#This Row],[CARGA PARCIAL]])+Tabela1[[#This Row],[REEMBOLSO]] -> 1500 | Q103: Cartão ativo
B104: RODRIGO FRANCISCO DE SOUSA | C104: 34459886847 | D104: =_xlfn.XLOOKUP(Tabela1[[#This Row],[CPF]],[1]Funcionário!$B:$B,[1]Funcionário!$H:$H) -> ATIVO | E104: TELEFONICA SP | G104: LEANDRO NUNES | H104: EVERSON GAIDSTIECHI | I104: 0 | J104: 1500 | K104: 1500 | L104: 0 | N104: =Tabela1[[#This Row],[1QZ DE ABRIL 26]]-Tabela1[[#This Row],[SALDO FINAL]]-Tabela1[[#This Row],[SALDO CARTAO]]-Tabela1[[#This Row],[ADIANTAMENTO]] -> 0 | O104: 0 | P104: =IF(Tabela1[[#This Row],[CARGA PARCIAL]]<0,0,Tabela1[[#This Row],[CARGA PARCIAL]])+Tabela1[[#This Row],[REEMBOLSO]] -> 0 | Q104: Cadastro pendente
...

Sheet Planilha3
B2: Cobrança | C2: Nome | D2: E-mail | E2: Tipo de usuário | F2: Status do Cartão | G2: Permissão de Uso | H2: Permissão de Gestão | I2: Ações
C3: ABNER ANDRADE CAVALCANTE | D3: abner.cavalcante@eqsengenharia.com.br | E3: Normal | F3: Cartão ativo | G3: Portador de Cartão | H3: Sem permissão
C4: ADAN LEONARDO SOUZA BATISTA | D4: adan.batista@eqsengenharia.com.br | E4: Normal | F4: Cartão ativo | G4: Portador de Cartão | H4: Sem permissão
C5: ADAUTO JOSE PEREIRA | D5: adautojosepereira@yahoo.com.br | E5: Normal | F5: Cartão ativo | G5: Portador de Cartão | H5: Sem permissão
C6: ADEMARCIO DUARTE LOPES | D6: ctba_projetos@hotmail.com | E6: Normal | F6: Cartão ativo | G6: Portador de Cartão | H6: Sem permissão
C7: ADILSON ANTONIO JACINTO | D7: dirson4867@yahoo.com | E7: Normal | F7: Cartão ativo | G7: Portador de Cartão | H7: Sem permissão
C8: ADILSON MELLO DE CAMARGO | D8: adilsoncamargo@eqseng.com.br | E8: Normal | F8: Cartão ativo | G8: Portador de Cartão | H8: Sem permissão
C9: ADILSON RODRIGUES FERREIRA | D9: adilson.ferreira@eqsengenharia.com.br | E9: Intermediário | F9: Cadastro pendente | G9: Portador de Cartão | H9: Sem permissão
C10: ADIVAR ANTONIO DA SILVA JUNIOR | D10: adivarjunior@gmail.com | E10: Normal | F10: Cartão ativo | G10: Portador de Cartão | H10: Sem permissão
C11: ADMILSON DA SILVA FARIAS | D11: admilsonfarias2016@gmail.com | E11: Normal | F11: Cadastro pendente | G11: Portador de Cartão | H11: Sem permissão
C12: ADMILSON DOS SANTOS GALAN | D12: admilsongalan@gmail.com | E12: Normal | F12: Cartão ativo | G12: Portador de Cartão | H12: Sem permissão
C13: ADRIANA DA CONCEICAO PEREIRA DE MELO | D13: adriana.melo@eqsengenharia.com.br | E13: Normal | F13: Cadastro pendente | G13: Portador de Cartão | H13: Sem permissão
C14: ADRIANE CARON | D14: adriane.caron@eqseng.com.br | E14: Normal | F14: Cartão ativo | G14: Portador de Cartão | H14: Sem permissão
... C435: MELSO CEZAR DA SILVA NETO | D435: melsocezar@gmail.com | E435: Normal | F435: Cartão ativo | G435: Portador de Cartão | H435: Sem permissão
C436: MELSO CEZAR DA SILVA NETO
C437: MICHAEL RODRIGUES SANTOS | D437: michael.santos@eqseng.com.br | E437: Normal | F437: Cartão ativo | G437: Portador de Cartão | H437: Sem permissão
C438: MICHEL DOS SANTOS VENANCIO | D438: michel.venancio29@gmail.com | E438: Normal | F438: Cartão ativo | G438: Portador de Cartão | H438: Sem permissão
C439: MICHEL VINHORTE DE SOUZA | D439: michellmvs@gmail.com | E439: Normal | F439: Cartão ativo | G439: Portador de Cartão | H439: Sem permissão
C440: MIGUEL JOAO DINIS MOTA | D440: mjdmota@gmail.com | E440: Normal | F440: Cartão ativo | G440: Portador de Cartão | H440: Sem permissão
C441: MILTON BRASIL CAVALCANTE | D441: v.tiomilton@gmail.com | E441: Normal | F441: Cadastro pendente | G441: Portador de Cartão | H441: Sem permissão
C442: MILTON FERREIRA DAS NEVES JUNIOR | D442: milton.neves@eqsengenharia.com.br | E442: Normal | F442: Cartão ativo | G442: Portador de Cartão | H442: Sem permissão
C443: MILTON FLECK PITROWSKI | D443: milton.pitrowski@eqseng.com.br | E443: Normal | F443: Cartão ativo | G443: Portador de Cartão | H443: Sem permissão
C444: MOISES DOS SANTOS CABRAL | D444: moises.cabral@eqsengenharia.com.br | E444: Normal | F444: Cartão ativo | G444: Portador de Cartão | H444: Sem permissão
C445: MURILO DE ALMEIDA | D445: murilo.almeida@eqsengenharia.com.br | E445: Normal | F445: Cartão ativo | G445: Portador de Cartão | H445: Sem permissão
C446: NELSON FILIPE MARTINS DA SILVA | D446: nelsonfilipe316@gmail.com | E446: Normal | F446: Cartão ativo | G446: Portador de Cartão | H446: Sem permissão
C447: NERTAN DE CASTRO MAIA | D447: nertancastromaia@gmail.com | E447: Normal | F447: Cartão ativo | G447: Portador de Cartão | H447: Sem permissão
C448: NEUDO SAMPIETRO | D448: neudoengeman@gmail.com | E448: Normal | F448: Cartão ativo | G448: Portador de Cartão | H448: Sem permissão
... C597: WILSON LUIZ CABRAL | D597: wilson.cabral@eqsengenharia.com.br | E597: Normal | F597: Cartão ativo | G597: Portador de Cartão | H597: Sem permissão
B598: Página 12 de 12
B599: Itens por página:
B600: 50

Sheet Planilha2
B2: Cobrança | C2: Nome | D2: E-mail | E2: Tipo de usuário | F2: Status do Cartão | G2: Permissão de Uso | H2: Permissão de Gestão | I2: Ações
C3: ABNER ANDRADE CAVALCANTE | D3: abner.cavalcante@eqsengenharia.com.br | E3: Normal | F3: Cartão ativo | G3: Portador de Cartão | H3: Sem permissão
C4: ADAN LEONARDO SOUZA BATISTA | D4: adan.batista@eqsengenharia.com.br | E4: Normal | F4: Cartão ativo | G4: Portador de Cartão | H4: Sem permissão
C5: ADAUTO JOSE PEREIRA | D5: adautojosepereira@yahoo.com.br | E5: Normal | F5: Cartão ativo | G5: Portador de Cartão | H5: Sem permissão
C6: ADEMARCIO DUARTE LOPES | D6: ctba_projetos@hotmail.com | E6: Normal | F6: Cartão ativo | G6: Portador de Cartão | H6: Sem permissão
C7: ADILSON MELLO DE CAMARGO | D7: adilsoncamargo@eqseng.com.br | E7: Normal | F7: Cartão ativo | G7: Portador de Cartão | H7: Sem permissão
C8: ADILSON RODRIGUES FERREIRA | D8: adilson.ferreira@eqsengenharia.com.br | E8: Intermediário | F8: Cadastro pendente | G8: Portador de Cartão | H8: Sem permissão
C9: ADIVAR ANTONIO DA SILVA JUNIOR | D9: adivarjunior@gmail.com | E9: Normal | F9: Cartão ativo | G9: Portador de Cartão | H9: Sem permissão
C10: ADMILSON DOS SANTOS GALAN | D10: admilsongalan@gmail.com | E10: Normal | F10: Cartão ativo | G10: Portador de Cartão | H10: Sem permissão
C11: ADRIANE CARON | D11: caronjca@gmail.com | E11: Normal | F11: Cadastro pendente | G11: Portador de Cartão | H11: Sem permissão
C12: ADRIANO BORGES TEIXEIRA | D12: adrianoteixeiraeletricista@gmail.com | E12: Normal | F12: Cartão não vinculado | G12: Portador de Cartão | H12: Sem permissão
C13: ADRIANO FRANCISCO DE PAULA | D13: adriano.paula@eqsengenharia.com.br | E13: Normal | F13: Cartão ativo | G13: Portador de Cartão | H13: Sem permissão
C14: ADSON ARAUJO DA SILVA | D14: adson.silva@eqsengenharia.com.br | E14: Normal | F14: Cartão ativo | G14: Portador de Cartão | H14: Sem permissão
... C543: WILSON LUIZ CABRAL | D543: wilson.cabral@eqsengenharia.com.br | E543: Normal | F543: Cartão ativo | G543: Portador de Cartão | H543: Sem permissão

Sheet Planilha1
B1: Cobrança | C1: Nome | D1: E-mail | E1: Tipo de usuário | F1: Status do Cartão | G1: Permissão de Uso | H1: Permissão de Gestão | I1: Ações
C2: ABNER ANDRADE CAVALCANTE | D2: abner.cavalcante@eqsengenharia.com.br | E2: Normal | F2: Cartão ativo | G2: Portador de Cartão | H2: Sem permissão
C3: ADAN LEONARDO SOUZA BATISTA | D3: adan.batista@eqsengenharia.com.br | E3: Normal | F3: Cartão ativo | G3: Portador de Cartão | H3: Sem permissão
C4: ADAUTO JOSE PEREIRA | D4: adautojosepereira@yahoo.com.br | E4: Normal | F4: Cartão ativo | G4: Portador de Cartão | H4: Sem permissão
C5: ADEMARCIO DUARTE LOPES | D5: ctba_projetos@hotmail.com | E5: Normal | F5: Cartão ativo | G5: Portador de Cartão | H5: Sem permissão
C6: ADILSON MELLO DE CAMARGO | D6: adilsoncamargo@eqseng.com.br | E6: Normal | F6: Cartão ativo | G6: Portador de Cartão | H6: Sem permissão
C7: ADILSON RODRIGUES FERREIRA | D7: adilson.ferreira@eqsengenharia.com.br | E7: Intermediário | F7: Cadastro pendente | G7: Portador de Cartão | H7: Sem permissão
C8: ADIVAR ANTONIO DA SILVA JUNIOR | D8: adivarjunior@gmail.com | E8: Normal | F8: Cartão ativo | G8: Portador de Cartão | H8: Sem permissão
C9: ADMILSON DOS SANTOS GALAN | D9: admilsongalan@gmail.com | E9: Normal | F9: Cartão ativo | G9: Portador de Cartão | H9: Sem permissão
C10: ADRIANE CARON | D10: caronjca@gmail.com | E10: Normal | F10: Cadastro pendente | G10: Portador de Cartão | H10: Sem permissão
C11: ADRIANO BORGES TEIXEIRA | D11: adrianoteixeiraeletricista@gmail.com | E11: Normal | F11: Cartão não vinculado | G11: Portador de Cartão | H11: Sem permissão
C12: ADRIANO FRANCISCO DE PAULA | D12: adriano.paula@eqsengenharia.com.br | E12: Normal | F12: Cartão ativo | G12: Portador de Cartão | H12: Sem permissão
C13: ADSON ARAUJO DA SILVA | D13: adson.silva@eqsengenharia.com.br | E13: Normal | F13: Cartão ativo | G13: Portador de Cartão | H13: Sem permissão
... C532: JOSE DO PRADO ROSA | D532: zepradoeqs@gmail.com | E532: Normal | F532: Cartão ativo | G532: Portador de Cartão | H532: Sem permissão

Sheet VALIDAÇÃO AGILLITAS
A1: PORTADOR | C1: CARTÃO | D1: AGILLITAS | E1: Situação cpf | F1: situação nome | G1: CARTAO VALIDACAO
A2: ABNER ANDRADE CAVALCANTE | B2: 02027745203 | C2: AGILLITAS | D2: 9042407399982 | E2: ATIVO | F2: ATIVO | G2: AGILLITAS
A3: JAEDER RODRIGUES JUNIOR | B3: 07505987607 | C3: AGILLITAS | D3: 9042408249079 | E3: ATIVO | F3: ATIVO | G3: AGILLITAS
A4: THIAGO DE MEDEIROS VANZELER | B4: 11590627733 | C4: AGILLITAS | D4: 9042407080491 | E4: ATIVO | F4: ATIVO | G4: AGILLITAS
A5: JOSE ROBERTO DA SILVA FREIRE | B5: 54229464134 | C5: AGILLITAS | D5: 9042406782287 | E5: ATIVO | F5: #N/A | G5: AGILLITAS
A6: WALTER DE CAMPOS NUNES NETO | B6: 99114160030 | C6: AGILLITAS | D6: 9042408803396 | E6: ATIVO | F6: ATIVO | G6: AGILLITAS
A7: JUAN CARLOS PANTOJA AMANAJAS | B7: 51027941249 | C7: AGILLITAS | D7: - | E7: ATIVO | F7: INATIVO | G7: AGILLITAS
A8: LUDGERO HORACIO DE OLIVEIRA | B8: 06576198922 | C8: AGILLITAS | D8: 9042407986861 | E8: ATIVO | F8: ATIVO | G8: AGILLITAS
A9: CARLOS NASCIMENTO NONATO JUNIOR | B9: 65973500225 | C9: AGILLITAS | D9: 9042406782022 | E9: ATIVO | F9: ATIVO | G9: AGILLITAS
A10: MICHAEL RODRIGUES SANTOS | B10: 37425574837 | C10: AGILLITAS | D10: 9042407400145 | E10: ATIVO | F10: ATIVO | G10: AGILLITAS
A11: FLAVIO FERNANDES DOS REIS LIMA | B11: 01767960107 | C11: AGILLITAS | D11: 9042408803750 | E11: ATIVO | F11: ATIVO | G11: AGILLITAS
A12: VICTOR SIGOLO PINHEIRO PIMENTA | B12: 12237490619 | C12: AGILLITAS | D12: 9076505613050 | E12: ATIVO | F12: ATIVO | G12: AGILLITAS
A13: JOSE CLAUDIO RIBEIRO | B13: 61158852649 | C13: AGILLITAS | D13: 9042408803859 | E13: ATIVO | F13: ATIVO | G13: AGILLITAS
A14: LEUSAFFAN GUSTAVO DE SIQUEIRA | B14: 09502929667 | C14: AGILLITAS | D14: #N/A | E14: #N/A | F14: #N/A | G14: #N/A
A15: FABIO DIOGO BITTENCOURT | B15: 00526143959 | C15: AGILLITAS | D15: 9042408970526 | E15: ATIVO | F15: ATIVO | G15: AGILLITAS
A16: LEANDRO FIGUEREDO BELCHIOR | B16: 26513583802 | C16: AGILLITAS | D16: 9042408599341 | E16: ATIVO | F16: ATIVO | G16: AGILLITAS
A17: BRUNO OLIVEIRA DIAS | B17: 11992259755 | C17: AGILLITAS | D17: 9042408803735 | E17: ATIVO | F17: #N/A | G17: AGILLITAS
A18: ANDRE LUIZ SANTANA | B18: 11897381638 | C18: AGILLITAS | D18: 9042408249145 | E18: ATIVO | F18: ATIVO | G18: AGILLITAS
A19: CARLOS EDUARDO SCATAMBULO | B19: 22730778829 | C19: AGILLITAS | D19: 9042406781958 | E19: ATIVO | F19: ATIVO | G19: AGILLITAS
A20: GUILHERME BATISTA DA SILVA | B20: 14829137711 | C20: AGILLITAS | D20: 9076509301751 | E20: ATIVO | F20: ATIVO | G20: AGILLITAS
A21: MARCO AURELIO DE LIMA | B21: 01356318665 | C21: AGILLITAS | D21: 9042408970203 | E21: ATIVO | F21: ATIVO | G21: AGILLITAS
A22: EDINALDO LEAL DE SOUZA | B22: 82277206172 | C22: AGILLITAS | D22: 9042408803305 | E22: ATIVO | F22: ATIVO | G22: AGILLITAS
A23: NEDSON LUIZ DURAES VELOSO | B23: 11498112692 | C23: AGILLITAS | D23: 9042407080285 | E23: ATIVO | F23: ATIVO | G23: AGILLITAS
A24: CLERITON BACILA DOS SANTOS | B24: 05456615959 | C24: AGILLITAS | D24: 9042406782311 | E24: ATIVO | F24: ATIVO | G24: AGILLITAS
A25: JOELSON FERREIRA DOS SANTOS | B25: 07690263623 | C25: AGILLITAS | D25: 9042406781990 | E25: ATIVO | F25: #N/A | G25: AGILLITAS
A26: ISA CARLA DE OLIVEIRA LOPES | B26: 06085235429 | C26: AGILLITAS | D26: #N/A | E26: #N/A | F26: #N/A | G26: #N/A
A27: RENATO DIAS DOS SANTOS | B27: 03498210114 | C27: AGILLITAS | D27: #N/A | E27: #N/A | F27: #N/A | G27: #N/A
A28: EDUARDO SANTOS | B28: 91270529072 | C28: AGILLITAS | D28: 9042407752073 | E28: ATIVO | F28: ATIVO | G28: AGILLITAS
A29: SAULO ARAUJO DE PAULA | B29: 31040091806 | C29: AGILLITAS | D29: 9042407552176 | E29: ATIVO | F29: ATIVO | G29: AGILLITAS
A30: ANGELICA APARECIDA DOS SANTOS | B30: 34857901846 | C30: AGILLITAS | D30: 9042408803891 | E30: ATIVO | F30: ATIVO | G30: AGILLITAS
A31: DANIEL DA SILVA LOPES | B31: 94288259053 | C31: AGILLITAS | D31: 9042407552085 | E31: ATIVO | F31: ATIVO | G31: FLASH
A32: VINICIUS ALVES VIEIRA | B32: EXCLUIR | C32: AGILLITAS | D32: #N/A | E32: #N/A | F32: #N/A | G32: #N/A
A33: CARLOS AUGUSTO ALVES CAVALCANTI | B33: EXCLUIR | C33: AGILLITAS | D33: #N/A | E33: #N/A | F33: #N/A | G33: #N/A
A34: ANDRESA INDIRA SANTANA AGGIO | B34: EXCLUIR | C34: AGILLITAS | D34: #N/A | E34: #N/A | F34: #N/A | G34: #N/A
A35: RODRIGO BOLDO | B35: 27104988807 | C35: AGILLITAS | D35: 9042408599291 | E35: ATIVO | F35: ATIVO | G35: AGILLITAS
A36: EMERSON LEITE DE BARROS | B36: 34168918807 | C36: AGILLITAS | D36: 9042408340399 | E36: ATIVO | F36: ATIVO | G36: AGILLITAS
A37: ANTONIO JOSE PEREIRA DA SILVA | B37: 08326260401 | C37: AGILLITAS | D37: 9042408481813 | E37: ATIVO | F37: ATIVO | G37: AGILLITAS
A38: STEPHANIE THAINARA DE OLIVEIRA ROCHA DA COSTA | B38: 14084321613 | C38: AGILLITAS | D38: 9076505613068 | E38: ATIVO | F38: ATIVO | G38: AGILLITAS
A39: JOSÉ LUIS TERRIBILE | B39: 65009304015 | C39: AGILLITAS | D39: 9042408804113 | E39: ATIVO | F39: ATIVO | G39: AGILLITAS
A40: CLAUDEMIR GREGOSKI RODRIGUES | B40: 05144026958 | C40: AGILLITAS | D40: 9042408970278 | E40: ATIVO | F40: ATIVO | G40: AGILLITAS
A41: MICHEL RODRIGUES FIALHO | B41: 01419704648 | C41: AGILLITAS | D41: 9042407080483 | E41: ATIVO | F41: ATIVO | G41: AGILLITAS
A42: LEONARDO ORESTES SOARES | B42: 05892698440 | C42: AGILLITAS | D42: 9042407266645 | E42: ATIVO | F42: ATIVO | G42: AGILLITAS
A43: FRANCINILDO JACKSON DE ALMEIDA ARAUJO | B43: 07021071400 | C43: AGILLITAS | D43: 9042408601386 | E43: ATIVO | F43: ATIVO | G43: FLASH
A44: TULIO VELOSO HONORATO | B44: 12609931670 | C44: AGILLITAS | D44: 9042408970195 | E44: ATIVO | F44: ATIVO | G44: AGILLITAS
A45: MOISES DOS SANTOS CABRAL | B45: 68746458204 | C45: AGILLITAS | D45: 9076509186467 | E45: ATIVO | F45: ATIVO | G45: AGILLITAS
A46: BRUNA LAIS AZEVEDO CUNHA | B46: 07747008406 | C46: AGILLITAS | D46: 9076505447152 | E46: ATIVO | F46: ATIVO | G46: AGILLITAS
... A48: ALMIR SILVA DA ROSA | B48: 80616232004 | C48: AGILLITAS | D48: 9042408970450 | E48: ATIVO | F48: ATIVO | G48: AGILLITAS
A49: HUGO DELLA JUSTINA | B49: 03031202902 | C49: AGILLITAS | D49: INCLUIR | E49: #N/A | F49: #N/A | G49: #N/A
A50: MARCIA CRISTINA DA CUNHA SCATAMBULO | B50: 27375810877 | C50: AGILLITAS | D50: INCLUIR | E50: #N/A | F50: #N/A | G50: #N/A
A51: CLAUDINEI AMARAL | B51: 10433881844 | C51: AGILLITAS | D51: 9076509186558 | E51: ATIVO | F51: ATIVO | G51: AGILLITAS
A52: RICARDO ZORZETTO | B52: 00539580040 | C52: AGILLITAS | D52: 9042407552150 | E52: ATIVO | F52: ATIVO | G52: AGILLITAS
A53: WALTER LUIZ DE OLIVEIRA BRAGA | B53: 04042182291 | C53: AGILLITAS | D53: 9042408340506 | E53: ATIVO | F53: ATIVO | G53: AGILLITAS
A54: RENATO PARREIRAS | B54: 97162485634 | C54: AGILLITAS | D54: 9042407351504 | E54: ATIVO | F54: ATIVO | G54: AGILLITAS
A55: RAUL ADRIANO DOS SANTOS | B55: 03288831902 | C55: AGILLITAS | D55: 9042408803529 | E55: ATIVO | F55: ATIVO | G55: AGILLITAS
A56: RAFAEL PORTO ALVES DA CRUZ | B56: 11914988671 | C56: AGILLITAS | D56: 9042407351496 | E56: ATIVO | F56: ATIVO | G56: AGILLITAS
A57: OSCAR DOMINGO PALARO | B57: 03067535960 | C57: AGILLITAS | D57: 9076505875451 | E57: ATIVO | F57: ATIVO | G57: FLASH
A58: MATHEUS LEANDRO BARROSO | B58: 11401604609 | C58: AGILLITAS | D58: 9042408249095 | E58: ATIVO | F58: ATIVO | G58: AGILLITAS
A59: FRANCIELLY CAVALCANTE SANTOS DE ANDRADE | B59: 09276240446 | C59: AGILLITAS | D59: 9042407400087 | E59: ATIVO | F59: #N/A | G59: AGILLITAS
A60: ADSON ARAUJO DA SILVA | B60: 94551804304 | C60: AGILLITAS | D60: 9042408803966 | E60: ATIVO | F60: ATIVO | G60: FLASH
A61: DIEGO DE ALCANTARA MOTA MENDES | B61: 09407167631 | C61: AGILLITAS | D61: 9042408970211 | E61: ATIVO | F61: ATIVO | G61: AGILLITAS
A62: ALISON ALVES DOS SANTOS | B62: EXCLUIR | C62: AGILLITAS | D62: #N/A | E62: #N/A | F62: #N/A | G62: #N/A
A63: ANTONIO FERREIRA DE MENDONCA NETO | B63: 05766838760 | C63: AGILLITAS | D63: 9042408803685 | E63: ATIVO | F63: #N/A | G63: AGILLITAS
A64: DIEGO JOSE DE PAULO | B64: 01553544692 | C64: AGILLITAS | D64: 9042408599317 | E64: ATIVO | F64: ATIVO | G64: AGILLITAS
A65: ODAIR CIRCO SOARES | B65: 84219122915 | C65: AGILLITAS | D65: 9042408803537 | E65: ATIVO | F65: ATIVO | G65: AGILLITAS
A66: JAQUELINE LEVATI PEREIRA | B66: 01310014264 | C66: AGILLITAS | D66: 9076509186731 | E66: ATIVO | F66: ATIVO | G66: AGILLITAS
A67: DHIEGO RIBEIRO DINIZ | B67: 00049250256 | C67: AGILLITAS | D67: 9042408599283 | E67: ATIVO | F67: #N/A | G67: AGILLITAS
A68: CRISTIANO DA SILVA VALADARES | B68: 99062208649 | C68: AGILLITAS | D68: 9042408601295 | E68: ATIVO | F68: ATIVO | G68: AGILLITAS
A69: SILVIO VINICIUS PINHEIRO GOES | B69: 51182084168 | C69: AGILLITAS | D69: 9042408481649 | E69: ATIVO | F69: #N/A | G69: AGILLITAS
A70: DANIEL RIBEIRO DE CASTRO | B70: 08496764605 | C70: AGILLITAS | D70: 9042408340530 | E70: ATIVO | F70: ATIVO | G70: AGILLITAS
A71: VALTER HUGO SILVERIO DA SILVA FACHINETTI | B71: 21704495822 | C71: AGILLITAS | D71: CONTA ENCERRADA | E71: ATIVO | F71: NÃO | G71: AGILLITAS
A72: WELTON GERALDO WROBLEWSKI | B72: 91443130982 | C72: AGILLITAS | D72: 9042408970336 | E72: ATIVO | F72: ATIVO | G72: AGILLITAS
A73: RAFAEL SILVA DA FONSECA | B73: 00635358077 | C73: AGILLITAS | D73: 9042406782352 | E73: ATIVO | F73: ATIVO | G73: AGILLITAS
A74: MARCOS SEGER | B74: 97135631900 | C74: AGILLITAS | D74: 9042406781933 | E74: ATIVO | F74: ATIVO | G74: AGILLITAS
A75: RAQUEL PANTOJA SANTOS | B75: 89395140259 | C75: AGILLITAS | D75: 9042407080335 | E75: ATIVO | F75: ATIVO | G75: AGILLITAS
A76: WEVERSON SANTANA SILVA | B76: #N/A | C76: AGILLITAS | D76: #N/A | E76: #N/A | F76: #N/A | G76: #N/A
A77: JOELSON JUNIOR MARTINS DE GOES | B77: 03528389907 | C77: AGILLITAS | D77: 9042407080210 | E77: ATIVO | F77: ATIVO | G77: AGILLITAS
A78: LAIS SOARES QUARESMA | B78: 05136678909 | C78: AGILLITAS | D78: 9076505447400 | E78: ATIVO | F78: #N/A | G78: AGILLITAS
A79: MARCIO BOUZAS FERREIRA | B79: 07318362780 | C79: AGILLITAS | D79: 9042407023905 | E79: ATIVO | F79: ATIVO | G79: AGILLITAS
A80: JOAO AGOSTINHO DA COSTA REIS | B80: 11764705661 | C80: AGILLITAS | D80: 9042407351512 | E80: ATIVO | F80: ATIVO | G80: AGILLITAS
A81: VICTOR MIGUEL PALARO | B81: 09265596996 | C81: AGILLITAS | D81: 9042408803503 | E81: ATIVO | F81: ATIVO | G81: AGILLITAS
A82: MARCELO PEREIRA LIMA | B82: 10254434894 | C82: AGILLITAS | D82: 9042408803834 | E82: ATIVO | F82: ATIVO | G82: AGILLITAS
A83: DAVID WILSON SILVA DOS SANTOS | B83: EXCLUIR | C83: AGILLITAS | D83: #N/A | E83: #N/A | F83: #N/A | G83: #N/A
A84: ANTONIO MARCOS CAMARGO | B84: 04836584990 | C84: AGILLITAS | D84: 9042407983678 | E84: ATIVO | F84: ATIVO | G84: AGILLITAS
A85: MATEUS DE CARVALHO BERTOL | B85: 01304856674 | C85: AGILLITAS | D85: 9042408340456 | E85: ATIVO | F85: ATIVO | G85: AGILLITAS
A86: SIDNEI MACHADO | B86: 02710155940 | C86: AGILLITAS | D86: 9042408803438 | E86: ATIVO | F86: ATIVO | G86: AGILLITAS
A87: EDSON VEIGA SILVEIRA | B87: 62063774072 | C87: AGILLITAS | D87: 9042408249046 | E87: ATIVO | F87: ATIVO | G87: AGILLITAS
A88: LUIZ GUSTAVO DI GIORGIO | B88: 29856268893 | C88: AGILLITAS | D88: 9076505447459 | E88: ATIVO | F88: ATIVO | G88: AGILLITAS
A89: AGUINA FERNANDES DE OLIVEIRA | B89: 60572957149 | C89: AGILLITAS | D89: 9042407266694 | E89: ATIVO | F89: ATIVO | G89: AGILLITAS
A90: DIVAN ALVES DE AMORIM | B90: 11422891844 | C90: AGILLITAS | D90: 9042408481680 | E90: ATIVO | F90: ATIVO | G90: AGILLITAS
A91: ANA LUIZA OLIVEIRA CAMELO | B91: 77283759204 | C91: AGILLITAS | D91: 9042407986804 | E91: ATIVO | F91: ATIVO | G91: AGILLITAS
A92: MICHEL VINHORTE DE SOUZA | B92: 70457883200 | C92: AGILLITAS | D92: 9042407400137 | E92: ATIVO | F92: ATIVO | G92: AGILLITAS
A93: LEANDRO DE MENEZES ASSUNCAO | B93: 09072032640 | C93: AGILLITAS | D93: 9042408483132 | E93: ATIVO | F93: #N/A | G93: AGILLITAS
A94: SANDRO CAPISTRANO | B94: 16996346886 | C94: AGILLITAS | D94: 9042408803875 | E94: ATIVO | F94: #N/A | G94: AGILLITAS
A95: RODRIGO MACHADO MOTTA | B95: 98808559068 | C95: AGILLITAS | D95: 9042408601337 | E95: ATIVO | F95: ATIVO | G95: AGILLITAS
A96: RODRIGO JOSE DE PAULA | B96: 03348917956 | C96: AGILLITAS | D96: 9042408340431 | E96: ATIVO | F96: ATIVO | G96: AGILLITAS
A97: CRISTIANE ANTUNES DA SILVA | B97: 07193849743 | C97: AGILLITAS | D97: 9042408599390 | E97: ATIVO | F97: ATIVO | G97: AGILLITAS
A98: MARCEL GOMES DE OLIVEIRA | B98: 29011288823 | C98: AGILLITAS | D98: 9076509186582 | E98: ATIVO | F98: ATIVO | G98: AGILLITAS
A99: LUCAS DE PAULA SILVA | B99: 08204909977 | C99: AGILLITAS | D99: 9042408804014 | E99: ATIVO | F99: ATIVO | G99: AGILLITAS
A100: RAFAEL NATAL LACHI | B100: 03710085900 | C100: AGILLITAS | D100: 9042408970310 | E100: ATIVO | F100: ATIVO | G100: AGILLITAS
A101: DOUGLAS TIAGO DE OLIVEIRA | B101: 08492402989 | C101: AGILLITAS | D101: 9076509186590 | E101: ATIVO | F101: ATIVO | G101: AGILLITAS
...
