Workbook

Sheet EXTRATO
A1: ANO | B1: MÊS | C1: Data | D1: Hora | E1: Código de Transação | F1: Usuário | G1: Tipo | H1: Descrição | I1: Valor | K1: Soma de Valor | L1: Rótulos de Coluna
A2: =YEAR(C2) -> 2025 | B2: =UPPER(TEXT(C2,"MMMM")) -> MAIO | C2: 45803.745 | D2: 17:53:10 | E2: 137C414978148D7BCE6116C90C32FB46 | F2: Andre Valerio de Paiva | G2: Carga | H2: Transf. EQS > Andre V. d. Paiva: 2 QUINZENA - MAIO/2025 | I2: 398.47 | K2: Rótulos de Linha | L2: Carga | M2: Saque | N2: Taxa | O2: Transferência | P2: Pix | Q2: Total Geral
A3: =YEAR(C3) -> 2025 | B3: =UPPER(TEXT(C3,"MMMM")) -> JUNHO | C3: 45817.647 | D3: 15:31:40 | E3: 1CD51B8DF8BA34A6A5D2AFF62E6338B7 | F3: Andre Valerio de Paiva | G3: Carga | H3: Transf. EQS > Andre V. d. Paiva | I3: 1.53 | K3: 2025 | L3: 460 | M3: -420 | N3: -7 | Q3: 33
A4: =YEAR(C4) -> 2025 | B4: =UPPER(TEXT(C4,"MMMM")) -> JUNHO | C4: 45819.749 | D4: 17:57:57 | E4: C8175505416C3DB5A589DE296B620152 | F4: Andre Valerio de Paiva | G4: Carga | H4: Transf. EQS > Andre V. d. Paiva | I4: 46 | K4: mai | L4: 398.47 | Q4: 398.47
A5: =YEAR(C5) -> 2025 | B5: =UPPER(TEXT(C5,"MMMM")) -> JULHO | C5: 45849.852 | D5: 20:27:22 | E5: 62FCDB383099619BDAEDAD40583645A5 | F5: Andre Valerio de Paiva | G5: Saque | H5: TECBAN-SUPERMERCADO BA | I5: -420 | K5: jun | L5: 47.53 | Q5: 47.53
A6: =YEAR(C6) -> 2025 | B6: =UPPER(TEXT(C6,"MMMM")) -> JULHO | C6: 45849.853 | D6: 20:27:46 | E6: 00C7EADE00EEBB1752FE29D0EC1CEC1E | F6: Andre Valerio de Paiva | G6: Taxa | H6: Taxa de saque | I6: -7 | K6: jul | M6: -420 | N6: -7 | Q6: -427
A7: =YEAR(C7) -> 2025 | B7: =UPPER(TEXT(C7,"MMMM")) -> AGOSTO | C7: 45880.63 | D7: 15:07:26 | E7: 2191753ADA6D312327FCB05EA9304316 | F7: Andre Valerio de Paiva | G7: Carga | H7: Transf. EQS > Andre V. d. Paiva | I7: 7 | K7: ago | L7: 14 | Q7: 14
A8: =YEAR(C8) -> 2025 | B8: =UPPER(TEXT(C8,"MMMM")) -> AGOSTO | C8: 45894.717 | D8: 17:12:11 | E8: EC61BF15E537FBDB296059BD2A09C22F | F8: Andre Valerio de Paiva | G8: Carga | H8: Transf. EQS > Andre V. d. Paiva | I8: 7 | K8: 2026 | L8: 2452.37 | M8: -1330 | N8: -39.43 | O8: -327.94 | P8: -788 | Q8: -33
A9: =YEAR(C9) -> 2026 | B9: =UPPER(TEXT(C9,"MMMM")) -> JANEIRO | C9: 46034.73 | D9: 17:31:39 | E9: 9A18D34C7527759F4CF6B1FE6E7756E6 | F9: Andre Valerio de Paiva | G9: Carga | H9: Transf. EQS > Andre V. d. Paiva | I9: 278.05 | K9: jan | L9: 985.05 | M9: -690 | N9: -14 | O9: -311.05 | Q9: -30
A10: =YEAR(C10) -> 2026 | B10: =UPPER(TEXT(C10,"MMMM")) -> JANEIRO | C10: 46036.593 | D10: 14:13:49 | E10: 11AD4C44172DB00115BA31D3CBF8BEB5 | F10: Andre Valerio de Paiva | G10: Transferência | H10: Transf. Andre V. d. Paiva > EQS | I10: -311.05 | K10: fev | L10: 377.1 | Q10: 377.1
A11: =YEAR(C11) -> 2026 | B11: =UPPER(TEXT(C11,"MMMM")) -> JANEIRO | C11: 46036.6 | D11: 14:24:36 | E11: 0FBAC1ABC3CE48C01EF09197DD26FE07 | F11: Andre Valerio de Paiva | G11: Carga | H11: Transf. REGIONAL MG > Andre V. d. Paiva | I11: 311.05 | K11: mar | L11: 278.11 | M11: -640 | N11: -14 | Q11: -375.89
A12: =YEAR(C12) -> 2026 | B12: =UPPER(TEXT(C12,"MMMM")) -> JANEIRO | C12: 46042.592 | D12: 14:11:52 | E12: 03F7965ED6179704C61F53D0C806AEC6 | F12: Andre Valerio de Paiva | G12: Saque | H12: TECBAN-SUPERM BH MURIA | I12: -300 | K12: abr | L12: 25.21 | O12: -11.21 | Q12: 14
A13: =YEAR(C13) -> 2026 | B13: =UPPER(TEXT(C13,"MMMM")) -> JANEIRO | C13: 46042.592 | D13: 14:12:22 | E13: C2187C044E75301D82DE7D63BC2D29DC | F13: Andre Valerio de Paiva | G13: Taxa | H13: Taxa de saque | I13: -7 | K13: mai | L13: 786.9 | N13: -11.43 | O13: -1.56 | P13: -788 | Q13: -14.09
A14: =YEAR(C14) -> 2026 | B14: =UPPER(TEXT(C14,"MMMM")) -> JANEIRO | C14: 46048.622 | D14: 14:55:02 | E14: 5BDAB8CCCA48630E3C1F437964CC5029 | F14: Andre Valerio de Paiva | G14: Carga | H14: Transf. REGIONAL MG > Andre V. d. Paiva | I14: 395.95 | K14: ago | O14: -4.12 | Q14: -4.12
A15: =YEAR(C15) -> 2026 | B15: =UPPER(TEXT(C15,"MMMM")) -> JANEIRO | C15: 46049.687 | D15: 16:29:34 | E15: 96C8F4F2A071C905A3EDD1212F0D4D83 | F15: Andre Valerio de Paiva | G15: Saque | H15: TECBAN-BAHAMAS EMPORIO | I15: -390 | K15: Total Geral | L15: 2912.37 | M15: -1750 | N15: -46.43 | O15: -327.94 | P15: -788 | Q15: 6.1284311e-14
A16: =YEAR(C16) -> 2026 | B16: =UPPER(TEXT(C16,"MMMM")) -> JANEIRO | C16: 46049.688 | D16: 16:30:10 | E16: 799A589369B7BADE79C8F9E808FEDCD8 | F16: Andre Valerio de Paiva | G16: Taxa | H16: Taxa de saque | I16: -7
A17: =YEAR(C17) -> 2026 | B17: =UPPER(TEXT(C17,"MMMM")) -> FEVEREIRO | C17: 46064.635 | D17: 15:14:29 | E17: 1E4FA6503789D8DB04304C878073DB1C | F17: Andre Valerio de Paiva | G17: Carga | H17: Transf. REGIONAL MG > Andre V. d. Paiva | I17: 188.55
A18: =YEAR(C18) -> 2026 | B18: =UPPER(TEXT(C18,"MMMM")) -> FEVEREIRO | C18: 46078.62 | D18: 14:52:24 | E18: 035F5095D076D48274704B8444505398 | F18: Andre Valerio de Paiva | G18: Carga | H18: Transf. REGIONAL MG > Andre V. d. Paiva | I18: 188.55
A19: =YEAR(C19) -> 2026 | B19: =UPPER(TEXT(C19,"MMMM")) -> MARÇO | C19: 46085.865 | D19: 20:45:18 | E19: 18DBBF828D6314C72EF2B5C367A78A30 | F19: Andre Valerio de Paiva | G19: Saque | H19: TECBAN-BAHAMAS EMPORIO | I19: -370
A20: =YEAR(C20) -> 2026 | B20: =UPPER(TEXT(C20,"MMMM")) -> MARÇO | C20: 46085.865 | D20: 20:45:35 | E20: 2EBF7815BA5D8A470DBFE58CE3A38269 | F20: Andre Valerio de Paiva | G20: Taxa | H20: Taxa de saque | I20: -7
A21: =YEAR(C21) -> 2026 | B21: =UPPER(TEXT(C21,"MMMM")) -> MARÇO | C21: 46097.648 | D21: 15:33:41 | E21: 866DF7C412FD54801B20B70CF887F84B | F21: Andre Valerio de Paiva | G21: Carga | H21: Transf. REGIONAL MG > Andre V. d. Paiva | I21: 278.11
A22: =YEAR(C22) -> 2026 | B22: =UPPER(TEXT(C22,"MMMM")) -> MARÇO | C22: 46108.769 | D22: 18:28:04 | E22: FC00108434016D163DB40B4ADE41FF60 | F22: Andre Valerio de Paiva | G22: Saque | H22: TECBAN-BAHAMAS EMPORIO | I22: -270
A23: =YEAR(C23) -> 2026 | B23: =UPPER(TEXT(C23,"MMMM")) -> MARÇO | C23: 46108.77 | D23: 18:28:35 | E23: E9B1DF3EAD9C251332A3C53D0A933A35 | F23: Andre Valerio de Paiva | G23: Taxa | H23: Taxa de saque | I23: -7
A24: =YEAR(C24) -> 2026 | B24: =UPPER(TEXT(C24,"MMMM")) -> ABRIL | C24: 46125.739 | D24: 17:43:42 | E24: D698997D4FD60E73CA2BE6B8847C9405 | F24: Andre Valerio de Paiva | G24: Carga | H24: Transf. REGIONAL MG > Andre V. d. Paiva | I24: 7
A25: =YEAR(C25) -> 2026 | B25: =UPPER(TEXT(C25,"MMMM")) -> ABRIL | C25: 46137.415 | D25: 09:56:58 | E25: D2A56B295AF8D9D9BD5641D72AF04E15 | F25: Andre Valerio de Paiva | G25: Transferência | H25: Transf. Andre V. d. Paiva > REGIONAL MG | I25: -11.21
A26: =YEAR(C26) -> 2026 | B26: =UPPER(TEXT(C26,"MMMM")) -> ABRIL | C26: 46139.71 | D26: 17:01:45 | E26: 8273D622F6294EDF01D0A81DA453DD33 | F26: Andre Valerio de Paiva | G26: Carga | H26: Transf. REGIONAL MG > Andre V. d. Paiva | I26: 18.21
A27: =YEAR(C27) -> 2026 | B27: =UPPER(TEXT(C27,"MMMM")) -> MAIO | C27: 46153.667 | D27: 16:00:10 | E27: A5527AB30545382AFA36ADBBDB02B84F | F27: Andre Valerio de Paiva | G27: Carga | H27: Transf. REGIONAL MG > Andre V. d. Paiva | I27: 387.12
... A34: =YEAR(C34) -> 2026 | B34: =UPPER(TEXT(C34,"MMMM")) -> AGOSTO | C34: 46235.423 | D34: 10:08:51 | E34: C6ED34D6E6F3CEB93AF4AA9063A0DB3E | F34: Andre Valerio de Paiva | G34: Transferência | H34: Transf. Andre V. d. Paiva > REGIONAL MG | I34: -4.12

Sheet PREST. CONTAS
A1: Ano | B1: Mês | C1: ID da Despesa | D1: ID do Relatório | E1: Nome do relatório | F1: Data | G1: Nome do membro de equipe | H1: CPF/CNPJ | I1: Status | J1: Data de Pagamento | K1: Descrição da despesa | L1: Tipo de Despesa | M1: Reembolsável | N1: Anotação da Despesa | O1: Anotação de Rateio | P1: Centro de Custos | Q1: Forma de pagamento | R1: Projeto | S1: Percentual de projeto | T1: Início do Percurso por GPS | U1: Fim do Percurso por GPS | V1: Valor do KM | W1: Kilômetros Percorridos | X1: Moeda do Relatório | Y1: Valor | Z1: Moeda da Conversão | AA1: Valor Convertido | AB1: Valor Total | AC1: Ultrapassou Política
A2: =YEAR(F2) -> 2026 | B2: =UPPER(TEXT(F2,"MMMM")) -> AGOSTO | C2: 88670231 | D2: 11259869 | E2: CAIXA 08/2026 | F2: 04/08/2026 | G2: ANDRE VALERIO DE PAIVA | H2: 12682517633 | I2: Enviado | K2: PEDAGIO | L2: PEDAGIO | M2: Não | N2: PEDAGIO | P2: CLARO INFRA MG | Q2: Saque VExpenses | R2: REGIONAL MG | S2: 1 | X2: BRL | Y2: 56.49 | AB2: 56.49 | AC2: Não
A3: =YEAR(F3) -> 2026 | B3: =UPPER(TEXT(F3,"MMMM")) -> JULHO | C3: 88670040 | D3: 11259841 | E3: CAIXA 07/2026 | F3: 15/07/2026 | G3: ANDRE VALERIO DE PAIVA | H3: 12682517633 | I3: Enviado | K3: PEDAGIO | L3: PEDAGIO | M3: Não | N3: PEDAGIO | P3: CLARO INFRA MG | Q3: Saque VExpenses | R3: REGIONAL MG | S3: 1 | X3: BRL | Y3: 81.83 | AB3: 81.83 | AC3: Não
A4: =YEAR(F4) -> 2026 | B4: =UPPER(TEXT(F4,"MMMM")) -> JUNHO | C4: 88669846 | D4: 11259811 | E4: CAIXA 06/2026 | F4: 15/06/2026 | G4: ANDRE VALERIO DE PAIVA | H4: 12682517633 | I4: Enviado | K4: PEDAGIO | L4: PEDAGIO | M4: Não | N4: PEDAGIO | P4: CLARO INFRA MG | Q4: Saque VExpenses | R4: REGIONAL MG | S4: 1 | X4: BRL | Y4: 206.66 | AB4: 206.66 | AC4: Não
A5: =YEAR(F5) -> 2026 | B5: =UPPER(TEXT(F5,"MMMM")) -> MAIO | C5: 88652413 | D5: 11257472 | E5: CAIXA 05/2026 | F5: 13/05/2026 | G5: ANDRE VALERIO DE PAIVA | H5: 12682517633 | I5: Enviado | K5: PEDAGIO | L5: PEDAGIO | M5: Não | N5: PEDAGIO | P5: CLARO INFRA MG | Q5: Saque VExpenses | R5: REGIONAL MG | S5: 1 | X5: BRL | Y5: 86.34 | AB5: 86.34 | AC5: Não
A6: =YEAR(F6) -> 2026 | B6: =UPPER(TEXT(F6,"MMMM")) -> MARÇO | C6: 81828782 | D6: 10334764 | E6: CAIXA 03/2026 | F6: 31/03/2026 | G6: ANDRE VALERIO DE PAIVA | H6: 12682517633 | I6: Enviado | K6: Pedagio | L6: PEDAGIO | M6: Não | N6: Pedagio colaborador Josué | P6: CLARO INFRA MG | Q6: Saque VExpenses | R6: REGIONAL MG | S6: 1 | X6: BRL | Y6: 230.76 | AB6: 230.76 | AC6: Não
A7: =YEAR(F7) -> 2026 | B7: =UPPER(TEXT(F7,"MMMM")) -> ABRIL | C7: 81828627 | D7: 10334753 | E7: CAIXA 04/2026 | F7: 29/04/2026 | G7: ANDRE VALERIO DE PAIVA | H7: 12682517633 | I7: Enviado | K7: Pedagio Josué | L7: PEDAGIO | M7: Não | N7: Pedagio colaborador Josué | P7: CLARO INFRA MG | Q7: Saque VExpenses | R7: REGIONAL MG | S7: 1 | X7: BRL | Y7: 168.69 | AB7: 168.69 | AC7: Não
A8: =YEAR(F8) -> 2026 | B8: =UPPER(TEXT(F8,"MMMM")) -> JANEIRO | C8: 77543931 | D8: 9699938 | E8: CAIXA 01/2026 | F8: 31/01/2026 | G8: ANDRE VALERIO DE PAIVA | H8: 12682517633 | I8: Aprovado | K8: Pedagio | L8: PEDAGIO | M8: Não | N8: Pagamento de pedágio frota. | P8: CLARO INFRA MG | Q8: Saque VExpenses | R8: REGIONAL MG | S8: 1 | W8: 0 | X8: BRL | Y8: 93.05 | AB8: 93.05 | AC8: Não
A9: =YEAR(F9) -> 2025 | B9: =UPPER(TEXT(F9,"MMMM")) -> DEZEMBRO | C9: 77542579 | D9: 9638760 | E9: CAIXA 12/2025 | F9: 31/12/2025 | G9: ANDRE VALERIO DE PAIVA | H9: 12682517633 | I9: Aprovado | K9: Pedagio | L9: PEDAGIO | M9: Não | N9: PAGAMENTO DE PEDÁGIO FROTA | P9: CLARO INFRA MG | Q9: Saque VExpenses | R9: REGIONAL MG | S9: 1 | X9: BRL | Y9: 366.61 | AB9: 366.61 | AC9: Não
A10: =YEAR(F10) -> 2025 | B10: =UPPER(TEXT(F10,"MMMM")) -> DEZEMBRO | C10: 74079627 | D10: 9130073 | E10: CAIXA 11/2025 | F10: 26/12/2025 | G10: ANDRE VALERIO DE PAIVA | H10: 12682517633 | I10: Aprovado | K10: Pedagio | L10: PEDAGIO | M10: Não | N10: Pedágios pagos na região | P10: CLARO INFRA MG | Q10: Saque VExpenses | R10: REGIONAL MG | S10: 1 | X10: BRL | Y10: 312.75 | AB10: 312.75 | AC10: Não
A11: =YEAR(F11) -> 2025 | B11: =UPPER(TEXT(F11,"MMMM")) -> DEZEMBRO | C11: 74079547 | D11: 9130070 | E11: CAIXA 10/2025 | F11: 26/12/2025 | G11: ANDRE VALERIO DE PAIVA | H11: 12682517633 | I11: Aprovado | K11: Pedagio | L11: PEDAGIO | M11: Não | N11: Pedagio pagos | P11: CLARO INFRA MG | Q11: Saque VExpenses | R11: REGIONAL MG | S11: 1 | X11: BRL | Y11: 159.46 | AB11: 159.46
A12: =YEAR(F12) -> 2025 | B12: =UPPER(TEXT(F12,"MMMM")) -> SETEMBRO | C12: 74079440 | D12: 9129655 | E12: CAIXA 09/2025 | F12: 30/09/2025 | G12: ANDRE VALERIO DE PAIVA | H12: 12682517633 | I12: Aprovado | K12: Pedagio | L12: PEDAGIO | M12: Não | N12: Comprovante dos pedágios pagos | P12: CLARO INFRA MG | Q12: Saque VExpenses | R12: REGIONAL MG | S12: 1 | X12: BRL | Y12: 163.79 | AB12: 163.79
A13: =YEAR(F13) -> 2025 | B13: =UPPER(TEXT(F13,"MMMM")) -> AGOSTO | C13: 74079371 | D13: 9129144 | E13: CAIXA 08/2025 | F13: 31/08/2025 | G13: ANDRE VALERIO DE PAIVA | H13: 12682517633 | I13: Aprovado | K13: PEdagio | L13: PEDAGIO | M13: Não | N13: Notas referente ao pedagios pagos. | P13: CLARO INFRA MG | Q13: Saque VExpenses | R13: REGIONAL MG | S13: 1 | X13: BRL | Y13: 219.55 | AB13: 219.55
A14: =YEAR(F14) -> 2025 | B14: =UPPER(TEXT(F14,"MMMM")) -> JUNHO | C14: 61835966 | D14: 7607502 | E14: CAIXA 06/2025 | F14: 03/06/2025 | G14: ANDRE VALERIO DE PAIVA | H14: 12682517633 | I14: Aprovado | K14: Material aplicado preventiva gmg | L14: MATERIAL | M14: Não | N14: Material aplicado preventiva GMG | P14: CLARO INFRA MG | Q14: Saque VExpenses | R14: REGIONAL MG | S14: 1 | W14: 0 | X14: BRL | Y14: 46 | AB14: 46

Sheet FECHAMENTO
B4: FECHAMENTO DE PRESTAÇÃO DE CONTAS
B6: ANDRE VALERIO DE PAIVA
B7: Ano | C7: Mês | D7: Carga | E7: Transferência | F7: Taxa | G7: Prest. Contas | H7: Saldo | I7: Acumulado | K7: STATUS | L7: VALOR
B8: 2025 | C8: MAIO | D8: =SUMIFS(EXTRATO!I:I,EXTRATO!G:G,FECHAMENTO!$D$7,EXTRATO!B:B,FECHAMENTO!C8,EXTRATO!A:A,FECHAMENTO!B8) -> 398.47 | E8: =SUMIFS(EXTRATO!I:I,EXTRATO!G:G,FECHAMENTO!$E$7,EXTRATO!B:B,FECHAMENTO!C8,EXTRATO!A:A,FECHAMENTO!B8) -> 0 | F8: =SUMIFS(EXTRATO!I:I,EXTRATO!G:G,FECHAMENTO!$F$7,EXTRATO!B:B,FECHAMENTO!C8,EXTRATO!A:A,FECHAMENTO!B8) -> 0 | G8: =SUMIFS('PREST. CONTAS'!AB:AB,'PREST. CONTAS'!B:B,FECHAMENTO!C8,'PREST. CONTAS'!A:A,FECHAMENTO!B8,'PREST. CONTAS'!I:I,"<>Aberto",'PREST. CONTAS'!I:I,"<>Reprovado") -> 0 | H8: =D8+E8+F8-G8 -> 398.47 | I8: =H8 -> 398.47 | K8: Aberto | L8: 399.45
B9: 2025 | C9: JUNHO | D9: =SUMIFS(EXTRATO!I:I,EXTRATO!G:G,FECHAMENTO!$D$7,EXTRATO!B:B,FECHAMENTO!C9,EXTRATO!A:A,FECHAMENTO!B9) -> 47.53 | E9: =SUMIFS(EXTRATO!I:I,EXTRATO!G:G,FECHAMENTO!$E$7,EXTRATO!B:B,FECHAMENTO!C9,EXTRATO!A:A,FECHAMENTO!B9) -> 0 | F9: =SUMIFS(EXTRATO!I:I,EXTRATO!G:G,FECHAMENTO!$F$7,EXTRATO!B:B,FECHAMENTO!C9,EXTRATO!A:A,FECHAMENTO!B9) -> 0 | G9: =SUMIFS('PREST. CONTAS'!AB:AB,'PREST. CONTAS'!B:B,C9,'PREST. CONTAS'!A:A,B9,'PREST. CONTAS'!I:I,"<>Aberto",'PREST. CONTAS'!I:I,"<>Reprovado") -> 46 | H9: =D9+E9+F9-G9 -> 1.53 | I9: =H9+I8 -> 400 | K9: Aprovado | L9: 1361.21
B10: 2025 | C10: JULHO | D10: =SUMIFS(EXTRATO!I:I,EXTRATO!G:G,FECHAMENTO!$D$7,EXTRATO!B:B,FECHAMENTO!C10,EXTRATO!A:A,FECHAMENTO!B10) -> 0 | E10: =SUMIFS(EXTRATO!I:I,EXTRATO!G:G,FECHAMENTO!$E$7,EXTRATO!B:B,FECHAMENTO!C10,EXTRATO!A:A,FECHAMENTO!B10) -> 0 | F10: =SUMIFS(EXTRATO!I:I,EXTRATO!G:G,FECHAMENTO!$F$7,EXTRATO!B:B,FECHAMENTO!C10,EXTRATO!A:A,FECHAMENTO!B10) -> -7 | G10: =SUMIFS('PREST. CONTAS'!AB:AB,'PREST. CONTAS'!B:B,C10,'PREST. CONTAS'!A:A,B10,'PREST. CONTAS'!I:I,"<>Aberto",'PREST. CONTAS'!I:I,"<>Reprovado") -> 0 | H10: =D10+E10+F10-G10 -> -7 | I10: =H10+I9 -> 393 | K10: Total Geral | L10: 1760.66
B11: 2025 | C11: AGOSTO | D11: =SUMIFS(EXTRATO!I:I,EXTRATO!G:G,FECHAMENTO!$D$7,EXTRATO!B:B,FECHAMENTO!C11,EXTRATO!A:A,FECHAMENTO!B11) -> 14 | E11: =SUMIFS(EXTRATO!I:I,EXTRATO!G:G,FECHAMENTO!$E$7,EXTRATO!B:B,FECHAMENTO!C11,EXTRATO!A:A,FECHAMENTO!B11) -> 0 | F11: =SUMIFS(EXTRATO!I:I,EXTRATO!G:G,FECHAMENTO!$F$7,EXTRATO!B:B,FECHAMENTO!C11,EXTRATO!A:A,FECHAMENTO!B11) -> 0 | G11: =SUMIFS('PREST. CONTAS'!AB:AB,'PREST. CONTAS'!B:B,C11,'PREST. CONTAS'!A:A,B11,'PREST. CONTAS'!I:I,"<>Aberto",'PREST. CONTAS'!I:I,"<>Reprovado") -> 219.55 | H11: =D11+E11+F11-G11 -> -205.55 | I11: =H11+I10 -> 187.45
B12: 2025 | C12: SETEMBRO | D12: =SUMIFS(EXTRATO!I:I,EXTRATO!G:G,FECHAMENTO!$D$7,EXTRATO!B:B,FECHAMENTO!C12,EXTRATO!A:A,FECHAMENTO!B12) -> 0 | E12: =SUMIFS(EXTRATO!I:I,EXTRATO!G:G,FECHAMENTO!$E$7,EXTRATO!B:B,FECHAMENTO!C12,EXTRATO!A:A,FECHAMENTO!B12) -> 0 | F12: =SUMIFS(EXTRATO!I:I,EXTRATO!G:G,FECHAMENTO!$F$7,EXTRATO!B:B,FECHAMENTO!C12,EXTRATO!A:A,FECHAMENTO!B12) -> 0 | G12: =SUMIFS('PREST. CONTAS'!AB:AB,'PREST. CONTAS'!B:B,C12,'PREST. CONTAS'!A:A,B12,'PREST. CONTAS'!I:I,"<>Aberto",'PREST. CONTAS'!I:I,"<>Reprovado") -> 163.79 | H12: =D12+E12+F12-G12 -> -163.79 | I12: =H12+I11 -> 23.66
B13: 2025 | C13: OUTUBRO | D13: =SUMIFS(EXTRATO!I:I,EXTRATO!G:G,FECHAMENTO!$D$7,EXTRATO!B:B,FECHAMENTO!C13,EXTRATO!A:A,FECHAMENTO!B13) -> 0 | E13: =SUMIFS(EXTRATO!I:I,EXTRATO!G:G,FECHAMENTO!$E$7,EXTRATO!B:B,FECHAMENTO!C13,EXTRATO!A:A,FECHAMENTO!B13) -> 0 | F13: =SUMIFS(EXTRATO!I:I,EXTRATO!G:G,FECHAMENTO!$F$7,EXTRATO!B:B,FECHAMENTO!C13,EXTRATO!A:A,FECHAMENTO!B13) -> 0 | G13: =SUMIFS('PREST. CONTAS'!AB:AB,'PREST. CONTAS'!B:B,C13,'PREST. CONTAS'!A:A,B13,'PREST. CONTAS'!I:I,"<>Aberto",'PREST. CONTAS'!I:I,"<>Reprovado") -> 0 | H13: =D13+E13+F13-G13 -> 0 | I13: =H13+I12 -> 23.66
B14: 2025 | C14: NOVEMBRO | D14: =SUMIFS(EXTRATO!I:I,EXTRATO!G:G,FECHAMENTO!$D$7,EXTRATO!B:B,FECHAMENTO!C14,EXTRATO!A:A,FECHAMENTO!B14) -> 0 | E14: =SUMIFS(EXTRATO!I:I,EXTRATO!G:G,FECHAMENTO!$E$7,EXTRATO!B:B,FECHAMENTO!C14,EXTRATO!A:A,FECHAMENTO!B14) -> 0 | F14: =SUMIFS(EXTRATO!I:I,EXTRATO!G:G,FECHAMENTO!$F$7,EXTRATO!B:B,FECHAMENTO!C14,EXTRATO!A:A,FECHAMENTO!B14) -> 0 | G14: =SUMIFS('PREST. CONTAS'!AB:AB,'PREST. CONTAS'!B:B,C14,'PREST. CONTAS'!A:A,B14,'PREST. CONTAS'!I:I,"<>Aberto",'PREST. CONTAS'!I:I,"<>Reprovado") -> 0 | H14: =D14+E14+F14-G14 -> 0 | I14: =H14+I13 -> 23.66
B15: 2025 | C15: DEZEMBRO | D15: =SUMIFS(EXTRATO!I:I,EXTRATO!G:G,FECHAMENTO!$D$7,EXTRATO!B:B,FECHAMENTO!C15,EXTRATO!A:A,FECHAMENTO!B15) -> 0 | E15: =SUMIFS(EXTRATO!I:I,EXTRATO!G:G,FECHAMENTO!$E$7,EXTRATO!B:B,FECHAMENTO!C15,EXTRATO!A:A,FECHAMENTO!B15) -> 0 | F15: =SUMIFS(EXTRATO!I:I,EXTRATO!G:G,FECHAMENTO!$F$7,EXTRATO!B:B,FECHAMENTO!C15,EXTRATO!A:A,FECHAMENTO!B15) -> 0 | G15: =SUMIFS('PREST. CONTAS'!AB:AB,'PREST. CONTAS'!B:B,C15,'PREST. CONTAS'!A:A,B15,'PREST. CONTAS'!I:I,"<>Aberto",'PREST. CONTAS'!I:I,"<>Reprovado") -> 838.82 | H15: =D15+E15+F15-G15 -> -838.82 | I15: =H15+I14 -> -815.16
B16: 2026 | C16: JANEIRO | D16: =SUMIFS(EXTRATO!I:I,EXTRATO!G:G,FECHAMENTO!$D$7,EXTRATO!B:B,FECHAMENTO!C16,EXTRATO!A:A,FECHAMENTO!B16) -> 985.05 | E16: =SUMIFS(EXTRATO!I:I,EXTRATO!G:G,FECHAMENTO!$E$7,EXTRATO!B:B,FECHAMENTO!C16,EXTRATO!A:A,FECHAMENTO!B16) -> -311.05 | F16: =SUMIFS(EXTRATO!I:I,EXTRATO!G:G,FECHAMENTO!$F$7,EXTRATO!B:B,FECHAMENTO!C16,EXTRATO!A:A,FECHAMENTO!B16) -> -14 | G16: =SUMIFS('PREST. CONTAS'!AB:AB,'PREST. CONTAS'!B:B,C16,'PREST. CONTAS'!A:A,B16,'PREST. CONTAS'!I:I,"<>Aberto",'PREST. CONTAS'!I:I,"<>Reprovado") -> 93.05 | H16: =D16+E16+F16-G16 -> 566.95 | I16: =H16+I15 -> -248.21
B17: 2026 | C17: FEVEREIRO | D17: =SUMIFS(EXTRATO!I:I,EXTRATO!G:G,FECHAMENTO!$D$7,EXTRATO!B:B,FECHAMENTO!C17,EXTRATO!A:A,FECHAMENTO!B17) -> 377.1 | E17: =SUMIFS(EXTRATO!I:I,EXTRATO!G:G,FECHAMENTO!$E$7,EXTRATO!B:B,FECHAMENTO!C17,EXTRATO!A:A,FECHAMENTO!B17) -> 0 | F17: =SUMIFS(EXTRATO!I:I,EXTRATO!G:G,FECHAMENTO!$F$7,EXTRATO!B:B,FECHAMENTO!C17,EXTRATO!A:A,FECHAMENTO!B17) -> 0 | G17: =SUMIFS('PREST. CONTAS'!AB:AB,'PREST. CONTAS'!B:B,C17,'PREST. CONTAS'!A:A,B17,'PREST. CONTAS'!I:I,"<>Aberto",'PREST. CONTAS'!I:I,"<>Reprovado") -> 0 | H17: =D17+E17+F17-G17 -> 377.1 | I17: =H17+I16 -> 128.89
B18: 2026 | C18: MARÇO | D18: =SUMIFS(EXTRATO!I:I,EXTRATO!G:G,FECHAMENTO!$D$7,EXTRATO!B:B,FECHAMENTO!C18,EXTRATO!A:A,FECHAMENTO!B18) -> 278.11 | E18: =SUMIFS(EXTRATO!I:I,EXTRATO!G:G,FECHAMENTO!$E$7,EXTRATO!B:B,FECHAMENTO!C18,EXTRATO!A:A,FECHAMENTO!B18) -> 0 | F18: =SUMIFS(EXTRATO!I:I,EXTRATO!G:G,FECHAMENTO!$F$7,EXTRATO!B:B,FECHAMENTO!C18,EXTRATO!A:A,FECHAMENTO!B18) -> -14 | G18: =SUMIFS('PREST. CONTAS'!AB:AB,'PREST. CONTAS'!B:B,C18,'PREST. CONTAS'!A:A,B18,'PREST. CONTAS'!I:I,"<>Aberto",'PREST. CONTAS'!I:I,"<>Reprovado") -> 230.76 | H18: =D18+E18+F18-G18 -> 33.35 | I18: =H18+I17 -> 162.24
B19: 2026 | C19: ABRIL | D19: =SUMIFS(EXTRATO!I:I,EXTRATO!G:G,FECHAMENTO!$D$7,EXTRATO!B:B,FECHAMENTO!C19,EXTRATO!A:A,FECHAMENTO!B19) -> 25.21 | E19: =SUMIFS(EXTRATO!I:I,EXTRATO!G:G,FECHAMENTO!$E$7,EXTRATO!B:B,FECHAMENTO!C19,EXTRATO!A:A,FECHAMENTO!B19) -> -11.21 | F19: =SUMIFS(EXTRATO!I:I,EXTRATO!G:G,FECHAMENTO!$F$7,EXTRATO!B:B,FECHAMENTO!C19,EXTRATO!A:A,FECHAMENTO!B19) -> 0 | G19: =SUMIFS('PREST. CONTAS'!AB:AB,'PREST. CONTAS'!B:B,C19,'PREST. CONTAS'!A:A,B19,'PREST. CONTAS'!I:I,"<>Aberto",'PREST. CONTAS'!I:I,"<>Reprovado") -> 168.69 | H19: =D19+E19+F19-G19 -> -154.69 | I19: =H19+I18 -> 7.55
B20: 2026 | C20: MAIO | D20: =SUMIFS(EXTRATO!I:I,EXTRATO!G:G,FECHAMENTO!$D$7,EXTRATO!B:B,FECHAMENTO!C20,EXTRATO!A:A,FECHAMENTO!B20) -> 786.9 | E20: =SUMIFS(EXTRATO!I:I,EXTRATO!G:G,FECHAMENTO!$E$7,EXTRATO!B:B,FECHAMENTO!C20,EXTRATO!A:A,FECHAMENTO!B20) -> -1.56 | F20: =SUMIFS(EXTRATO!I:I,EXTRATO!G:G,FECHAMENTO!$F$7,EXTRATO!B:B,FECHAMENTO!C20,EXTRATO!A:A,FECHAMENTO!B20) -> -11.43 | G20: =SUMIFS('PREST. CONTAS'!AB:AB,'PREST. CONTAS'!B:B,C20,'PREST. CONTAS'!A:A,B20,'PREST. CONTAS'!I:I,"<>Aberto",'PREST. CONTAS'!I:I,"<>Reprovado") -> 86.34 | H20: =D20+E20+F20-G20 -> 687.57 | I20: =H20+I19 -> 695.12
B21: 2026 | C21: JUNHO | D21: =SUMIFS(EXTRATO!I:I,EXTRATO!G:G,FECHAMENTO!$D$7,EXTRATO!B:B,FECHAMENTO!C21,EXTRATO!A:A,FECHAMENTO!B21) -> 0 | E21: =SUMIFS(EXTRATO!I:I,EXTRATO!G:G,FECHAMENTO!$E$7,EXTRATO!B:B,FECHAMENTO!C21,EXTRATO!A:A,FECHAMENTO!B21) -> 0 | F21: =SUMIFS(EXTRATO!I:I,EXTRATO!G:G,FECHAMENTO!$F$7,EXTRATO!B:B,FECHAMENTO!C21,EXTRATO!A:A,FECHAMENTO!B21) -> 0 | G21: =SUMIFS('PREST. CONTAS'!AB:AB,'PREST. CONTAS'!B:B,C21,'PREST. CONTAS'!A:A,B21,'PREST. CONTAS'!I:I,"<>Aberto",'PREST. CONTAS'!I:I,"<>Reprovado") -> 206.66 | H21: =D21+E21+F21-G21 -> -206.66 | I21: =H21+I20 -> 488.46
B22: 2026 | C22: JULHO | D22: =SUMIFS(EXTRATO!I:I,EXTRATO!G:G,FECHAMENTO!$D$7,EXTRATO!B:B,FECHAMENTO!C22,EXTRATO!A:A,FECHAMENTO!B22) -> 0 | E22: =SUMIFS(EXTRATO!I:I,EXTRATO!G:G,FECHAMENTO!$E$7,EXTRATO!B:B,FECHAMENTO!C22,EXTRATO!A:A,FECHAMENTO!B22) -> 0 | F22: =SUMIFS(EXTRATO!I:I,EXTRATO!G:G,FECHAMENTO!$F$7,EXTRATO!B:B,FECHAMENTO!C22,EXTRATO!A:A,FECHAMENTO!B22) -> 0 | G22: =SUMIFS('PREST. CONTAS'!AB:AB,'PREST. CONTAS'!B:B,C22,'PREST. CONTAS'!A:A,B22,'PREST. CONTAS'!I:I,"<>Aberto",'PREST. CONTAS'!I:I,"<>Reprovado") -> 81.83 | H22: =D22+E22+F22-G22 -> -81.83 | I22: =H22+I21 -> 406.63
D23: =SUM(D8:D22) -> 2912.37 | E23: =SUM(E8:E22) -> -323.82 | F23: =SUM(F8:F22) -> -46.43 | G23: =SUM(G8:G22) -> 2135.49 | H23: =SUM(H8:H22) -> 406.63
B25: SALDO FINAL | H25: =H23 -> 406.63 | K25: LEGENDA SINAIS
B26: (+) SALDO DISPONIVEL | H26: =D23+E23+F23 -> 2542.12 | K26: NEGATIVO | L26: A REEMBOLSAR
B27: (-) PRESTAÇÃO DE CONTAS | H27: =G23 -> 2135.49 | K27: POSITIVO | L27: A PRESTAR
B28: = FECHAMENTO PRESTE CONTAS | H28: =H26-H27 -> 406.63 | K28: EM AMARELO | L28: O VALOR PODE SER ALTERADO
B29: = SALDO CARTÃO | H29: 0 | K29: EM VERMELHO | L29: CAIXA REPROVADO
B30: FECHAMENTO FINAL - SALDO PENDENTE | H30: =H28-H29 -> 406.63 | K30: EM VERDE | L30: CAIXA APROVADO
